Workbook

Sheet Leia-me
A1: Kodoo — guia do roadmap revisado
A3: Princípio | B3: Roadmap alinhado às fases do repositório bootstrapprx/kodoo, separado do inventário legado de telas/funções.
A4: Fonte de verdade | B4: context/roadmap.md define F0–F6 e A1; context/domain-app-migration.md e context/application-architecture.md refinam o estado contábil e as aplicações.
A5: Como usar | B5: Comece pela aba Roadmap. Mude Estado inicial/Estado atual apenas após conferir código, testes e documentação. Registre evidências clicáveis ou comandos reproduzíveis.
A6: Importante | B6: Os status da planilha original não foram confirmados contra o código; foram preservados como dados legados e rotulados explicitamente como não verificados.
A7: Fases | B7: A aba Fases contém a taxonomia do repositório. F0–F6 não devem ser interpretadas como as fases antigas da planilha.
A8: Inventário — Telas | B8: O catálogo original foi preservado. A coluna Fase catálogo antigo mantém o valor anterior; preencha Fase Kodoo (reclassificar) após análise individual.
A9: Inventário — Funções | B9: O catálogo original foi preservado. A coluna Fase catálogo antigo mantém o valor anterior; preencha Fase Kodoo (reclassificar) após análise individual.
A10: Gates de aceite | B10: Checklist transversal de definição de pronto. Aplique por capacidade e marque N/A com justificativa quando uma superfície não se aplicar.
A11: Auditoria | B11: Registra os principais riscos de planejamento encontrados ao comparar a planilha com a documentação do repositório.
A12: Limite desta versão | B12: É uma revisão documental, não uma auditoria completa de cada linha de código. Estados iniciais são hipóteses baseadas nos documentos consultados; valide contra o HEAD atual.
A13: Repositório | B13: https://github.com/bootstrapprx/kodoo
A14: Documentos principais | B14: https://github.com/bootstrapprx/kodoo/blob/main/context/roadmap.md
... A27: Health (inventários) | B27: ⚠ lacuna de evidência/código · ◐ proprietário pendente · ○ sem relações em Dependencies · ✔ OK.

Sheet Painel
A1: Kodoo — painel de acompanhamento
A2: Tudo aqui é calculado por fórmulas a partir das outras abas — não edite o Painel. Atualize Current Status (Roadmap), Implementation Status (definições), Dependencies e Gates; os números e gráficos acompanham.
A4: ITENS DO ROADMAP | B4: % ROADMAP CONCLUÍDO | D4: P0 AINDA ABERTOS | F4: GATES DE ACEITE ATENDIDOS | H4: Como ler • Roadmap, gates e definições começam em "A validar"/"Planned": é um estado honesto, não uma falha. • Sem prova (código, teste, CI) o status não sobe. • Alertas ⚠ aparecem nos inventários (coluna Health).
A5: =COUNTA(Roadmap!$A$6:$A$200) | B5: =IFERROR(COUNTIF(Roadmap!$M$6:$M$200,"Concluído")/(COUNTA(Roadmap!$A$6:$A$200)-COUNTIF(Roadmap!$M$6:$M$200,"Não se aplica")),0) | D5: =COUNTIFS(Roadmap!$F$6:$F$200,"P0",Roadmap!$M$6:$M$200,"<>Concluído") | F5: =IFERROR(COUNTIF('Gates de aceite'!$E$6:$E$18,"Concluído")/(COUNTA('Gates de aceite'!$E$6:$E$18)-COUNTIF('Gates de aceite'!$E$6:$E$18,"Não se aplica")),0)
A6: =COUNTIF(Roadmap!$M$6:$M$200,"Concluído")&" concluídos" | B6: =COUNTIF(Roadmap!$M$6:$M$200,"Em andamento")&" em andamento" | D6: ="de "&COUNTIF(Roadmap!$F$6:$F$200,"P0")&" itens P0" | F6: =COUNTIF('Gates de aceite'!$E$6:$E$18,"Concluído")&" de "&COUNTA('Gates de aceite'!$E$6:$E$18)&" gates"
A8: DEFINIÇÕES CATALOGADAS | B8: % IMPLEMENTADAS / VERIFICADAS | D8: DECISÕES ABERTAS | F8: ALERTAS DE INTEGRIDADE
A9: =COUNTA('Constants & Enums'!$A$5:$A$200)+COUNTA('Metrics & Formulas'!$A$5:$A$200)+COUNTA('Projections & Dashboards'!$A$5:$A$200) | B9: =IFERROR((COUNTIF('Constants & Enums'!$I$5:$I$200,"Implemented")+COUNTIF('Metrics & Formulas'!$I$5:$I$200,"Implemented")+COUNTIF('Projections & Dashboards'!$I$5:$I$200,"Implemented")+COUNTIF('Constants & Enums'!$I$5:$I$200,"Verified")+COUNTIF('Metrics & Formulas'!$I$5:$I$200,"Verified")+COUNTIF('Projections & Dashboards'!$I$5:$I$200,"Verified"))/(COUNTA('Constants & Enums'!$A$5:$A$200)+COUNTA('Metrics & Formulas'!$A$5:$A$200)+COUNTA('Projections & Dashboards'!$A$5:$A$200)),0) | D9: =COUNTIF('Decisões pendentes'!$H$5:$H$104,"Aberta") | F9: =COUNTIF(Dependencies!$I$5:$I$300,"✖*")+COUNTIF('Constants & Enums'!$T$5:$T$200,"⚠*")+COUNTIF('Metrics & Formulas'!$T$5:$T$200,"⚠*")+COUNTIF('Projections & Dashboards'!$T$5:$T$200,"⚠*")
A10: ="constantes, métricas, projeções e dashboards" | B10: ="Verified: "&(COUNTIF('Constants & Enums'!$I$5:$I$200,"Verified")+COUNTIF('Metrics & Formulas'!$I$5:$I$200,"Verified")+COUNTIF('Projections & Dashboards'!$I$5:$I$200,"Verified")) | D10: ="proprietários / localização pendentes" | F10: ="IDs inexistentes, sem link ou sem evidência"
A12: 1 · Roadmap por fase e estado | M12: 2 · Gates de aceite por estado
A13: Fase | B13: A validar | C13: Não iniciado | D13: Em andamento | E13: Parcial | F13: Concluído | G13: Bloqueado | H13: Não se aplica | I13: Total | J13: % concluído | M13: Estado | N13: Gates | O13: %
A14: F0 | B14: =COUNTIFS(Roadmap!$B$6:$B$200,$A14,Roadmap!$M$6:$M$200,B$13) | C14: =COUNTIFS(Roadmap!$B$6:$B$200,$A14,Roadmap!$M$6:$M$200,C$13) | D14: =COUNTIFS(Roadmap!$B$6:$B$200,$A14,Roadmap!$M$6:$M$200,D$13) | E14: =COUNTIFS(Roadmap!$B$6:$B$200,$A14,Roadmap!$M$6:$M$200,E$13) | F14: =COUNTIFS(Roadmap!$B$6:$B$200,$A14,Roadmap!$M$6:$M$200,F$13) | G14: =COUNTIFS(Roadmap!$B$6:$B$200,$A14,Roadmap!$M$6:$M$200,G$13) | H14: =COUNTIFS(Roadmap!$B$6:$B$200,$A14,Roadmap!$M$6:$M$200,H$13) | I14: =SUM(B14:H14) | J14: =IFERROR(F14/(I14-H14),0) | M14: A validar | N14: =COUNTIF('Gates de aceite'!$E$6:$E$18,M14) | O14: =IFERROR(N14/N$20,0)
A15: F1 | B15: =COUNTIFS(Roadmap!$B$6:$B$200,$A15,Roadmap!$M$6:$M$200,B$13) | C15: =COUNTIFS(Roadmap!$B$6:$B$200,$A15,Roadmap!$M$6:$M$200,C$13) | D15: =COUNTIFS(Roadmap!$B$6:$B$200,$A15,Roadmap!$M$6:$M$200,D$13) | E15: =COUNTIFS(Roadmap!$B$6:$B$200,$A15,Roadmap!$M$6:$M$200,E$13) | F15: =COUNTIFS(Roadmap!$B$6:$B$200,$A15,Roadmap!$M$6:$M$200,F$13) | G15: =COUNTIFS(Roadmap!$B$6:$B$200,$A15,Roadmap!$M$6:$M$200,G$13) | H15: =COUNTIFS(Roadmap!$B$6:$B$200,$A15,Roadmap!$M$6:$M$200,H$13) | I15: =SUM(B15:H15) | J15: =IFERROR(F15/(I15-H15),0) | M15: Não iniciado | N15: =COUNTIF('Gates de aceite'!$E$6:$E$18,M15) | O15: =IFERROR(N15/N$20,0)
A16: F2 | B16: =COUNTIFS(Roadmap!$B$6:$B$200,$A16,Roadmap!$M$6:$M$200,B$13) | C16: =COUNTIFS(Roadmap!$B$6:$B$200,$A16,Roadmap!$M$6:$M$200,C$13) | D16: =COUNTIFS(Roadmap!$B$6:$B$200,$A16,Roadmap!$M$6:$M$200,D$13) | E16: =COUNTIFS(Roadmap!$B$6:$B$200,$A16,Roadmap!$M$6:$M$200,E$13) | F16: =COUNTIFS(Roadmap!$B$6:$B$200,$A16,Roadmap!$M$6:$M$200,F$13) | G16: =COUNTIFS(Roadmap!$B$6:$B$200,$A16,Roadmap!$M$6:$M$200,G$13) | H16: =COUNTIFS(Roadmap!$B$6:$B$200,$A16,Roadmap!$M$6:$M$200,H$13) | I16: =SUM(B16:H16) | J16: =IFERROR(F16/(I16-H16),0) | M16: Em andamento | N16: =COUNTIF('Gates de aceite'!$E$6:$E$18,M16) | O16: =IFERROR(N16/N$20,0)
A17: F3 | B17: =COUNTIFS(Roadmap!$B$6:$B$200,$A17,Roadmap!$M$6:$M$200,B$13) | C17: =COUNTIFS(Roadmap!$B$6:$B$200,$A17,Roadmap!$M$6:$M$200,C$13) | D17: =COUNTIFS(Roadmap!$B$6:$B$200,$A17,Roadmap!$M$6:$M$200,D$13) | E17: =COUNTIFS(Roadmap!$B$6:$B$200,$A17,Roadmap!$M$6:$M$200,E$13) | F17: =COUNTIFS(Roadmap!$B$6:$B$200,$A17,Roadmap!$M$6:$M$200,F$13) | G17: =COUNTIFS(Roadmap!$B$6:$B$200,$A17,Roadmap!$M$6:$M$200,G$13) | H17: =COUNTIFS(Roadmap!$B$6:$B$200,$A17,Roadmap!$M$6:$M$200,H$13) | I17: =SUM(B17:H17) | J17: =IFERROR(F17/(I17-H17),0) | M17: Concluído | N17: =COUNTIF('Gates de aceite'!$E$6:$E$18,M17) | O17: =IFERROR(N17/N$20,0)
A18: F4 | B18: =COUNTIFS(Roadmap!$B$6:$B$200,$A18,Roadmap!$M$6:$M$200,B$13) | C18: =COUNTIFS(Roadmap!$B$6:$B$200,$A18,Roadmap!$M$6:$M$200,C$13) | D18: =COUNTIFS(Roadmap!$B$6:$B$200,$A18,Roadmap!$M$6:$M$200,D$13) | E18: =COUNTIFS(Roadmap!$B$6:$B$200,$A18,Roadmap!$M$6:$M$200,E$13) | F18: =COUNTIFS(Roadmap!$B$6:$B$200,$A18,Roadmap!$M$6:$M$200,F$13) | G18: =COUNTIFS(Roadmap!$B$6:$B$200,$A18,Roadmap!$M$6:$M$200,G$13) | H18: =COUNTIFS(Roadmap!$B$6:$B$200,$A18,Roadmap!$M$6:$M$200,H$13) | I18: =SUM(B18:H18) | J18: =IFERROR(F18/(I18-H18),0) | M18: Bloqueado | N18: =COUNTIF('Gates de aceite'!$E$6:$E$18,M18) | O18: =IFERROR(N18/N$20,0)
A19: F5 | B19: =COUNTIFS(Roadmap!$B$6:$B$200,$A19,Roadmap!$M$6:$M$200,B$13) | C19: =COUNTIFS(Roadmap!$B$6:$B$200,$A19,Roadmap!$M$6:$M$200,C$13) | D19: =COUNTIFS(Roadmap!$B$6:$B$200,$A19,Roadmap!$M$6:$M$200,D$13) | E19: =COUNTIFS(Roadmap!$B$6:$B$200,$A19,Roadmap!$M$6:$M$200,E$13) | F19: =COUNTIFS(Roadmap!$B$6:$B$200,$A19,Roadmap!$M$6:$M$200,F$13) | G19: =COUNTIFS(Roadmap!$B$6:$B$200,$A19,Roadmap!$M$6:$M$200,G$13) | H19: =COUNTIFS(Roadmap!$B$6:$B$200,$A19,Roadmap!$M$6:$M$200,H$13) | I19: =SUM(B19:H19) | J19: =IFERROR(F19/(I19-H19),0) | M19: Não se aplica | N19: =COUNTIF('Gates de aceite'!$E$6:$E$18,M19) | O19: =IFERROR(N19/N$20,0)
A20: F6 | B20: =COUNTIFS(Roadmap!$B$6:$B$200,$A20,Roadmap!$M$6:$M$200,B$13) | C20: =COUNTIFS(Roadmap!$B$6:$B$200,$A20,Roadmap!$M$6:$M$200,C$13) | D20: =COUNTIFS(Roadmap!$B$6:$B$200,$A20,Roadmap!$M$6:$M$200,D$13) | E20: =COUNTIFS(Roadmap!$B$6:$B$200,$A20,Roadmap!$M$6:$M$200,E$13) | F20: =COUNTIFS(Roadmap!$B$6:$B$200,$A20,Roadmap!$M$6:$M$200,F$13) | G20: =COUNTIFS(Roadmap!$B$6:$B$200,$A20,Roadmap!$M$6:$M$200,G$13) | H20: =COUNTIFS(Roadmap!$B$6:$B$200,$A20,Roadmap!$M$6:$M$200,H$13) | I20: =SUM(B20:H20) | J20: =IFERROR(F20/(I20-H20),0) | M20: Total | N20: =SUM(N14:N19) | O20: =SUM(O14:O19)
A21: A1 | B21: =COUNTIFS(Roadmap!$B$6:$B$200,$A21,Roadmap!$M$6:$M$200,B$13) | C21: =COUNTIFS(Roadmap!$B$6:$B$200,$A21,Roadmap!$M$6:$M$200,C$13) | D21: =COUNTIFS(Roadmap!$B$6:$B$200,$A21,Roadmap!$M$6:$M$200,D$13) | E21: =COUNTIFS(Roadmap!$B$6:$B$200,$A21,Roadmap!$M$6:$M$200,E$13) | F21: =COUNTIFS(Roadmap!$B$6:$B$200,$A21,Roadmap!$M$6:$M$200,F$13) | G21: =COUNTIFS(Roadmap!$B$6:$B$200,$A21,Roadmap!$M$6:$M$200,G$13) | H21: =COUNTIFS(Roadmap!$B$6:$B$200,$A21,Roadmap!$M$6:$M$200,H$13) | I21: =SUM(B21:H21) | J21: =IFERROR(F21/(I21-H21),0)
A22: Transversal | B22: =COUNTIFS(Roadmap!$B$6:$B$200,$A22,Roadmap!$M$6:$M$200,B$13) | C22: =COUNTIFS(Roadmap!$B$6:$B$200,$A22,Roadmap!$M$6:$M$200,C$13) | D22: =COUNTIFS(Roadmap!$B$6:$B$200,$A22,Roadmap!$M$6:$M$200,D$13) | E22: =COUNTIFS(Roadmap!$B$6:$B$200,$A22,Roadmap!$M$6:$M$200,E$13) | F22: =COUNTIFS(Roadmap!$B$6:$B$200,$A22,Roadmap!$M$6:$M$200,F$13) | G22: =COUNTIFS(Roadmap!$B$6:$B$200,$A22,Roadmap!$M$6:$M$200,G$13) | H22: =COUNTIFS(Roadmap!$B$6:$B$200,$A22,Roadmap!$M$6:$M$200,H$13) | I22: =SUM(B22:H22) | J22: =IFERROR(F22/(I22-H22),0)
A23: Total | B23: =SUM(B14:B22) | C23: =SUM(C14:C22) | D23: =SUM(D14:D22) | E23: =SUM(E14:E22) | F23: =SUM(F14:F22) | G23: =SUM(G14:G22) | H23: =SUM(H14:H22) | I23: =SUM(I14:I22) | J23: =IFERROR(F23/(I23-H23),0)
A44: 3 · Definições por tipo e status de implementação | M44: 4 · Definições por módulo pai
A45: Tipo | B45: Planned | C45: Partial | D45: Implemented | E45: Verified | F45: Total | G45: % impl./verif. | M45: Módulo pai | N45: Constants & Enums | O45: Metrics & Formulas | P45: Projections & Dashboards | Q45: Total
A46: DomainConstant | B46: =COUNTIFS('Constants & Enums'!$C$5:$C$200,$A46,'Constants & Enums'!$I$5:$I$200,B$45)+COUNTIFS('Metrics & Formulas'!$C$5:$C$200,$A46,'Metrics & Formulas'!$I$5:$I$200,B$45)+COUNTIFS('Projections & Dashboards'!$C$5:$C$200,$A46,'Projections & Dashboards'!$I$5:$I$200,B$45) | C46: =COUNTIFS('Constants & Enums'!$C$5:$C$200,$A46,'Constants & Enums'!$I$5:$I$200,C$45)+COUNTIFS('Metrics & Formulas'!$C$5:$C$200,$A46,'Metrics & Formulas'!$I$5:$I$200,C$45)+COUNTIFS('Projections & Dashboards'!$C$5:$C$200,$A46,'Projections & Dashboards'!$I$5:$I$200,C$45) | D46: =COUNTIFS('Constants & Enums'!$C$5:$C$200,$A46,'Constants & Enums'!$I$5:$I$200,D$45)+COUNTIFS('Metrics & Formulas'!$C$5:$C$200,$A46,'Metrics & Formulas'!$I$5:$I$200,D$45)+COUNTIFS('Projections & Dashboards'!$C$5:$C$200,$A46,'Projections & Dashboards'!$I$5:$I$200,D$45) | E46: =COUNTIFS('Constants & Enums'!$C$5:$C$200,$A46,'Constants & Enums'!$I$5:$I$200,E$45)+COUNTIFS('Metrics & Formulas'!$C$5:$C$200,$A46,'Metrics & Formulas'!$I$5:$I$200,E$45)+COUNTIFS('Projections & Dashboards'!$C$5:$C$200,$A46,'Projections & Dashboards'!$I$5:$I$200,E$45) | F46: =SUM(B46:E46) | G46: =IFERROR((D46+E46)/F46,0) | M46: =Listas!P5 | N46: =COUNTIF('Constants & Enums'!$D$5:$D$200,$M46) | O46: =COUNTIF('Metrics & Formulas'!$D$5:$D$200,$M46) | P46: =COUNTIF('Projections & Dashboards'!$D$5:$D$200,$M46) | Q46: =SUM(N46:P46)
A47: Enum | B47: =COUNTIFS('Constants & Enums'!$C$5:$C$200,$A47,'Constants & Enums'!$I$5:$I$200,B$45)+COUNTIFS('Metrics & Formulas'!$C$5:$C$200,$A47,'Metrics & Formulas'!$I$5:$I$200,B$45)+COUNTIFS('Projections & Dashboards'!$C$5:$C$200,$A47,'Projections & Dashboards'!$I$5:$I$200,B$45) | C47: =COUNTIFS('Constants & Enums'!$C$5:$C$200,$A47,'Constants & Enums'!$I$5:$I$200,C$45)+COUNTIFS('Metrics & Formulas'!$C$5:$C$200,$A47,'Metrics & Formulas'!$I$5:$I$200,C$45)+COUNTIFS('Projections & Dashboards'!$C$5:$C$200,$A47,'Projections & Dashboards'!$I$5:$I$200,C$45) | D47: =COUNTIFS('Constants & Enums'!$C$5:$C$200,$A47,'Constants & Enums'!$I$5:$I$200,D$45)+COUNTIFS('Metrics & Formulas'!$C$5:$C$200,$A47,'Metrics & Formulas'!$I$5:$I$200,D$45)+COUNTIFS('Projections & Dashboards'!$C$5:$C$200,$A47,'Projections & Dashboards'!$I$5:$I$200,D$45) | E47: =COUNTIFS('Constants & Enums'!$C$5:$C$200,$A47,'Constants & Enums'!$I$5:$I$200,E$45)+COUNTIFS('Metrics & Formulas'!$C$5:$C$200,$A47,'Metrics & Formulas'!$I$5:$I$200,E$45)+COUNTIFS('Projections & Dashboards'!$C$5:$C$200,$A47,'Projections & Dashboards'!$I$5:$I$200,E$45) | F47: =SUM(B47:E47) | G47: =IFERROR((D47+E47)/F47,0) | M47: =Listas!P6 | N47: =COUNTIF('Constants & Enums'!$D$5:$D$200,$M47) | O47: =COUNTIF('Metrics & Formulas'!$D$5:$D$200,$M47) | P47: =COUNTIF('Projections & Dashboards'!$D$5:$D$200,$M47) | Q47: =SUM(N47:P47)
A48: Policy | B48: =COUNTIFS('Constants & Enums'!$C$5:$C$200,$A48,'Constants & Enums'!$I$5:$I$200,B$45)+COUNTIFS('Metrics & Formulas'!$C$5:$C$200,$A48,'Metrics & Formulas'!$I$5:$I$200,B$45)+COUNTIFS('Projections & Dashboards'!$C$5:$C$200,$A48,'Projections & Dashboards'!$I$5:$I$200,B$45) | C48: =COUNTIFS('Constants & Enums'!$C$5:$C$200,$A48,'Constants & Enums'!$I$5:$I$200,C$45)+COUNTIFS('Metrics & Formulas'!$C$5:$C$200,$A48,'Metrics & Formulas'!$I$5:$I$200,C$45)+COUNTIFS('Projections & Dashboards'!$C$5:$C$200,$A48,'Projections & Dashboards'!$I$5:$I$200,C$45) | D48: =COUNTIFS('Constants & Enums'!$C$5:$C$200,$A48,'Constants & Enums'!$I$5:$I$200,D$45)+COUNTIFS('Metrics & Formulas'!$C$5:$C$200,$A48,'Metrics & Formulas'!$I$5:$I$200,D$45)+COUNTIFS('Projections & Dashboards'!$C$5:$C$200,$A48,'Projections & Dashboards'!$I$5:$I$200,D$45) | E48: =COUNTIFS('Constants & Enums'!$C$5:$C$200,$A48,'Constants & Enums'!$I$5:$I$200,E$45)+COUNTIFS('Metrics & Formulas'!$C$5:$C$200,$A48,'Metrics & Formulas'!$I$5:$I$200,E$45)+COUNTIFS('Projections & Dashboards'!$C$5:$C$200,$A48,'Projections & Dashboards'!$I$5:$I$200,E$45) | F48: =SUM(B48:E48) | G48: =IFERROR((D48+E48)/F48,0) | M48: =Listas!P7 | N48: =COUNTIF('Constants & Enums'!$D$5:$D$200,$M48) | O48: =COUNTIF('Metrics & Formulas'!$D$5:$D$200,$M48) | P48: =COUNTIF('Projections & Dashboards'!$D$5:$D$200,$M48) | Q48: =SUM(N48:P48)
A49: Metric | B49: =COUNTIFS('Constants & Enums'!$C$5:$C$200,$A49,'Constants & Enums'!$I$5:$I$200,B$45)+COUNTIFS('Metrics & Formulas'!$C$5:$C$200,$A49,'Metrics & Formulas'!$I$5:$I$200,B$45)+COUNTIFS('Projections & Dashboards'!$C$5:$C$200,$A49,'Projections & Dashboards'!$I$5:$I$200,B$45) | C49: =COUNTIFS('Constants & Enums'!$C$5:$C$200,$A49,'Constants & Enums'!$I$5:$I$200,C$45)+COUNTIFS('Metrics & Formulas'!$C$5:$C$200,$A49,'Metrics & Formulas'!$I$5:$I$200,C$45)+COUNTIFS('Projections & Dashboards'!$C$5:$C$200,$A49,'Projections & Dashboards'!$I$5:$I$200,C$45) | D49: =COUNTIFS('Constants & Enums'!$C$5:$C$200,$A49,'Constants & Enums'!$I$5:$I$200,D$45)+COUNTIFS('Metrics & Formulas'!$C$5:$C$200,$A49,'Metrics & Formulas'!$I$5:$I$200,D$45)+COUNTIFS('Projections & Dashboards'!$C$5:$C$200,$A49,'Projections & Dashboards'!$I$5:$I$200,D$45) | E49: =COUNTIFS('Constants & Enums'!$C$5:$C$200,$A49,'Constants & Enums'!$I$5:$I$200,E$45)+COUNTIFS('Metrics & Formulas'!$C$5:$C$200,$A49,'Metrics & Formulas'!$I$5:$I$200,E$45)+COUNTIFS('Projections & Dashboards'!$C$5:$C$200,$A49,'Projections & Dashboards'!$I$5:$I$200,E$45) | F49: =SUM(B49:E49) | G49: =IFERROR((D49+E49)/F49,0) | M49: =Listas!P8 | N49: =COUNTIF('Constants & Enums'!$D$5:$D$200,$M49) | O49: =COUNTIF('Metrics & Formulas'!$D$5:$D$200,$M49) | P49: =COUNTIF('Projections & Dashboards'!$D$5:$D$200,$M49) | Q49: =SUM(N49:P49)
A50: Projection | B50: =COUNTIFS('Constants & Enums'!$C$5:$C$200,$A50,'Constants & Enums'!$I$5:$I$200,B$45)+COUNTIFS('Metrics & Formulas'!$C$5:$C$200,$A50,'Metrics & Formulas'!$I$5:$I$200,B$45)+COUNTIFS('Projections & Dashboards'!$C$5:$C$200,$A50,'Projections & Dashboards'!$I$5:$I$200,B$45) | C50: =COUNTIFS('Constants & Enums'!$C$5:$C$200,$A50,'Constants & Enums'!$I$5:$I$200,C$45)+COUNTIFS('Metrics & Formulas'!$C$5:$C$200,$A50,'Metrics & Formulas'!$I$5:$I$200,C$45)+COUNTIFS('Projections & Dashboards'!$C$5:$C$200,$A50,'Projections & Dashboards'!$I$5:$I$200,C$45) | D50: =COUNTIFS('Constants & Enums'!$C$5:$C$200,$A50,'Constants & Enums'!$I$5:$I$200,D$45)+COUNTIFS('Metrics & Formulas'!$C$5:$C$200,$A50,'Metrics & Formulas'!$I$5:$I$200,D$45)+COUNTIFS('Projections & Dashboards'!$C$5:$C$200,$A50,'Projections & Dashboards'!$I$5:$I$200,D$45) | E50: =COUNTIFS('Constants & Enums'!$C$5:$C$200,$A50,'Constants & Enums'!$I$5:$I$200,E$45)+COUNTIFS('Metrics & Formulas'!$C$5:$C$200,$A50,'Metrics & Formulas'!$I$5:$I$200,E$45)+COUNTIFS('Projections & Dashboards'!$C$5:$C$200,$A50,'Projections & Dashboards'!$I$5:$I$200,E$45) | F50: =SUM(B50:E50) | G50: =IFERROR((D50+E50)/F50,0) | M50: =Listas!P9 | N50: =COUNTIF('Constants & Enums'!$D$5:$D$200,$M50) | O50: =COUNTIF('Metrics & Formulas'!$D$5:$D$200,$M50) | P50: =COUNTIF('Projections & Dashboards'!$D$5:$D$200,$M50) | Q50: =SUM(N50:P50)
A51: Dashboard | B51: =COUNTIFS('Constants & Enums'!$C$5:$C$200,$A51,'Constants & Enums'!$I$5:$I$200,B$45)+COUNTIFS('Metrics & Formulas'!$C$5:$C$200,$A51,'Metrics & Formulas'!$I$5:$I$200,B$45)+COUNTIFS('Projections & Dashboards'!$C$5:$C$200,$A51,'Projections & Dashboards'!$I$5:$I$200,B$45) | C51: =COUNTIFS('Constants & Enums'!$C$5:$C$200,$A51,'Constants & Enums'!$I$5:$I$200,C$45)+COUNTIFS('Metrics & Formulas'!$C$5:$C$200,$A51,'Metrics & Formulas'!$I$5:$I$200,C$45)+COUNTIFS('Projections & Dashboards'!$C$5:$C$200,$A51,'Projections & Dashboards'!$I$5:$I$200,C$45) | D51: =COUNTIFS('Constants & Enums'!$C$5:$C$200,$A51,'Constants & Enums'!$I$5:$I$200,D$45)+COUNTIFS('Metrics & Formulas'!$C$5:$C$200,$A51,'Metrics & Formulas'!$I$5:$I$200,D$45)+COUNTIFS('Projections & Dashboards'!$C$5:$C$200,$A51,'Projections & Dashboards'!$I$5:$I$200,D$45) | E51: =COUNTIFS('Constants & Enums'!$C$5:$C$200,$A51,'Constants & Enums'!$I$5:$I$200,E$45)+COUNTIFS('Metrics & Formulas'!$C$5:$C$200,$A51,'Metrics & Formulas'!$I$5:$I$200,E$45)+COUNTIFS('Projections & Dashboards'!$C$5:$C$200,$A51,'Projections & Dashboards'!$I$5:$I$200,E$45) | F51: =SUM(B51:E51) | G51: =IFERROR((D51+E51)/F51,0) | M51: =Listas!P10 | N51: =COUNTIF('Constants & Enums'!$D$5:$D$200,$M51) | O51: =COUNTIF('Metrics & Formulas'!$D$5:$D$200,$M51) | P51: =COUNTIF('Projections & Dashboards'!$D$5:$D$200,$M51) | Q51: =SUM(N51:P51)
A52: Total | B52: =SUM(B46:B51) | C52: =SUM(C46:C51) | D52: =SUM(D46:D51) | E52: =SUM(E46:E51) | F52: =SUM(F46:F51) | G52: =IFERROR((D52+E52)/F52,0) | M52: =Listas!P11 | N52: =COUNTIF('Constants & Enums'!$D$5:$D$200,$M52) | O52: =COUNTIF('Metrics & Formulas'!$D$5:$D$200,$M52) | P52: =COUNTIF('Projections & Dashboards'!$D$5:$D$200,$M52) | Q52: =SUM(N52:P52)
M53: =Listas!P12 | N53: =COUNTIF('Constants & Enums'!$D$5:$D$200,$M53) | O53: =COUNTIF('Metrics & Formulas'!$D$5:$D$200,$M53) | P53: =COUNTIF('Projections & Dashboards'!$D$5:$D$200,$M53) | Q53: =SUM(N53:P53)
M54: =Listas!P13 | N54: =COUNTIF('Constants & Enums'!$D$5:$D$200,$M54) | O54: =COUNTIF('Metrics & Formulas'!$D$5:$D$200,$M54) | P54: =COUNTIF('Projections & Dashboards'!$D$5:$D$200,$M54) | Q54: =SUM(N54:P54)
M55: =Listas!P14 | N55: =COUNTIF('Constants & Enums'!$D$5:$D$200,$M55) | O55: =COUNTIF('Metrics & Formulas'!$D$5:$D$200,$M55) | P55: =COUNTIF('Projections & Dashboards'!$D$5:$D$200,$M55) | Q55: =SUM(N55:P55)
M56: =Listas!P15 | N56: =COUNTIF('Constants & Enums'!$D$5:$D$200,$M56) | O56: =COUNTIF('Metrics & Formulas'!$D$5:$D$200,$M56) | P56: =COUNTIF('Projections & Dashboards'!$D$5:$D$200,$M56) | Q56: =SUM(N56:P56)
M57: =Listas!P16 | N57: =COUNTIF('Constants & Enums'!$D$5:$D$200,$M57) | O57: =COUNTIF('Metrics & Formulas'!$D$5:$D$200,$M57) | P57: =COUNTIF('Projections & Dashboards'!$D$5:$D$200,$M57) | Q57: =SUM(N57:P57)
M58: Total | N58: =SUM(N46:N57) | O58: =SUM(O46:O57) | P58: =SUM(P46:P57) | Q58: =SUM(Q46:Q57)
A76: 5 · Telas por fase legada e status (inventário original) | M76: 6 · Funções por fase legada e status (inventário original)
A77: Fase (legado) | B77: Existe | C77: Em andamento | D77: Planejada | E77: Descartada | F77: Total | M77: Fase (legado) | N77: Existe | O77: Em andamento | P77: Planejada | Q77: Descartada | R77: Total
A78: F0 | B78: =COUNTIFS(Telas!$H$5:$H$400,$A78,Telas!$J$5:$J$400,B$77) | C78: =COUNTIFS(Telas!$H$5:$H$400,$A78,Telas!$J$5:$J$400,C$77) | D78: =COUNTIFS(Telas!$H$5:$H$400,$A78,Telas!$J$5:$J$400,D$77) | E78: =COUNTIFS(Telas!$H$5:$H$400,$A78,Telas!$J$5:$J$400,E$77) | F78: =SUM(B78:E78) | M78: F0 | N78: =COUNTIFS(Funções!$F$5:$F$300,$M78,Funções!$H$5:$H$300,N$77) | O78: =COUNTIFS(Funções!$F$5:$F$300,$M78,Funções!$H$5:$H$300,O$77) | P78: =COUNTIFS(Funções!$F$5:$F$300,$M78,Funções!$H$5:$H$300,P$77) | Q78: =COUNTIFS(Funções!$F$5:$F$300,$M78,Funções!$H$5:$H$300,Q$77) | R78: =SUM(N78:Q78)
A79: F1 | B79: =COUNTIFS(Telas!$H$5:$H$400,$A79,Telas!$J$5:$J$400,B$77) | C79: =COUNTIFS(Telas!$H$5:$H$400,$A79,Telas!$J$5:$J$400,C$77) | D79: =COUNTIFS(Telas!$H$5:$H$400,$A79,Telas!$J$5:$J$400,D$77) | E79: =COUNTIFS(Telas!$H$5:$H$400,$A79,Telas!$J$5:$J$400,E$77) | F79: =SUM(B79:E79) | M79: F1 | N79: =COUNTIFS(Funções!$F$5:$F$300,$M79,Funções!$H$5:$H$300,N$77) | O79: =COUNTIFS(Funções!$F$5:$F$300,$M79,Funções!$H$5:$H$300,O$77) | P79: =COUNTIFS(Funções!$F$5:$F$300,$M79,Funções!$H$5:$H$300,P$77) | Q79: =COUNTIFS(Funções!$F$5:$F$300,$M79,Funções!$H$5:$H$300,Q$77) | R79: =SUM(N79:Q79)
A80: F2 | B80: =COUNTIFS(Telas!$H$5:$H$400,$A80,Telas!$J$5:$J$400,B$77) | C80: =COUNTIFS(Telas!$H$5:$H$400,$A80,Telas!$J$5:$J$400,C$77) | D80: =COUNTIFS(Telas!$H$5:$H$400,$A80,Telas!$J$5:$J$400,D$77) | E80: =COUNTIFS(Telas!$H$5:$H$400,$A80,Telas!$J$5:$J$400,E$77) | F80: =SUM(B80:E80) | M80: F2 | N80: =COUNTIFS(Funções!$F$5:$F$300,$M80,Funções!$H$5:$H$300,N$77) | O80: =COUNTIFS(Funções!$F$5:$F$300,$M80,Funções!$H$5:$H$300,O$77) | P80: =COUNTIFS(Funções!$F$5:$F$300,$M80,Funções!$H$5:$H$300,P$77) | Q80: =COUNTIFS(Funções!$F$5:$F$300,$M80,Funções!$H$5:$H$300,Q$77) | R80: =SUM(N80:Q80)
A81: F3 | B81: =COUNTIFS(Telas!$H$5:$H$400,$A81,Telas!$J$5:$J$400,B$77) | C81: =COUNTIFS(Telas!$H$5:$H$400,$A81,Telas!$J$5:$J$400,C$77) | D81: =COUNTIFS(Telas!$H$5:$H$400,$A81,Telas!$J$5:$J$400,D$77) | E81: =COUNTIFS(Telas!$H$5:$H$400,$A81,Telas!$J$5:$J$400,E$77) | F81: =SUM(B81:E81) | M81: F3 | N81: =COUNTIFS(Funções!$F$5:$F$300,$M81,Funções!$H$5:$H$300,N$77) | O81: =COUNTIFS(Funções!$F$5:$F$300,$M81,Funções!$H$5:$H$300,O$77) | P81: =COUNTIFS(Funções!$F$5:$F$300,$M81,Funções!$H$5:$H$300,P$77) | Q81: =COUNTIFS(Funções!$F$5:$F$300,$M81,Funções!$H$5:$H$300,Q$77) | R81: =SUM(N81:Q81)
A82: F4 | B82: =COUNTIFS(Telas!$H$5:$H$400,$A82,Telas!$J$5:$J$400,B$77) | C82: =COUNTIFS(Telas!$H$5:$H$400,$A82,Telas!$J$5:$J$400,C$77) | D82: =COUNTIFS(Telas!$H$5:$H$400,$A82,Telas!$J$5:$J$400,D$77) | E82: =COUNTIFS(Telas!$H$5:$H$400,$A82,Telas!$J$5:$J$400,E$77) | F82: =SUM(B82:E82) | M82: F4 | N82: =COUNTIFS(Funções!$F$5:$F$300,$M82,Funções!$H$5:$H$300,N$77) | O82: =COUNTIFS(Funções!$F$5:$F$300,$M82,Funções!$H$5:$H$300,O$77) | P82: =COUNTIFS(Funções!$F$5:$F$300,$M82,Funções!$H$5:$H$300,P$77) | Q82: =COUNTIFS(Funções!$F$5:$F$300,$M82,Funções!$H$5:$H$300,Q$77) | R82: =SUM(N82:Q82)
A83: F5 | B83: =COUNTIFS(Telas!$H$5:$H$400,$A83,Telas!$J$5:$J$400,B$77) | C83: =COUNTIFS(Telas!$H$5:$H$400,$A83,Telas!$J$5:$J$400,C$77) | D83: =COUNTIFS(Telas!$H$5:$H$400,$A83,Telas!$J$5:$J$400,D$77) | E83: =COUNTIFS(Telas!$H$5:$H$400,$A83,Telas!$J$5:$J$400,E$77) | F83: =SUM(B83:E83) | M83: F5 | N83: =COUNTIFS(Funções!$F$5:$F$300,$M83,Funções!$H$5:$H$300,N$77) | O83: =COUNTIFS(Funções!$F$5:$F$300,$M83,Funções!$H$5:$H$300,O$77) | P83: =COUNTIFS(Funções!$F$5:$F$300,$M83,Funções!$H$5:$H$300,P$77) | Q83: =COUNTIFS(Funções!$F$5:$F$300,$M83,Funções!$H$5:$H$300,Q$77) | R83: =SUM(N83:Q83)
A84: F6 | B84: =COUNTIFS(Telas!$H$5:$H$400,$A84,Telas!$J$5:$J$400,B$77) | C84: =COUNTIFS(Telas!$H$5:$H$400,$A84,Telas!$J$5:$J$400,C$77) | D84: =COUNTIFS(Telas!$H$5:$H$400,$A84,Telas!$J$5:$J$400,D$77) | E84: =COUNTIFS(Telas!$H$5:$H$400,$A84,Telas!$J$5:$J$400,E$77) | F84: =SUM(B84:E84) | M84: F6 | N84: =COUNTIFS(Funções!$F$5:$F$300,$M84,Funções!$H$5:$H$300,N$77) | O84: =COUNTIFS(Funções!$F$5:$F$300,$M84,Funções!$H$5:$H$300,O$77) | P84: =COUNTIFS(Funções!$F$5:$F$300,$M84,Funções!$H$5:$H$300,P$77) | Q84: =COUNTIFS(Funções!$F$5:$F$300,$M84,Funções!$H$5:$H$300,Q$77) | R84: =SUM(N84:Q84)
A85: Total | B85: =SUM(B78:B84) | C85: =SUM(C78:C84) | D85: =SUM(D78:D84) | E85: =SUM(E78:E84) | F85: =SUM(F78:F84) | M85: Total | N85: =SUM(N78:N84) | O85: =SUM(O78:O84) | P85: =SUM(P78:P84) | Q85: =SUM(Q78:Q84) | R85: =SUM(R78:R84)
A108: 7 · Matriz de dependências (de → para) | M108: 8 · Módulos por nível de confiança (aba Modules)
A109: De \ Para | B109: Constant | C109: Enum | D109: Policy | E109: Metric | F109: Projection | G109: Dashboard | H109: Function | I109: Screen | J109: Roadmap item | K109: Module / area | M109: Nível | N109: Módulos | O109: Critério (COUNTIF)
A110: Constant | B110: =COUNTIFS(Dependencies!$D$5:$D$300,$A110,Dependencies!$H$5:$H$300,B$109) | C110: =COUNTIFS(Dependencies!$D$5:$D$300,$A110,Dependencies!$H$5:$H$300,C$109) | D110: =COUNTIFS(Dependencies!$D$5:$D$300,$A110,Dependencies!$H$5:$H$300,D$109) | E110: =COUNTIFS(Dependencies!$D$5:$D$300,$A110,Dependencies!$H$5:$H$300,E$109) | F110: =COUNTIFS(Dependencies!$D$5:$D$300,$A110,Dependencies!$H$5:$H$300,F$109) | G110: =COUNTIFS(Dependencies!$D$5:$D$300,$A110,Dependencies!$H$5:$H$300,G$109) | H110: =COUNTIFS(Dependencies!$D$5:$D$300,$A110,Dependencies!$H$5:$H$300,H$109) | I110: =COUNTIFS(Dependencies!$D$5:$D$300,$A110,Dependencies!$H$5:$H$300,I$109) | ... K110: =COUNTIFS(Dependencies!$D$5:$D$300,$A110,Dependencies!$H$5:$H$300,K$109) | M110: Documentado | N110: =COUNTIF(Modules!$I$5:$I$100,O110) | O110: Documented*
A111: Enum | B111: =COUNTIFS(Dependencies!$D$5:$D$300,$A111,Dependencies!$H$5:$H$300,B$109) | C111: =COUNTIFS(Dependencies!$D$5:$D$300,$A111,Dependencies!$H$5:$H$300,C$109) | D111: =COUNTIFS(Dependencies!$D$5:$D$300,$A111,Dependencies!$H$5:$H$300,D$109) | E111: =COUNTIFS(Dependencies!$D$5:$D$300,$A111,Dependencies!$H$5:$H$300,E$109) | F111: =COUNTIFS(Dependencies!$D$5:$D$300,$A111,Dependencies!$H$5:$H$300,F$109) | G111: =COUNTIFS(Dependencies!$D$5:$D$300,$A111,Dependencies!$H$5:$H$300,G$109) | H111: =COUNTIFS(Dependencies!$D$5:$D$300,$A111,Dependencies!$H$5:$H$300,H$109) | I111: =COUNTIFS(Dependencies!$D$5:$D$300,$A111,Dependencies!$H$5:$H$300,I$109) | ... K111: =COUNTIFS(Dependencies!$D$5:$D$300,$A111,Dependencies!$H$5:$H$300,K$109) | M111: Precisa de auditoria | N111: =COUNTIF(Modules!$I$5:$I$100,O111) | O111: Needs code audit
A112: Policy | B112: =COUNTIFS(Dependencies!$D$5:$D$300,$A112,Dependencies!$H$5:$H$300,B$109) | C112: =COUNTIFS(Dependencies!$D$5:$D$300,$A112,Dependencies!$H$5:$H$300,C$109) | D112: =COUNTIFS(Dependencies!$D$5:$D$300,$A112,Dependencies!$H$5:$H$300,D$109) | E112: =COUNTIFS(Dependencies!$D$5:$D$300,$A112,Dependencies!$H$5:$H$300,E$109) | F112: =COUNTIFS(Dependencies!$D$5:$D$300,$A112,Dependencies!$H$5:$H$300,F$109) | G112: =COUNTIFS(Dependencies!$D$5:$D$300,$A112,Dependencies!$H$5:$H$300,G$109) | H112: =COUNTIFS(Dependencies!$D$5:$D$300,$A112,Dependencies!$H$5:$H$300,H$109) | I112: =COUNTIFS(Dependencies!$D$5:$D$300,$A112,Dependencies!$H$5:$H$300,I$109) | ... K112: =COUNTIFS(Dependencies!$D$5:$D$300,$A112,Dependencies!$H$5:$H$300,K$109) | M112: Planejado / pendente | N112: =COUNTIF(Modules!$I$5:$I$100,O112) | O112: Planned*
A113: Metric | B113: =COUNTIFS(Dependencies!$D$5:$D$300,$A113,Dependencies!$H$5:$H$300,B$109) | C113: =COUNTIFS(Dependencies!$D$5:$D$300,$A113,Dependencies!$H$5:$H$300,C$109) | D113: =COUNTIFS(Dependencies!$D$5:$D$300,$A113,Dependencies!$H$5:$H$300,D$109) | E113: =COUNTIFS(Dependencies!$D$5:$D$300,$A113,Dependencies!$H$5:$H$300,E$109) | F113: =COUNTIFS(Dependencies!$D$5:$D$300,$A113,Dependencies!$H$5:$H$300,F$109) | G113: =COUNTIFS(Dependencies!$D$5:$D$300,$A113,Dependencies!$H$5:$H$300,G$109) | H113: =COUNTIFS(Dependencies!$D$5:$D$300,$A113,Dependencies!$H$5:$H$300,H$109) | I113: =COUNTIFS(Dependencies!$D$5:$D$300,$A113,Dependencies!$H$5:$H$300,I$109) | ... K113: =COUNTIFS(Dependencies!$D$5:$D$300,$A113,Dependencies!$H$5:$H$300,K$109) | M113: Template | N113: =COUNTIF(Modules!$I$5:$I$100,O113) | O113: Template
A114: Projection | B114: =COUNTIFS(Dependencies!$D$5:$D$300,$A114,Dependencies!$H$5:$H$300,B$109) | C114: =COUNTIFS(Dependencies!$D$5:$D$300,$A114,Dependencies!$H$5:$H$300,C$109) | D114: =COUNTIFS(Dependencies!$D$5:$D$300,$A114,Dependencies!$H$5:$H$300,D$109) | E114: =COUNTIFS(Dependencies!$D$5:$D$300,$A114,Dependencies!$H$5:$H$300,E$109) | F114: =COUNTIFS(Dependencies!$D$5:$D$300,$A114,Dependencies!$H$5:$H$300,F$109) | G114: =COUNTIFS(Dependencies!$D$5:$D$300,$A114,Dependencies!$H$5:$H$300,G$109) | H114: =COUNTIFS(Dependencies!$D$5:$D$300,$A114,Dependencies!$H$5:$H$300,H$109) | I114: =COUNTIFS(Dependencies!$D$5:$D$300,$A114,Dependencies!$H$5:$H$300,I$109) | ... K114: =COUNTIFS(Dependencies!$D$5:$D$300,$A114,Dependencies!$H$5:$H$300,K$109)
A115: Dashboard | B115: =COUNTIFS(Dependencies!$D$5:$D$300,$A115,Dependencies!$H$5:$H$300,B$109) | C115: =COUNTIFS(Dependencies!$D$5:$D$300,$A115,Dependencies!$H$5:$H$300,C$109) | D115: =COUNTIFS(Dependencies!$D$5:$D$300,$A115,Dependencies!$H$5:$H$300,D$109) | E115: =COUNTIFS(Dependencies!$D$5:$D$300,$A115,Dependencies!$H$5:$H$300,E$109) | F115: =COUNTIFS(Dependencies!$D$5:$D$300,$A115,Dependencies!$H$5:$H$300,F$109) | G115: =COUNTIFS(Dependencies!$D$5:$D$300,$A115,Dependencies!$H$5:$H$300,G$109) | H115: =COUNTIFS(Dependencies!$D$5:$D$300,$A115,Dependencies!$H$5:$H$300,H$109) | I115: =COUNTIFS(Dependencies!$D$5:$D$300,$A115,Dependencies!$H$5:$H$300,I$109) | ... K115: =COUNTIFS(Dependencies!$D$5:$D$300,$A115,Dependencies!$H$5:$H$300,K$109)
A116: Function | B116: =COUNTIFS(Dependencies!$D$5:$D$300,$A116,Dependencies!$H$5:$H$300,B$109) | C116: =COUNTIFS(Dependencies!$D$5:$D$300,$A116,Dependencies!$H$5:$H$300,C$109) | D116: =COUNTIFS(Dependencies!$D$5:$D$300,$A116,Dependencies!$H$5:$H$300,D$109) | E116: =COUNTIFS(Dependencies!$D$5:$D$300,$A116,Dependencies!$H$5:$H$300,E$109) | F116: =COUNTIFS(Dependencies!$D$5:$D$300,$A116,Dependencies!$H$5:$H$300,F$109) | G116: =COUNTIFS(Dependencies!$D$5:$D$300,$A116,Dependencies!$H$5:$H$300,G$109) | H116: =COUNTIFS(Dependencies!$D$5:$D$300,$A116,Dependencies!$H$5:$H$300,H$109) | I116: =COUNTIFS(Dependencies!$D$5:$D$300,$A116,Dependencies!$H$5:$H$300,I$109) | ... K116: =COUNTIFS(Dependencies!$D$5:$D$300,$A116,Dependencies!$H$5:$H$300,K$109)
A117: Screen | B117: =COUNTIFS(Dependencies!$D$5:$D$300,$A117,Dependencies!$H$5:$H$300,B$109) | C117: =COUNTIFS(Dependencies!$D$5:$D$300,$A117,Dependencies!$H$5:$H$300,C$109) | D117: =COUNTIFS(Dependencies!$D$5:$D$300,$A117,Dependencies!$H$5:$H$300,D$109) | E117: =COUNTIFS(Dependencies!$D$5:$D$300,$A117,Dependencies!$H$5:$H$300,E$109) | F117: =COUNTIFS(Dependencies!$D$5:$D$300,$A117,Dependencies!$H$5:$H$300,F$109) | G117: =COUNTIFS(Dependencies!$D$5:$D$300,$A117,Dependencies!$H$5:$H$300,G$109) | H117: =COUNTIFS(Dependencies!$D$5:$D$300,$A117,Dependencies!$H$5:$H$300,H$109) | I117: =COUNTIFS(Dependencies!$D$5:$D$300,$A117,Dependencies!$H$5:$H$300,I$109) | ... K117: =COUNTIFS(Dependencies!$D$5:$D$300,$A117,Dependencies!$H$5:$H$300,K$109)
A118: Roadmap item | B118: =COUNTIFS(Dependencies!$D$5:$D$300,$A118,Dependencies!$H$5:$H$300,B$109) | C118: =COUNTIFS(Dependencies!$D$5:$D$300,$A118,Dependencies!$H$5:$H$300,C$109) | D118: =COUNTIFS(Dependencies!$D$5:$D$300,$A118,Dependencies!$H$5:$H$300,D$109) | E118: =COUNTIFS(Dependencies!$D$5:$D$300,$A118,Dependencies!$H$5:$H$300,E$109) | F118: =COUNTIFS(Dependencies!$D$5:$D$300,$A118,Dependencies!$H$5:$H$300,F$109) | G118: =COUNTIFS(Dependencies!$D$5:$D$300,$A118,Dependencies!$H$5:$H$300,G$109) | H118: =COUNTIFS(Dependencies!$D$5:$D$300,$A118,Dependencies!$H$5:$H$300,H$109) | I118: =COUNTIFS(Dependencies!$D$5:$D$300,$A118,Dependencies!$H$5:$H$300,I$109) | ... K118: =COUNTIFS(Dependencies!$D$5:$D$300,$A118,Dependencies!$H$5:$H$300,K$109)
A119: Module / area | B119: =COUNTIFS(Dependencies!$D$5:$D$300,$A119,Dependencies!$H$5:$H$300,B$109) | C119: =COUNTIFS(Dependencies!$D$5:$D$300,$A119,Dependencies!$H$5:$H$300,C$109) | D119: =COUNTIFS(Dependencies!$D$5:$D$300,$A119,Dependencies!$H$5:$H$300,D$109) | E119: =COUNTIFS(Dependencies!$D$5:$D$300,$A119,Dependencies!$H$5:$H$300,E$109) | F119: =COUNTIFS(Dependencies!$D$5:$D$300,$A119,Dependencies!$H$5:$H$300,F$109) | G119: =COUNTIFS(Dependencies!$D$5:$D$300,$A119,Dependencies!$H$5:$H$300,G$109) | H119: =COUNTIFS(Dependencies!$D$5:$D$300,$A119,Dependencies!$H$5:$H$300,H$109) | I119: =COUNTIFS(Dependencies!$D$5:$D$300,$A119,Dependencies!$H$5:$H$300,I$109) | ... K119: =COUNTIFS(Dependencies!$D$5:$D$300,$A119,Dependencies!$H$5:$H$300,K$109)
A120: Linhas = tipo de origem; colunas = tipo de destino. Células mais escuras concentram mais relações — bons pontos de atenção para dependências ocultas.

Sheet Roadmap
A1: Kodoo — roadmap revisado orientado por evidência
A2: Este plano segue as fases do repositório, não as fases legadas do catálogo de telas/funções. Estados iniciais são hipóteses da auditoria documental, não declaração de conclusão do código.
A3: Repositório | B3: https://github.com/bootstrapprx/kodoo | C3: Docs base | D3: context/roadmap.md (21/09/2026); context/domain-app-migration.md e context/application-architecture.md (19/10/2026) | M3: Atualize o Current Status somente após conferir código, testes e CI.
A5: ID | B5: Repository Phase | C5: Workstream | D5: Deliverable / Work Item | E5: Definition of Done / Acceptance Criteria | F5: Priority | G5: Initial Status | H5: Dependencies | I5: Required Evidence | J5: Source / Notes | K5: Owner | L5: Target | M5: Current Status | N5: Evidence Link / Path / Command
A6: RM-001 | B6: F0 | C6: Governança do roadmap | D6: Confirmar decisões de execução/provisionamento e registrar as decisões abertas. | E6: Cada decisão tem valor escolhido, justificativa, responsável e consequência técnica; docs/scripts refletem a decisão. | F6: P0 | G6: A validar | H6: — | I6: Registro de decisões + execução em ambiente limpo | J6: context/roadmap.md | M6: A validar
A7: RM-002 | B7: F1 | C7: Banco e migrações | D7: Validar bootstrap de papéis PostgreSQL, ownership, migrations e checks SQL em ambiente limpo. | E7: Pipeline reproduzível desde banco vazio; papéis e ownership corretos; falhas de migration/check impedem avanço. | F7: P0 | G7: Parcial/documentado; validar HEAD | H7: RM-001 | I7: Log CI + execução local documentada | J7: context/roadmap.md; .github/workflows/ci.yml | M7: A validar
A8: RM-003 | B8: F2 | C8: Identidade e escopo | D8: Fechar contrato de ator, organização ativa e propagação de contexto em todas as entradas relevantes. | E8: Contexto ausente/malformado é rejeitado; autorização aplicada no servidor, não apenas na UI; sem vazamento entre organizações. | F8: P0 | G8: Implementado no primeiro slice; aceite CI pendente | H8: RM-002 | I8: Testes de contexto Rust + SQL F2; API auth remains F3 | J8: context/roadmap.md; context/identity-isolation.md; context/f2-authorization-matrix.md | M8: Em andamento | N8: crates/kodoo-core; crates/kodoo-postgres/tests/identity_context.rs; tests/database/0005-f2-isolation.sql
A9: RM-004 | B9: F2 | C9: Autorização e isolamento | D9: Criar matriz de permissões por ação e validar acesso cruzado entre organizações. | E9: Ações permitidas/negadas documentadas; testes provam negação por padrão e isolamento de dados em sucesso, erro e rollback. | F9: P0 | G9: Implementado no primeiro slice; aceite CI pendente | H9: RM-003 | I9: Matriz por operação + negação por padrão + isolamento cross-org | J9: context/f2-authorization-matrix.md; schema/postgresql/migrations/0041-restrictive-worker-rls.sql | M9: Em andamento | N9: schema/postgresql/checks/0002-f2-worker-scope.sql; tests/database/0005-f2-isolation.sql
A10: RM-005 | B10: F3 | C10: Fatia vertical nativa | D10: Escolher uma operação de negócio estreita e concluí-la ponta a ponta com persistência durável. | E10: API, domínio/use case, PostgreSQL, autorização, auditoria, CLI e testes representam a mesma regra; sem estado em memória como fonte de verdade. | F10: P0 | G10: Implementado na fatia Project Manager; aceite CI pendente | H10: RM-003; RM-004 | I10: Teste SQL F3 + API/caso de uso + CLI/MCP; workspace CI pendente | J10: context/f3-project-manager.md; tests/database/0006-f3-project-manager.sql | M10: Em andamento | N10: modules/project-manager; crates/kodoo-postgres/src/project_manager.rs; backend/src/api.rs
A11: RM-006 | B11: F3 | C11: Auditoria e transições | D11: Formalizar eventos auditáveis e transições inválidas da primeira fatia. | E11: Cada mutação relevante deixa evidência; transições inválidas e chamadas não autorizadas falham com erro estável e teste. | F11: P1 | G11: Auditoria e transições implementadas; aceite CI pendente | H11: RM-005 | I11: Migração 0042 + teste de transição inválida e auditoria same-transaction | J11: schema/postgresql/migrations/0042-project-manager-audit.sql; tests/database/0006-f3-project-manager.sql | M11: Em andamento | N11: audit.event; administration.record_event; project_manager.transition_task
A12: RM-007 | B12: F4 | C12: Outbox e worker | D12: Fechar ciclo de vida de efeitos externos: agendamento, retry, deduplicação e recuperação. | E12: Falhas temporárias, timeout ambíguo e entregas duplicadas são testados; estado final e reprocessamento são determinísticos. | F12: P1 | G12: Infra parcial/documentada | H12: RM-005 | I12: Testes de falha/duplicação/retomada em stack real | J12: context/roadmap.md | M12: A validar
A13: RM-008 | B13: F4 | C13: Integrações concretas | D13: Listar providers reais e implementar dispatchers faltantes sem espalhar regra de domínio. | E13: Cada provider tem contrato, configuração segura, timeout, retry, idempotência e testes de contrato. | F13: P2 | G13: Pendente/documentado | H13: RM-007 | I13: Testes de contrato e configuração de exemplo sem segredos | J13: context/roadmap.md | M13: A validar
A14: RM-009 | B14: F5 | C14: Inventário de origem | D14: Inventariar dados, fluxos e dependências do sistema de origem antes de desenhar importação. | E14: Inventário versionado; cada entidade tem volume, proprietário, mapeamento, qualidade e regra de reconciliação. | F14: P1 | G14: Pendente/documentado | H14: RM-005 | I14: Relatório de inventário revisável | J14: context/roadmap.md | M14: A validar
A15: RM-010 | B15: F5 | C15: Ensaio de importação | D15: Construir ensaio repetível e determinístico com proveniência e reconciliação. | E15: Importar duas vezes produz resultado controlado; divergências são explicadas; proveniência por registro; plano de correção/rollback documentado. | F15: P1 | G15: Pendente/documentado | H15: RM-009 | I15: Relatório de dry-run + fixtures representativas | J15: context/roadmap.md | M15: A validar
A16: RM-011 | B16: F5 | C16: Adaptador Odoo restrito | D16: Definir e testar o contrato mínimo de compatibilidade necessário para migração. | E16: Adaptador limitado a contratos explícitos; sem replicar arquitetura do legado; testes de contrato e limites de uso. | F16: P2 | G16: Pendente/documentado | H16: RM-009; RM-010 | I16: Contrato versionado + testes de contrato | J16: README.md; context/roadmap.md | M16: A validar
A17: RM-012 | B17: F6 | C17: Cutover e fencing | D17: Desenhar e ensaiar corte controlado com bloqueio de escrita no sistema antigo. | E17: Fencing demonstrado; nenhuma escrita concorrente obsoleta; reconciliação antes/depois; recuperação testada sem perder escrita aceita. | F17: P1 | G17: Pendente/documentado | H17: RM-010; RM-011 | I17: Ensaio completo com relatório de reconciliação | J17: context/roadmap.md | M17: A validar
A18: RM-013 | B18: A1 | C18: Autoridade do ledger | D18: Verificar que TigerBeetle é autoridade contábil e só é acessado pelo módulo de contabilidade. | E18: Limite arquitetural respeitado; nenhum acesso a TigerBeetle por kodoo-core/outros módulos; testes/CI protegem a regra. | F18: P0 | G18: Regra arquitetural documentada; validar código atual | H18: RM-002 | I18: Busca de dependências + teste/checagem estrutural | J18: README.md; context/application-architecture.md | M18: A validar
A19: RM-014 | B19: A1 | C19: Postagem e reversão | D19: Fechar ciclos de períodos, lançamentos, lotes, estornos e fechamento ainda com TODOs. | E19: Invariantes de partidas dobradas; idempotência e correções sem apagar histórico; casos de período fechado cobertos. | F19: P0 | G19: Parcial; há lacunas/TODOs documentados | H19: RM-003; RM-013 | I19: Testes de domínio e integração com TigerBeetle real | J19: context/domain-app-migration.md | M19: A validar
A20: RM-015 | B20: A1 | C20: Reconciliação bancária e subledger | D20: Definir modelo de reconciliação entre extratos, subledger, diário e ledger autoritativo. | E20: Diferenças explicáveis; não há ajuste silencioso; histórico de conciliação e exceções é auditável. | F20: P1 | G20: Lacuna identificada na auditoria documental | H20: RM-014 | I20: Casos de aceitação com divergência e correção | J20: context/domain-app-migration.md | M20: A validar
A21: RM-016 | B21: A1 | C21: Relatórios contábeis e trilha | D21: Validar razão, balancete e demonstrações contra a fonte contábil autoritativa. | E21: Relatórios reconciliam com o ledger; filtros/intervalos definidos; trilha de auditoria permite explicar cada saldo. | F21: P1 | G21: Parcial; validar read models restantes | H21: RM-014 | I21: Testes de reconciliação e fixtures de aceitação | J21: context/domain-app-migration.md | M21: A validar
A22: RM-017 | B22: A1 | C22: Read models do Kalkulisto | D22: Completar os read models que faltam e integrá-los à aplicação de domínio. | E22: Estados de carregamento/vazio/erro; autorização; paginação/filtros quando aplicáveis; nenhum dado fictício em produção. | F22: P1 | G22: Parcial; lacunas documentadas | H22: RM-003; RM-014; RM-016 | I22: Teste UI/integração e verificação desktop real | J22: context/domain-app-migration.md; context/application-architecture.md | M22: A validar
A23: RM-018 | B23: A1 | C23: QA com stack real | D23: Definir evidência de aceitação para cada fatia contábil em Docker/stack real. | E23: Testes passam com PostgreSQL e TigerBeetle reais; falhas de rede/duplicação/recuperação relevantes cobertas; comandos reproduzíveis. | F23: P0 | G23: Necessário por fatia | H23: RM-014; RM-015; RM-016 | I23: Relatório QA por fatia + CI | J23: context/domain-app-migration.md; .github/workflows/ci.yml | M23: A validar
... A31: RM-026 | B31: Transversal | C31: Dependências e proprietários das definições | D31: Mapear relações entre métricas, funções, tabelas, módulos e telas na aba Dependencies e resolver proprietários pendentes. | E31: Toda definição tem proprietário explícito (ou decisão pendente registrada); nenhuma dependência aponta para ID inexistente; localização não é inventada. | F31: P2 | G31: A validar | H31: RM-023; RM-024; RM-025 | I31: Aba Dependencies sem alertas + decisões registradas | J31: Resposta sobre projeções (aba Racional (Constantes)) | M31: A validar

Sheet Telas
A1: Telas: o que preciso ter, em que fase e em que estado
A2: Edite as colunas com lista suspensa e os textos. A coluna Família (cinza) é fórmula. Adicione telas nas linhas livres abaixo, usando o próximo ID sugerido na aba Leia-me. Use o filtro do cabeçalho para navegar.
O3: Fase do roadmap do repositório; preencher após validar item a item. | P3: Caminho, teste, PR ou comando que prova o estado real.
A4: ID | B4: Módulo | C4: Tela | D4: Arquétipo | E4: Família | F4: Entidade | G4: Descrição | H4: Fase catálogo antigo (não equivalente às fases do repo) | I4: Prioridade | J4: Status do inventário (não verificado no código) | K4: Funções (IDs) | L4: Depende de (IDs) | M4: Spec (ViewSpec) | N4: Notas | O4: Fase Kodoo (reclassificar) | P4: Evidência no repositório
A5: T-001 | B5: Shell e Navegação | C5: Login | D5: Shell | E5: =IF(D5="","",IFERROR(INDEX(Arquétipos!$B$5:$B$40,MATCH(D5,Arquétipos!$A$5:$A$40,0)),"")) | G5: Autenticação do usuário | H5: F0 | I5: Alta | J5: Planejada | K5: FN-013 | M5: Não
A6: T-002 | B6: Shell e Navegação | C6: Lançador de módulos | D6: Launcher | E6: =IF(D6="","",IFERROR(INDEX(Arquétipos!$B$5:$B$40,MATCH(D6,Arquétipos!$A$5:$A$40,0)),"")) | G6: Ponto de entrada; esconde módulos sem permissão | H6: F0 | I6: Alta | J6: Planejada | K6: FN-014 | L6: T-001 | M6: Não
A7: T-003 | B7: Shell e Navegação | C7: Navegação lateral e breadcrumbs | D7: Shell | E7: =IF(D7="","",IFERROR(INDEX(Arquétipos!$B$5:$B$40,MATCH(D7,Arquétipos!$A$5:$A$40,0)),"")) | H7: F0 | I7: Alta | J7: Planejada | M7: Não
A8: T-004 | B8: Shell e Navegação | C8: Estados padrão (carregando, vazio, erro) | D8: Shell | E8: =IF(D8="","",IFERROR(INDEX(Arquétipos!$B$5:$B$40,MATCH(D8,Arquétipos!$A$5:$A$40,0)),"")) | G8: Componentes de ViewState usados por todos os arquétipos | H8: F0 | I8: Alta | J8: Planejada | M8: Não
A9: T-005 | B9: Shell e Navegação | C9: Acesso negado | D9: Shell | E9: =IF(D9="","",IFERROR(INDEX(Arquétipos!$B$5:$B$40,MATCH(D9,Arquétipos!$A$5:$A$40,0)),"")) | H9: F0 | I9: Média | J9: Planejada | K9: FN-014 | M9: Não
A10: T-006 | B10: Shell e Navegação | C10: Página não encontrada (404) | D10: Shell | E10: =IF(D10="","",IFERROR(INDEX(Arquétipos!$B$5:$B$40,MATCH(D10,Arquétipos!$A$5:$A$40,0)),"")) | H10: F0 | I10: Baixa | J10: Planejada | M10: Não
A11: T-007 | B11: Shell e Navegação | C11: Seleção de organização | D11: Shell | E11: =IF(D11="","",IFERROR(INDEX(Arquétipos!$B$5:$B$40,MATCH(D11,Arquétipos!$A$5:$A$40,0)),"")) | G11: Escolher a organização ativa | H11: F2 | I11: Alta | J11: Planejada | K11: FN-020 | L11: T-001 | M11: Não
A12: T-008 | B12: Shell e Navegação | C12: Perfil do usuário | D12: Form | E12: =IF(D12="","",IFERROR(INDEX(Arquétipos!$B$5:$B$40,MATCH(D12,Arquétipos!$A$5:$A$40,0)),"")) | H12: F2 | I12: Baixa | J12: Planejada | M12: Não
A13: T-009 | B13: Shell e Navegação | C13: Preferências de interface (tema, idioma, densidade) | D13: Settings | E13: =IF(D13="","",IFERROR(INDEX(Arquétipos!$B$5:$B$40,MATCH(D13,Arquétipos!$A$5:$A$40,0)),"")) | H13: F2 | I13: Baixa | J13: Planejada | K13: FN-010 | M13: Não
A14: T-010 | B14: Shell e Navegação | C14: Busca global | D14: List | E14: =IF(D14="","",IFERROR(INDEX(Arquétipos!$B$5:$B$40,MATCH(D14,Arquétipos!$A$5:$A$40,0)),"")) | H14: F4 | I14: Média | J14: Planejada | M14: Não
A15: T-011 | B15: Shell e Navegação | C15: Centro de notificações | D15: List | E15: =IF(D15="","",IFERROR(INDEX(Arquétipos!$B$5:$B$40,MATCH(D15,Arquétipos!$A$5:$A$40,0)),"")) | H15: F4 | I15: Baixa | J15: Planejada | M15: Não
A16: T-012 | B16: Shell e Navegação | C16: Paleta de comandos e atalhos | D16: Shell | E16: =IF(D16="","",IFERROR(INDEX(Arquétipos!$B$5:$B$40,MATCH(D16,Arquétipos!$A$5:$A$40,0)),"")) | H16: F5 | I16: Baixa | J16: Planejada | M16: Não
A17: T-013 | B17: Shell e Navegação | C17: Recuperação de senha | D17: Shell | E17: =IF(D17="","",IFERROR(INDEX(Arquétipos!$B$5:$B$40,MATCH(D17,Arquétipos!$A$5:$A$40,0)),"")) | H17: F5 | I17: Média | J17: Planejada | K17: FN-017 | M17: Não
A18: T-014 | B18: Fundação e Infraestrutura | C18: Galeria de arquétipos (com fixtures) | D18: List | E18: =IF(D18="","",IFERROR(INDEX(Arquétipos!$B$5:$B$40,MATCH(D18,Arquétipos!$A$5:$A$40,0)),"")) | G18: Mostra cada arquétipo com dados de teste; ferramenta de visualização e aprendizado | H18: F0 | I18: Alta | J18: Planejada | K18: FN-002, FN-003 | L18: T-003 | M18: Não
A19: T-015 | B19: Fundação e Infraestrutura | C19: Inspetor de ViewSpec | D19: Detail | E19: =IF(D19="","",IFERROR(INDEX(Arquétipos!$B$5:$B$40,MATCH(D19,Arquétipos!$A$5:$A$40,0)),"")) | G19: Exibe a spec de cada tela e os erros de validação | H19: F0 | I19: Média | J19: Planejada | K19: FN-001 | L19: T-014 | M19: Não
A20: T-016 | B20: Fundação e Infraestrutura | C20: Painel de verificação de funções (Ratatui) | D20: Shell | E20: =IF(D20="","",IFERROR(INDEX(Arquétipos!$B$5:$B$40,MATCH(D20,Arquétipos!$A$5:$A$40,0)),"")) | G20: Verifica funções de domínio sem passar pela UI | H20: F1 | I20: Média | J20: Planejada | K20: FN-008, FN-007 | M20: Não
A21: T-017 | B21: Administração e Segurança | C21: Organizações | D21: List | E21: =IF(D21="","",IFERROR(INDEX(Arquétipos!$B$5:$B$40,MATCH(D21,Arquétipos!$A$5:$A$40,0)),"")) | H21: F2 | I21: Alta | J21: Planejada | K21: FN-020 | L21: T-002 | M21: Não
A22: T-018 | B22: Administração e Segurança | C22: Organização | D22: Form | E22: =IF(D22="","",IFERROR(INDEX(Arquétipos!$B$5:$B$40,MATCH(D22,Arquétipos!$A$5:$A$40,0)),"")) | H22: F2 | I22: Alta | J22: Planejada | K22: FN-020 | M22: Não
A23: T-019 | B23: Administração e Segurança | C23: Parâmetros gerais | D23: Settings | E23: =IF(D23="","",IFERROR(INDEX(Arquétipos!$B$5:$B$40,MATCH(D23,Arquétipos!$A$5:$A$40,0)),"")) | H23: F2 | I23: Média | J23: Planejada | K23: FN-021 | M23: Não
A24: T-020 | B24: Administração e Segurança | C24: Sequências de numeração | D24: Settings | E24: =IF(D24="","",IFERROR(INDEX(Arquétipos!$B$5:$B$40,MATCH(D24,Arquétipos!$A$5:$A$40,0)),"")) | H24: F2 | I24: Média | J24: Planejada | K24: FN-022, FN-037 | M24: Não
A25: T-021 | B25: Administração e Segurança | C25: Usuários | D25: List | E25: =IF(D25="","",IFERROR(INDEX(Arquétipos!$B$5:$B$40,MATCH(D25,Arquétipos!$A$5:$A$40,0)),"")) | H25: F5 | I25: Média | J25: Planejada | K25: FN-018 | M25: Não
A26: T-022 | B26: Administração e Segurança | C26: Usuário | D26: Form | E26: =IF(D26="","",IFERROR(INDEX(Arquétipos!$B$5:$B$40,MATCH(D26,Arquétipos!$A$5:$A$40,0)),"")) | H26: F5 | I26: Média | J26: Planejada | K26: FN-018 | M26: Não
A27: T-023 | B27: Administração e Segurança | C27: Papéis | D27: List | E27: =IF(D27="","",IFERROR(INDEX(Arquétipos!$B$5:$B$40,MATCH(D27,Arquétipos!$A$5:$A$40,0)),"")) | H27: F5 | I27: Média | J27: Planejada | K27: FN-019 | M27: Não
A28: T-024 | B28: Administração e Segurança | C28: Papel e permissões | D28: MasterDetail | E28: =IF(D28="","",IFERROR(INDEX(Arquétipos!$B$5:$B$40,MATCH(D28,Arquétipos!$A$5:$A$40,0)),"")) | H28: F5 | I28: Média | J28: Planejada | K28: FN-019 | M28: Não
A29: T-025 | B29: Administração e Segurança | C29: Matriz papel × permissão | D29: Mapping | E29: =IF(D29="","",IFERROR(INDEX(Arquétipos!$B$5:$B$40,MATCH(D29,Arquétipos!$A$5:$A$40,0)),"")) | H29: F5 | I29: Média | J29: Planejada | K29: FN-019 | M29: Não
A30: T-026 | B30: Administração e Segurança | C30: Sessões ativas | D30: List | E30: =IF(D30="","",IFERROR(INDEX(Arquétipos!$B$5:$B$40,MATCH(D30,Arquétipos!$A$5:$A$40,0)),"")) | H30: F5 | I30: Baixa | J30: Planejada | K30: FN-015 | M30: Não
A31: T-027 | B31: Administração e Segurança | C31: Autenticação em dois fatores | D31: Settings | E31: =IF(D31="","",IFERROR(INDEX(Arquétipos!$B$5:$B$40,MATCH(D31,Arquétipos!$A$5:$A$40,0)),"")) | H31: F5 | I31: Média | J31: Planejada | K31: FN-016 | M31: Não
A32: T-028 | B32: Administração e Segurança | C32: Log de acessos | D32: AuditTrail | E32: =IF(D32="","",IFERROR(INDEX(Arquétipos!$B$5:$B$40,MATCH(D32,Arquétipos!$A$5:$A$40,0)),"")) | H32: F5 | I32: Baixa | J32: Planejada | K32: FN-113 | M32: Não
A33: T-029 | B33: Administração e Segurança | C33: Integrações e chaves de API | D33: Settings | E33: =IF(D33="","",IFERROR(INDEX(Arquétipos!$B$5:$B$40,MATCH(D33,Arquétipos!$A$5:$A$40,0)),"")) | H33: F6 | I33: Baixa | J33: Planejada | K33: FN-111 | M33: Não
A34: T-030 | B34: Administração e Segurança | C34: Backup e restauração | D34: Wizard | E34: =IF(D34="","",IFERROR(INDEX(Arquétipos!$B$5:$B$40,MATCH(D34,Arquétipos!$A$5:$A$40,0)),"")) | H34: F6 | I34: Média | J34: Planejada | K34: FN-012 | M34: Não
A35: T-031 | B35: Plano de Contas | C35: Plano de contas | D35: Tree | E35: =IF(D35="","",IFERROR(INDEX(Arquétipos!$B$5:$B$40,MATCH(D35,Arquétipos!$A$5:$A$40,0)),"")) | F35: conta | G35: Hierarquia de contas; primeira fatia vertical | H35: F1 | I35: Alta | J35: Planejada | K35: FN-026, FN-029 | L35: T-003 | M35: Não
A36: T-032 | B36: Plano de Contas | C36: Conta | D36: Form | E36: =IF(D36="","",IFERROR(INDEX(Arquétipos!$B$5:$B$40,MATCH(D36,Arquétipos!$A$5:$A$40,0)),"")) | F36: conta | H36: F1 | I36: Alta | J36: Planejada | K36: FN-027, FN-028, FN-024, FN-023, FN-025 | L36: T-031 | M36: Não
A37: T-033 | B37: Plano de Contas | C37: Detalhe da conta (saldo e movimento) | D37: Detail | E37: =IF(D37="","",IFERROR(INDEX(Arquétipos!$B$5:$B$40,MATCH(D37,Arquétipos!$A$5:$A$40,0)),"")) | F37: conta | H37: F1 | I37: Média | J37: Planejada | K37: FN-051, FN-052 | L37: T-031 | M37: Não
A38: T-034 | B38: Plano de Contas | C38: Naturezas e tipos de conta | D38: List | E38: =IF(D38="","",IFERROR(INDEX(Arquétipos!$B$5:$B$40,MATCH(D38,Arquétipos!$A$5:$A$40,0)),"")) | H38: F1 | I38: Média | J38: Planejada | M38: Não
A39: T-035 | B39: Plano de Contas | C39: Importar plano de contas | D39: Import | E39: =IF(D39="","",IFERROR(INDEX(Arquétipos!$B$5:$B$40,MATCH(D39,Arquétipos!$A$5:$A$40,0)),"")) | H39: F2 | I39: Média | J39: Planejada | K39: FN-031, FN-109 | L39: T-031 | M39: Não
A40: T-036 | B40: Plano de Contas | C40: Mapeamento para plano referencial | D40: Mapping | E40: =IF(D40="","",IFERROR(INDEX(Arquétipos!$B$5:$B$40,MATCH(D40,Arquétipos!$A$5:$A$40,0)),"")) | H40: F3 | I40: Média | J40: Planejada | K40: FN-032 | L40: T-031 | M40: Não
A41: T-037 | B41: Plano de Contas | C41: Edição em lote de contas | D41: BulkEdit | E41: =IF(D41="","",IFERROR(INDEX(Arquétipos!$B$5:$B$40,MATCH(D41,Arquétipos!$A$5:$A$40,0)),"")) | H41: F3 | I41: Baixa | J41: Planejada | K41: FN-028 | L41: T-031 | M41: Não
A42: T-038 | B42: Plano de Contas | C42: Histórico de alterações da conta | D42: AuditTrail | E42: =IF(D42="","",IFERROR(INDEX(Arquétipos!$B$5:$B$40,MATCH(D42,Arquétipos!$A$5:$A$40,0)),"")) | H42: F5 | I42: Baixa | J42: Planejada | K42: FN-113 | M42: Não
A43: T-039 | B43: Plano de Contas | C43: Planos referenciais | D43: List | E43: =IF(D43="","",IFERROR(INDEX(Arquétipos!$B$5:$B$40,MATCH(D43,Arquétipos!$A$5:$A$40,0)),"")) | H43: F5 | I43: Baixa | J43: Planejada | M43: Não
A44: T-040 | B44: Plano de Contas | C44: Desativar conta com saldo (transferência) | D44: Wizard | E44: =IF(D44="","",IFERROR(INDEX(Arquétipos!$B$5:$B$40,MATCH(D44,Arquétipos!$A$5:$A$40,0)),"")) | H44: F4 | I44: Baixa | J44: Planejada | K44: FN-030 | M44: Não
A45: T-041 | B45: Lançamentos e Diários | C45: Diários | D45: List | E45: =IF(D45="","",IFERROR(INDEX(Arquétipos!$B$5:$B$40,MATCH(D45,Arquétipos!$A$5:$A$40,0)),"")) | H45: F1 | I45: Alta | J45: Planejada | K45: FN-038 | M45: Não
A46: T-042 | B46: Lançamentos e Diários | C46: Diário | D46: Form | E46: =IF(D46="","",IFERROR(INDEX(Arquétipos!$B$5:$B$40,MATCH(D46,Arquétipos!$A$5:$A$40,0)),"")) | H46: F1 | I46: Alta | J46: Planejada | K46: FN-038 | L46: T-041 | M46: Não
A47: T-043 | B47: Lançamentos e Diários | C47: Lançamentos | D47: List | E47: =IF(D47="","",IFERROR(INDEX(Arquétipos!$B$5:$B$40,MATCH(D47,Arquétipos!$A$5:$A$40,0)),"")) | F47: lancamento | H47: F1 | I47: Alta | J47: Planejada | K47: FN-043 | L47: T-041 | M47: Não
A48: T-044 | B48: Lançamentos e Diários | C48: Lançamento (cabeçalho e partidas) | D48: MasterDetail | E48: =IF(D48="","",IFERROR(INDEX(Arquétipos!$B$5:$B$40,MATCH(D48,Arquétipos!$A$5:$A$40,0)),"")) | F48: lancamento | G48: Núcleo contábil; invariantes avaliadas no domínio | H48: F1 | I48: Alta | J48: Planejada | K48: FN-039, FN-040, FN-041, FN-042, FN-033, FN-034, FN-035, FN-112 | L48: T-031, T-041 | M48: Não
A49: T-045 | B49: Lançamentos e Diários | C49: Detalhe do lançamento | D49: Detail | E49: =IF(D49="","",IFERROR(INDEX(Arquétipos!$B$5:$B$40,MATCH(D49,Arquétipos!$A$5:$A$40,0)),"")) | F49: lancamento | H49: F1 | I49: Alta | J49: Planejada | K49: FN-043 | L49: T-043 | M49: Não
A50: T-046 | B50: Lançamentos e Diários | C50: Estorno de lançamento | D50: Wizard | E50: =IF(D50="","",IFERROR(INDEX(Arquétipos!$B$5:$B$40,MATCH(D50,Arquétipos!$A$5:$A$40,0)),"")) | H50: F2 | I50: Alta | J50: Planejada | K50: FN-044 | L50: T-044 | M50: Não
A51: T-047 | B51: Lançamentos e Diários | C51: Saldos iniciais (abertura) | D51: Wizard | E51: =IF(D51="","",IFERROR(INDEX(Arquétipos!$B$5:$B$40,MATCH(D51,Arquétipos!$A$5:$A$40,0)),"")) | H51: F2 | I51: Alta | J51: Planejada | K51: FN-045 | L51: T-031 | M51: Não
A52: T-048 | B52: Lançamentos e Diários | C52: Rascunhos pendentes de postagem | D52: Inbox | E52: =IF(D52="","",IFERROR(INDEX(Arquétipos!$B$5:$B$40,MATCH(D52,Arquétipos!$A$5:$A$40,0)),"")) | H52: F2 | I52: Média | J52: Planejada | K52: FN-041 | L52: T-044 | M52: Não
A53: T-049 | B53: Lançamentos e Diários | C53: Trilha do lançamento | D53: AuditTrail | E53: =IF(D53="","",IFERROR(INDEX(Arquétipos!$B$5:$B$40,MATCH(D53,Arquétipos!$A$5:$A$40,0)),"")) | H53: F2 | I53: Média | J53: Planejada | K53: FN-113 | L53: T-044 | M53: Não
A54: T-050 | B54: Lançamentos e Diários | C54: Modelos de lançamento | D54: List | E54: =IF(D54="","",IFERROR(INDEX(Arquétipos!$B$5:$B$40,MATCH(D54,Arquétipos!$A$5:$A$40,0)),"")) | H54: F3 | I54: Média | J54: Planejada | K54: FN-046 | M54: Não
A55: T-051 | B55: Lançamentos e Diários | C55: Modelo de lançamento | D55: Form | E55: =IF(D55="","",IFERROR(INDEX(Arquétipos!$B$5:$B$40,MATCH(D55,Arquétipos!$A$5:$A$40,0)),"")) | H55: F3 | I55: Média | J55: Planejada | K55: FN-046 | M55: Não
A56: T-052 | B56: Lançamentos e Diários | C56: Postagem em lote | D56: Wizard | E56: =IF(D56="","",IFERROR(INDEX(Arquétipos!$B$5:$B$40,MATCH(D56,Arquétipos!$A$5:$A$40,0)),"")) | H56: F3 | I56: Média | J56: Planejada | K56: FN-047 | L56: T-043 | M56: Não
A57: T-053 | B57: Lançamentos e Diários | C57: Importar lançamentos | D57: Import | E57: =IF(D57="","",IFERROR(INDEX(Arquétipos!$B$5:$B$40,MATCH(D57,Arquétipos!$A$5:$A$40,0)),"")) | H57: F3 | I57: Média | J57: Planejada | K57: FN-048, FN-109 | L57: T-044 | M57: Não
A58: T-054 | B58: Lançamentos e Diários | C58: Edição em lote de rascunhos | D58: BulkEdit | E58: =IF(D58="","",IFERROR(INDEX(Arquétipos!$B$5:$B$40,MATCH(D58,Arquétipos!$A$5:$A$40,0)),"")) | H58: F4 | I58: Baixa | J58: Planejada | K58: FN-040 | M58: Não
A59: T-055 | B59: Lançamentos e Diários | C59: Reclassificação de saldos | D59: Wizard | E59: =IF(D59="","",IFERROR(INDEX(Arquétipos!$B$5:$B$40,MATCH(D59,Arquétipos!$A$5:$A$40,0)),"")) | H59: F4 | I59: Baixa | J59: Planejada | M59: Não
A60: T-056 | B60: Razão e Balancetes | C60: Razão | D60: List | E60: =IF(D60="","",IFERROR(INDEX(Arquétipos!$B$5:$B$40,MATCH(D60,Arquétipos!$A$5:$A$40,0)),"")) | F60: conta | H60: F1 | I60: Alta | J60: Planejada | K60: FN-050 | L60: T-031 | M60: Não
A61: T-057 | B61: Razão e Balancetes | C61: Razão por conta | D61: Report | E61: =IF(D61="","",IFERROR(INDEX(Arquétipos!$B$5:$B$40,MATCH(D61,Arquétipos!$A$5:$A$40,0)),"")) | H61: F1 | I61: Alta | J61: Planejada | K61: FN-050, FN-051 | L61: T-056 | M61: Não
A62: T-058 | B62: Razão e Balancetes | C62: Diário geral | D62: Report | E62: =IF(D62="","",IFERROR(INDEX(Arquétipos!$B$5:$B$40,MATCH(D62,Arquétipos!$A$5:$A$40,0)),"")) | H62: F1 | I62: Média | J62: Planejada | K62: FN-054 | M62: Não
A63: T-059 | B63: Razão e Balancetes | C63: Balancete de verificação | D63: Report | E63: =IF(D63="","",IFERROR(INDEX(Arquétipos!$B$5:$B$40,MATCH(D63,Arquétipos!$A$5:$A$40,0)),"")) | G63: Primeiro relatório; valida o núcleo contábil | H63: F1 | I63: Alta | J63: Planejada | K63: FN-053, FN-051 | L63: T-056 | M63: Não
A64: T-060 | B64: Razão e Balancetes | C64: Drill-down: do saldo aos lançamentos | D64: List | E64: =IF(D64="","",IFERROR(INDEX(Arquétipos!$B$5:$B$40,MATCH(D64,Arquétipos!$A$5:$A$40,0)),"")) | H64: F1 | I64: Alta | J64: Planejada | K64: FN-052 | L64: T-059 | M64: Não
A65: T-061 | B65: Razão e Balancetes | C65: Extrato de conta | D65: Report | E65: =IF(D65="","",IFERROR(INDEX(Arquétipos!$B$5:$B$40,MATCH(D65,Arquétipos!$A$5:$A$40,0)),"")) | H65: F2 | I65: Média | J65: Planejada | K65: FN-055 | L65: T-056 | M65: Não
A66: T-062 | B66: Razão e Balancetes | C66: Balancete comparativo (períodos) | D66: Comparative | E66: =IF(D66="","",IFERROR(INDEX(Arquétipos!$B$5:$B$40,MATCH(D66,Arquétipos!$A$5:$A$40,0)),"")) | H66: F4 | I66: Média | J66: Planejada | K66: FN-056 | L66: T-059 | M66: Não
A67: T-063 | B67: Razão e Balancetes | C67: Saldos por conta e período | D67: Pivot | E67: =IF(D67="","",IFERROR(INDEX(Arquétipos!$B$5:$B$40,MATCH(D67,Arquétipos!$A$5:$A$40,0)),"")) | H67: F4 | I67: Média | J67: Planejada | K67: FN-051 | L67: T-059 | M67: Não
A68: T-064 | B68: Razão e Balancetes | C68: Evolução de saldo | D68: Chart | E68: =IF(D68="","",IFERROR(INDEX(Arquétipos!$B$5:$B$40,MATCH(D68,Arquétipos!$A$5:$A$40,0)),"")) | H68: F4 | I68: Baixa | J68: Planejada | K68: FN-051 | M68: Não
A69: T-065 | B69: Períodos e Fechamento | C69: Períodos fiscais | D69: List | E69: =IF(D69="","",IFERROR(INDEX(Arquétipos!$B$5:$B$40,MATCH(D69,Arquétipos!$A$5:$A$40,0)),"")) | H69: F2 | I69: Alta | J69: Planejada | K69: FN-057 | M69: Não
A70: T-066 | B70: Períodos e Fechamento | C70: Exercício fiscal | D70: Form | E70: =IF(D70="","",IFERROR(INDEX(Arquétipos!$B$5:$B$40,MATCH(D70,Arquétipos!$A$5:$A$40,0)),"")) | H70: F2 | I70: Alta | J70: Planejada | K70: FN-057 | L70: T-065 | M70: Não
A71: T-067 | B71: Períodos e Fechamento | C71: Fechamento de período | D71: PeriodClose | E71: =IF(D71="","",IFERROR(INDEX(Arquétipos!$B$5:$B$40,MATCH(D71,Arquétipos!$A$5:$A$40,0)),"")) | H71: F2 | I71: Alta | J71: Planejada | K71: FN-058, FN-059, FN-034 | L71: T-059, T-065 | M71: Não
A72: T-068 | B72: Períodos e Fechamento | C72: Reabertura de período | D72: Wizard | E72: =IF(D72="","",IFERROR(INDEX(Arquétipos!$B$5:$B$40,MATCH(D72,Arquétipos!$A$5:$A$40,0)),"")) | H72: F2 | I72: Média | J72: Planejada | K72: FN-060 | L72: T-067 | M72: Não
A73: T-069 | B73: Períodos e Fechamento | C73: Apuração do resultado | D73: Wizard | E73: =IF(D73="","",IFERROR(INDEX(Arquétipos!$B$5:$B$40,MATCH(D73,Arquétipos!$A$5:$A$40,0)),"")) | H73: F4 | I73: Média | J73: Planejada | K73: FN-062 | L73: T-067 | M73: Não
A74: T-070 | B74: Períodos e Fechamento | C74: Encerramento do exercício | D74: Wizard | E74: =IF(D74="","",IFERROR(INDEX(Arquétipos!$B$5:$B$40,MATCH(D74,Arquétipos!$A$5:$A$40,0)),"")) | H74: F4 | I74: Média | J74: Planejada | K74: FN-061, FN-062 | L74: T-067 | M74: Não
A75: T-071 | B75: Períodos e Fechamento | C75: Calendário de fechamento | D75: Calendar | E75: =IF(D75="","",IFERROR(INDEX(Arquétipos!$B$5:$B$40,MATCH(D75,Arquétipos!$A$5:$A$40,0)),"")) | H75: F4 | I75: Baixa | J75: Planejada | K75: FN-058 | L75: T-065 | M75: Não
A76: T-072 | B76: Cadastros Base | C76: Parceiros | D76: List | E76: =IF(D76="","",IFERROR(INDEX(Arquétipos!$B$5:$B$40,MATCH(D76,Arquétipos!$A$5:$A$40,0)),"")) | H76: F2 | I76: Alta | J76: Planejada | K76: FN-063 | M76: Não
A77: T-073 | B77: Cadastros Base | C77: Parceiro | D77: Form | E77: =IF(D77="","",IFERROR(INDEX(Arquétipos!$B$5:$B$40,MATCH(D77,Arquétipos!$A$5:$A$40,0)),"")) | H77: F2 | I77: Alta | J77: Planejada | K77: FN-063 | L77: T-072 | M77: Não
A78: T-074 | B78: Cadastros Base | C78: Posição do parceiro (saldos e documentos) | D78: Detail | E78: =IF(D78="","",IFERROR(INDEX(Arquétipos!$B$5:$B$40,MATCH(D78,Arquétipos!$A$5:$A$40,0)),"")) | H78: F4 | I78: Média | J78: Planejada | K78: FN-063 | L78: T-072 | M78: Não
A79: T-075 | B79: Cadastros Base | C79: Centros de custo | D79: Tree | E79: =IF(D79="","",IFERROR(INDEX(Arquétipos!$B$5:$B$40,MATCH(D79,Arquétipos!$A$5:$A$40,0)),"")) | H79: F2 | I79: Média | J79: Planejada | K79: FN-064 | M79: Não
A80: T-076 | B80: Cadastros Base | C80: Centro de custo | D80: Form | E80: =IF(D80="","",IFERROR(INDEX(Arquétipos!$B$5:$B$40,MATCH(D80,Arquétipos!$A$5:$A$40,0)),"")) | H80: F2 | I80: Média | J80: Planejada | K80: FN-064 | M80: Não
A81: T-077 | B81: Cadastros Base | C81: Dimensões analíticas | D81: List | E81: =IF(D81="","",IFERROR(INDEX(Arquétipos!$B$5:$B$40,MATCH(D81,Arquétipos!$A$5:$A$40,0)),"")) | H81: F3 | I81: Média | J81: Planejada | K81: FN-065 | M81: Não
A82: T-078 | B82: Cadastros Base | C82: Condições de pagamento | D82: List | E82: =IF(D82="","",IFERROR(INDEX(Arquétipos!$B$5:$B$40,MATCH(D82,Arquétipos!$A$5:$A$40,0)),"")) | H82: F3 | I82: Média | J82: Planejada | K82: FN-066 | M82: Não
A83: T-079 | B83: Cadastros Base | C83: Contas bancárias | D83: List | E83: =IF(D83="","",IFERROR(INDEX(Arquétipos!$B$5:$B$40,MATCH(D83,Arquétipos!$A$5:$A$40,0)),"")) | H83: F3 | I83: Alta | J83: Planejada | K83: FN-067 | M83: Não
A84: T-080 | B84: Cadastros Base | C84: Conta bancária | D84: Form | E84: =IF(D84="","",IFERROR(INDEX(Arquétipos!$B$5:$B$40,MATCH(D84,Arquétipos!$A$5:$A$40,0)),"")) | H84: F3 | I84: Alta | J84: Planejada | K84: FN-067 | L84: T-079 | M84: Não
A85: T-081 | B85: Cadastros Base | C85: Departamentos e unidades | D85: Tree | E85: =IF(D85="","",IFERROR(INDEX(Arquétipos!$B$5:$B$40,MATCH(D85,Arquétipos!$A$5:$A$40,0)),"")) | H85: F5 | I85: Baixa | J85: Planejada | M85: Não
A86: T-082 | B86: Moedas e Câmbio | C86: Moedas | D86: List | E86: =IF(D86="","",IFERROR(INDEX(Arquétipos!$B$5:$B$40,MATCH(D86,Arquétipos!$A$5:$A$40,0)),"")) | H86: F2 | I86: Alta | J86: Planejada | M86: Não
A87: T-083 | B87: Moedas e Câmbio | C87: Moeda | D87: Form | E87: =IF(D87="","",IFERROR(INDEX(Arquétipos!$B$5:$B$40,MATCH(D87,Arquétipos!$A$5:$A$40,0)),"")) | H87: F2 | I87: Média | J87: Planejada | M87: Não
A88: T-084 | B88: Moedas e Câmbio | C88: Taxas de câmbio | D88: List | E88: =IF(D88="","",IFERROR(INDEX(Arquétipos!$B$5:$B$40,MATCH(D88,Arquétipos!$A$5:$A$40,0)),"")) | H88: F2 | I88: Alta | J88: Planejada | K88: FN-068, FN-069 | M88: Não
A89: T-085 | B89: Moedas e Câmbio | C89: Importar taxas | D89: Import | E89: =IF(D89="","",IFERROR(INDEX(Arquétipos!$B$5:$B$40,MATCH(D89,Arquétipos!$A$5:$A$40,0)),"")) | H89: F3 | I89: Baixa | J89: Planejada | K89: FN-070, FN-109 | M89: Não
A90: T-086 | B90: Moedas e Câmbio | C90: Reavaliação cambial | D90: Wizard | E90: =IF(D90="","",IFERROR(INDEX(Arquétipos!$B$5:$B$40,MATCH(D90,Arquétipos!$A$5:$A$40,0)),"")) | H90: F4 | I90: Média | J90: Planejada | K90: FN-071 | M90: Não
A91: T-087 | B91: Moedas e Câmbio | C91: Conversão de saldos | D91: Report | E91: =IF(D91="","",IFERROR(INDEX(Arquétipos!$B$5:$B$40,MATCH(D91,Arquétipos!$A$5:$A$40,0)),"")) | H91: F4 | I91: Baixa | J91: Planejada | K91: FN-069 | M91: Não
A92: T-088 | B92: Contas a Pagar | C92: Faturas de fornecedor | D92: List | E92: =IF(D92="","",IFERROR(INDEX(Arquétipos!$B$5:$B$40,MATCH(D92,Arquétipos!$A$5:$A$40,0)),"")) | H92: F3 | I92: Alta | J92: Planejada | K92: FN-072 | L92: T-072 | M92: Não
A93: T-089 | B93: Contas a Pagar | C93: Fatura de fornecedor | D93: MasterDetail | E93: =IF(D93="","",IFERROR(INDEX(Arquétipos!$B$5:$B$40,MATCH(D93,Arquétipos!$A$5:$A$40,0)),"")) | H93: F3 | I93: Alta | J93: Planejada | K93: FN-072, FN-073 | L93: T-072, T-044 | M93: Não
A94: T-090 | B94: Contas a Pagar | C94: Pagamentos a fornecedores | D94: List | E94: =IF(D94="","",IFERROR(INDEX(Arquétipos!$B$5:$B$40,MATCH(D94,Arquétipos!$A$5:$A$40,0)),"")) | H94: F3 | I94: Alta | J94: Planejada | K94: FN-074 | L94: T-088 | M94: Não
A95: T-091 | B95: Contas a Pagar | C95: Pagamento a fornecedor | D95: Form | E95: =IF(D95="","",IFERROR(INDEX(Arquétipos!$B$5:$B$40,MATCH(D95,Arquétipos!$A$5:$A$40,0)),"")) | H95: F3 | I95: Alta | J95: Planejada | K95: FN-074, FN-075 | L95: T-088 | M95: Não
A96: T-092 | B96: Contas a Pagar | C96: Lote de pagamentos | D96: Wizard | E96: =IF(D96="","",IFERROR(INDEX(Arquétipos!$B$5:$B$40,MATCH(D96,Arquétipos!$A$5:$A$40,0)),"")) | H96: F4 | I96: Média | J96: Planejada | K96: FN-076 | L96: T-088 | M96: Não
A97: T-093 | B97: Contas a Pagar | C97: Aprovação de pagamentos | D97: Inbox | E97: =IF(D97="","",IFERROR(INDEX(Arquétipos!$B$5:$B$40,MATCH(D97,Arquétipos!$A$5:$A$40,0)),"")) | H97: F4 | I97: Média | J97: Planejada | K97: FN-077 | M97: Não
A98: T-094 | B98: Contas a Pagar | C98: Vencimentos a pagar | D98: Calendar | E98: =IF(D98="","",IFERROR(INDEX(Arquétipos!$B$5:$B$40,MATCH(D98,Arquétipos!$A$5:$A$40,0)),"")) | H98: F4 | I98: Média | J98: Planejada | L98: T-088 | M98: Não
A99: T-095 | B99: Contas a Pagar | C99: Aging de contas a pagar | D99: Report | E99: =IF(D99="","",IFERROR(INDEX(Arquétipos!$B$5:$B$40,MATCH(D99,Arquétipos!$A$5:$A$40,0)),"")) | H99: F4 | I99: Média | J99: Planejada | K99: FN-078 | L99: T-088 | M99: Não
A100: T-096 | B100: Contas a Receber | C100: Faturas de cliente | D100: List | E100: =IF(D100="","",IFERROR(INDEX(Arquétipos!$B$5:$B$40,MATCH(D100,Arquétipos!$A$5:$A$40,0)),"")) | H100: F3 | I100: Alta | J100: Planejada | K100: FN-079 | L100: T-072 | M100: Não
...

Sheet Funções
A1: Function inventory — repository mapping and English identifiers
A2: English identifiers are proposed translations of legacy catalog names, not Rust symbol names. Parent-module mappings are hypotheses until checked against code.
M3: Repository roadmap phase; classify after checking each function. | N3: Code path, test, PR, or command proving actual implementation. | O3: Proposed English identifier; not necessarily an existing symbol. | P3: Parent module/crate that should own the capability. | Q3: Submodule or capability area. | R3: Repository entry point. Confirm exact file/symbol. | S3: Confidence / follow-up required.
A4: Function ID | B4: Legacy Module Label | C4: Legacy Function / Command | D4: Function Type | E4: Description (Portuguese source) | F4: Legacy Phase (not repository phase) | G4: Priority | H4: Inventory Status (unverified) | I4: Screens Using (IDs) | J4: CLI / Ratatui Verified | K4: Tests | L4: Notes | M4: Repository Phase (reclassify) | N4: Repository Evidence | O4: Function / Command (English) | P4: Parent Module | Q4: Submodule / Capability | R4: Repository Link | S4: Mapping Confidence
A5: FN-001 | B5: Fundação e Infraestrutura | C5: kodoo_view.validar_spec | D5: Infra | E5: Validação estrutural de ViewSpec (esqueleto gerado, não compilado) | F5: F0 | G5: Alta | H5: Em andamento | I5: T-015 | J5: Não | K5: Não | O5: kodoo_view.validate_spec | P5: kodoo-core | Q5: foundation / infrastructure | R5: https://github.com/bootstrapprx/kodoo/tree/main/crates/kodoo-core | S5: Conceptual mapping; confirm exact crate
A6: FN-002 | B6: Fundação e Infraestrutura | C6: ui.renderizar_arquetipo | D6: Infra | E6: Renderizador genérico por arquétipo (Dioxus) | F6: F0 | G6: Alta | H6: Planejada | I6: T-014 | J6: Não | K6: Não | O6: ui.renderizar_arquetipo | P6: kodoo-core | Q6: foundation / infrastructure | R6: https://github.com/bootstrapprx/kodoo/tree/main/crates/kodoo-core | S6: Conceptual mapping; confirm exact crate
A7: FN-003 | B7: Fundação e Infraestrutura | C7: dev.fixtures_carregar | D7: Infra | E7: Dados de teste tipados para as telas | F7: F0 | G7: Alta | H7: Planejada | I7: T-014 | J7: Não | K7: Não | O7: dev.fixtures_carregar | P7: kodoo-core | Q7: foundation / infrastructure | R7: https://github.com/bootstrapprx/kodoo/tree/main/crates/kodoo-core | S7: Conceptual mapping; confirm exact crate
A8: FN-004 | B8: Fundação e Infraestrutura | C8: dominio.repositorio | D8: Infra | E8: Interface de repositório extraída do que as telas pedem | F8: F1 | G8: Alta | H8: Planejada | J8: Não | K8: Não | O8: dominio.repository | P8: kodoo-core | Q8: foundation / infrastructure | R8: https://github.com/bootstrapprx/kodoo/tree/main/crates/kodoo-core | S8: Conceptual mapping; confirm exact crate
A9: FN-005 | B9: Fundação e Infraestrutura | C9: db.migrar_esquema | D9: Infra | E9: Migrações do PostgreSQL | F9: F1 | G9: Alta | H9: Planejada | J9: Não | K9: Não | O9: db.migrar_esquema | P9: kodoo-core | Q9: foundation / infrastructure | R9: https://github.com/bootstrapprx/kodoo/tree/main/crates/kodoo-core | S9: Conceptual mapping; confirm exact crate
A10: FN-006 | B10: Fundação e Infraestrutura | C10: api.servidor_base | D10: Infra | E10: API: rotas, erros e versionamento | F10: F1 | G10: Alta | H10: Planejada | J10: Não | K10: Não | O10: api.servidor_base | P10: kodoo-core | Q10: foundation / infrastructure | R10: https://github.com/bootstrapprx/kodoo/tree/main/crates/kodoo-core | S10: Conceptual mapping; confirm exact crate
A11: FN-007 | B11: Fundação e Infraestrutura | C11: cli.comando_base | D11: Infra | E11: CLI com os mesmos nomes de comando do domínio | F11: F1 | G11: Alta | H11: Planejada | I11: T-016 | J11: Não | K11: Não | O11: cli.comando_base | P11: kodoo-core | Q11: foundation / infrastructure | R11: https://github.com/bootstrapprx/kodoo/tree/main/crates/kodoo-core | S11: Conceptual mapping; confirm exact crate
A12: FN-008 | B12: Fundação e Infraestrutura | C12: tui.verificador | D12: Infra | E12: Ratatui para verificação direta de funções | F12: F1 | G12: Média | H12: Planejada | I12: T-016 | J12: Não | K12: Não | O12: tui.verifier | P12: kodoo-core | Q12: foundation / infrastructure | R12: https://github.com/bootstrapprx/kodoo/tree/main/crates/kodoo-core | S12: Conceptual mapping; confirm exact crate
A13: FN-009 | B13: Fundação e Infraestrutura | C13: db.seed_demo | D13: Infra | E13: Dados de demonstração no banco | F13: F1 | G13: Média | H13: Planejada | J13: Não | K13: Não | O13: db.seed_demo | P13: kodoo-core | Q13: foundation / infrastructure | R13: https://github.com/bootstrapprx/kodoo/tree/main/crates/kodoo-core | S13: Conceptual mapping; confirm exact crate
A14: FN-010 | B14: Fundação e Infraestrutura | C14: ui.i18n_carregar | D14: Infra | E14: Carregar traduções (pt-BR e en) | F14: F2 | G14: Média | H14: Planejada | I14: T-009 | J14: Não | K14: Não | O14: ui.i18n_carregar | P14: kodoo-core | Q14: foundation / infrastructure | R14: https://github.com/bootstrapprx/kodoo/tree/main/crates/kodoo-core | S14: Conceptual mapping; confirm exact crate
A15: FN-011 | B15: Fundação e Infraestrutura | C15: infra.provisionar_organizacao | D15: Infra | E15: Provisionar organização (multi-tenant) | F15: F6 | G15: Baixa | H15: Planejada | J15: Não | K15: Não | O15: infra.provisionar_organization | P15: kodoo-core | Q15: foundation / infrastructure | R15: https://github.com/bootstrapprx/kodoo/tree/main/crates/kodoo-core | S15: Conceptual mapping; confirm exact crate
A16: FN-012 | B16: Fundação e Infraestrutura | C16: infra.backup_restaurar | D16: Infra | E16: Backup e restauração | F16: F6 | G16: Média | H16: Planejada | I16: T-030 | J16: Não | K16: Não | O16: infra.backup_restaurar | P16: kodoo-core | Q16: foundation / infrastructure | R16: https://github.com/bootstrapprx/kodoo/tree/main/crates/kodoo-core | S16: Conceptual mapping; confirm exact crate
A17: FN-013 | B17: Administração e Segurança | C17: auth.autenticar | D17: Segurança | E17: Login e emissão de sessão | F17: F0 | G17: Alta | H17: Planejada | I17: T-001 | J17: Não | K17: Não | O17: auth.authenticate | P17: kodoo-core | Q17: identity / authorization (verify ownership) | R17: https://github.com/bootstrapprx/kodoo/tree/main/crates/kodoo-core | S17: Conceptual mapping; confirm exact crate
A18: FN-014 | B18: Administração e Segurança | C18: auth.autorizar | D18: Segurança | E18: Checagem de permissão por tela e ação | F18: F1 | G18: Alta | H18: Planejada | I18: T-002, T-005 | J18: Não | K18: Não | O18: auth.authorize | P18: kodoo-core | Q18: identity / authorization (verify ownership) | R18: https://github.com/bootstrapprx/kodoo/tree/main/crates/kodoo-core | S18: Conceptual mapping; confirm exact crate
A19: FN-015 | B19: Administração e Segurança | C19: auth.renovar_sessao | D19: Segurança | E19: Renovar e encerrar sessão | F19: F2 | G19: Média | H19: Planejada | I19: T-026 | J19: Não | K19: Não | O19: auth.renovar_session | P19: kodoo-core | Q19: identity / authorization (verify ownership) | R19: https://github.com/bootstrapprx/kodoo/tree/main/crates/kodoo-core | S19: Conceptual mapping; confirm exact crate
A20: FN-016 | B20: Administração e Segurança | C20: auth.mfa | D20: Segurança | E20: Segundo fator de autenticação | F20: F5 | G20: Média | H20: Planejada | I20: T-027 | J20: Não | K20: Não | O20: auth.mfa | P20: kodoo-core | Q20: identity / authorization (verify ownership) | R20: https://github.com/bootstrapprx/kodoo/tree/main/crates/kodoo-core | S20: Conceptual mapping; confirm exact crate
A21: FN-017 | B21: Administração e Segurança | C21: auth.recuperar_senha | D21: Segurança | E21: Recuperação de senha | F21: F5 | G21: Média | H21: Planejada | I21: T-013 | J21: Não | K21: Não | O21: auth.recuperar_senha | P21: kodoo-core | Q21: identity / authorization (verify ownership) | R21: https://github.com/bootstrapprx/kodoo/tree/main/crates/kodoo-core | S21: Conceptual mapping; confirm exact crate
A22: FN-018 | B22: Administração e Segurança | C22: admin.usuario.gerir | D22: Comando | E22: Criar, editar e desativar usuário | F22: F5 | G22: Média | H22: Planejada | I22: T-021, T-022 | J22: Não | K22: Não | O22: admin.user.manage | P22: kodoo-core | Q22: identity / authorization (verify ownership) | R22: https://github.com/bootstrapprx/kodoo/tree/main/crates/kodoo-core | S22: Conceptual mapping; confirm exact crate
A23: FN-019 | B23: Administração e Segurança | C23: admin.papel.gerir | D23: Comando | E23: Papéis e permissões | F23: F5 | G23: Média | H23: Planejada | I23: T-023, T-024, T-025 | J23: Não | K23: Não | O23: admin.role.manage | P23: kodoo-core | Q23: identity / authorization (verify ownership) | R23: https://github.com/bootstrapprx/kodoo/tree/main/crates/kodoo-core | S23: Conceptual mapping; confirm exact crate
A24: FN-020 | B24: Administração e Segurança | C24: admin.organizacao.gerir | D24: Comando | E24: Organização ou empresa | F24: F2 | G24: Alta | H24: Planejada | I24: T-007, T-017, T-018 | J24: Não | K24: Não | O24: admin.organization.manage | P24: kodoo-core | Q24: identity / authorization (verify ownership) | R24: https://github.com/bootstrapprx/kodoo/tree/main/crates/kodoo-core | S24: Conceptual mapping; confirm exact crate
A25: FN-021 | B25: Administração e Segurança | C25: admin.parametros.salvar | D25: Comando | E25: Parâmetros gerais | F25: F2 | G25: Média | H25: Planejada | I25: T-019 | J25: Não | K25: Não | O25: admin.settings.save | P25: kodoo-core | Q25: identity / authorization (verify ownership) | R25: https://github.com/bootstrapprx/kodoo/tree/main/crates/kodoo-core | S25: Conceptual mapping; confirm exact crate
A26: FN-022 | B26: Administração e Segurança | C26: admin.sequencia.proximo | D26: Comando | E26: Numeração sequencial | F26: F2 | G26: Média | H26: Planejada | I26: T-020 | J26: Não | K26: Não | O26: admin.sequencia.next | P26: kodoo-core | Q26: identity / authorization (verify ownership) | R26: https://github.com/bootstrapprx/kodoo/tree/main/crates/kodoo-core | S26: Conceptual mapping; confirm exact crate
A27: FN-023 | B27: Plano de Contas | C27: contabil.invariante.hierarquia_sem_ciclos | D27: Invariante | E27: Plano de contas sem ciclos | F27: F1 | G27: Alta | H27: Planejada | I27: T-032 | J27: Não | K27: Não | O27: contabil.invariant.hierarquia_sem_ciclos | P27: accounting | Q27: chart | R27: https://github.com/bootstrapprx/kodoo/tree/main/modules/accounting | S27: Likely mapping; confirm exact function
... A39: FN-035 | B39: Lançamentos e Diários | C39: contabil.invariante.imutavel_postado | D39: Invariante | E39: Lançamento postado não é alterado | F39: F1 | G39: Alta | H39: Planejada | I39: T-044 | J39: Não | K39: Não | O39: contabil.invariant.imutavel_postado | P39: accounting | Q39: core / journal | R39: https://github.com/bootstrapprx/kodoo/tree/main/modules/accounting | S39: Likely mapping; confirm exact function
A40: FN-036 | B40: Lançamentos e Diários | C40: contabil.invariante.moeda_consistente | D40: Invariante | E40: Consistência de moeda nas partidas | F40: F2 | G40: Média | H40: Planejada | J40: Não | K40: Não | O40: contabil.invariant.currency_consistente | P40: accounting | Q40: core / journal | R40: https://github.com/bootstrapprx/kodoo/tree/main/modules/accounting | S40: Likely mapping; confirm exact function
A41: FN-037 | B41: Lançamentos e Diários | C41: contabil.invariante.numeracao_sem_lacunas | D41: Invariante | E41: Numeração sem lacunas | F41: F2 | G41: Média | H41: Planejada | I41: T-020 | J41: Não | K41: Não | O41: contabil.invariant.numeracao_sem_lacunas | P41: accounting | Q41: core / journal | R41: https://github.com/bootstrapprx/kodoo/tree/main/modules/accounting | S41: Likely mapping; confirm exact function
A42: FN-038 | B42: Lançamentos e Diários | C42: contabil.diario.gerir | D42: Comando | E42: Criar e editar diário | F42: F1 | G42: Alta | H42: Planejada | I42: T-041, T-042 | J42: Não | K42: Não | O42: contabil.journal.manage | P42: accounting | Q42: core / journal | R42: https://github.com/bootstrapprx/kodoo/tree/main/modules/accounting | S42: Likely mapping; confirm exact function
A43: FN-039 | B43: Lançamentos e Diários | C43: contabil.lancamento.criar_rascunho | D43: Comando | E43: Criar lançamento em rascunho | F43: F1 | G43: Alta | H43: Planejada | I43: T-044 | J43: Não | K43: Não | O43: contabil.lancamento.create_rascunho | P43: accounting | Q43: core / journal | R43: https://github.com/bootstrapprx/kodoo/tree/main/modules/accounting | S43: Likely mapping; confirm exact function
A44: FN-040 | B44: Lançamentos e Diários | C44: contabil.lancamento.editar_rascunho | D44: Comando | E44: Editar rascunho | F44: F1 | G44: Alta | H44: Planejada | I44: T-044, T-054 | J44: Não | K44: Não | O44: contabil.lancamento.update_rascunho | P44: accounting | Q44: core / journal | R44: https://github.com/bootstrapprx/kodoo/tree/main/modules/accounting | S44: Likely mapping; confirm exact function
A45: FN-041 | B45: Lançamentos e Diários | C45: contabil.lancamento.postar | D45: Comando | E45: Postar lançamento | F45: F1 | G45: Alta | H45: Planejada | I45: T-044, T-048 | J45: Não | K45: Não | O45: contabil.lancamento.postar | P45: accounting | Q45: core / journal | R45: https://github.com/bootstrapprx/kodoo/tree/main/modules/accounting | S45: Likely mapping; confirm exact function
A46: FN-042 | B46: Lançamentos e Diários | C46: contabil.lancamento.excluir_rascunho | D46: Comando | E46: Excluir rascunho | F46: F1 | G46: Média | H46: Planejada | I46: T-044 | J46: Não | K46: Não | O46: contabil.lancamento.excluir_rascunho | P46: accounting | Q46: core / journal | R46: https://github.com/bootstrapprx/kodoo/tree/main/modules/accounting | S46: Likely mapping; confirm exact function
A47: FN-043 | B47: Lançamentos e Diários | C47: contabil.lancamento.listar | D47: Consulta | E47: Consultar lançamentos com filtros | F47: F1 | G47: Alta | H47: Planejada | I47: T-043, T-045 | J47: Não | K47: Não | O47: contabil.lancamento.list | P47: accounting | Q47: core / journal | R47: https://github.com/bootstrapprx/kodoo/tree/main/modules/accounting | S47: Likely mapping; confirm exact function
A48: FN-044 | B48: Lançamentos e Diários | C48: contabil.lancamento.estornar | D48: Comando | E48: Estornar lançamento postado | F48: F2 | G48: Alta | H48: Planejada | I48: T-046 | J48: Não | K48: Não | O48: contabil.lancamento.reverse | P48: accounting | Q48: core / journal | R48: https://github.com/bootstrapprx/kodoo/tree/main/modules/accounting | S48: Likely mapping; confirm exact function
A49: FN-045 | B49: Lançamentos e Diários | C49: contabil.saldo_inicial.lancar | D49: Comando | E49: Lançar saldos iniciais | F49: F2 | G49: Alta | H49: Planejada | I49: T-047 | J49: Não | K49: Não | O49: contabil.balance_inicial.post | P49: accounting | Q49: core / journal | R49: https://github.com/bootstrapprx/kodoo/tree/main/modules/accounting | S49: Likely mapping; confirm exact function
A50: FN-046 | B50: Lançamentos e Diários | C50: contabil.lancamento.modelo | D50: Comando | E50: Modelos e lançamentos recorrentes | F50: F3 | G50: Média | H50: Planejada | I50: T-050, T-051 | J50: Não | K50: Não | O50: contabil.lancamento.modelo | P50: accounting | Q50: core / journal | R50: https://github.com/bootstrapprx/kodoo/tree/main/modules/accounting | S50: Likely mapping; confirm exact function
A51: FN-047 | B51: Lançamentos e Diários | C51: contabil.lancamento.postar_lote | D51: Comando | E51: Postagem em lote | F51: F3 | G51: Média | H51: Planejada | I51: T-052 | J51: Não | K51: Não | O51: contabil.lancamento.postar_batch | P51: accounting | Q51: core / journal | R51: https://github.com/bootstrapprx/kodoo/tree/main/modules/accounting | S51: Likely mapping; confirm exact function
A52: FN-048 | B52: Lançamentos e Diários | C52: contabil.lancamento.importar | D52: Importação | E52: Importar lançamentos | F52: F3 | G52: Média | H52: Planejada | I52: T-053 | J52: Não | K52: Não | O52: contabil.lancamento.import | P52: accounting | Q52: core / journal | R52: https://github.com/bootstrapprx/kodoo/tree/main/modules/accounting | S52: Likely mapping; confirm exact function
A53: FN-049 | B53: Lançamentos e Diários | C53: contabil.lancamento.duplicar | D53: Comando | E53: Duplicar lançamento | F53: F3 | G53: Baixa | H53: Planejada | J53: Não | K53: Não | O53: contabil.lancamento.duplicate | P53: accounting | Q53: core / journal | R53: https://github.com/bootstrapprx/kodoo/tree/main/modules/accounting | S53: Likely mapping; confirm exact function
A54: FN-050 | B54: Razão e Balancetes | C54: contabil.razao.consultar | D54: Consulta | E54: Razão por conta e período | F54: F1 | G54: Alta | H54: Planejada | I54: T-056, T-057 | J54: Não | K54: Não | O54: contabil.general_ledger.query | P54: accounting | Q54: reports / ledger | R54: https://github.com/bootstrapprx/kodoo/tree/main/modules/accounting | S54: Likely mapping; confirm exact function
A55: FN-051 | B55: Razão e Balancetes | C55: contabil.saldo.calcular | D55: Cálculo | E55: Saldo de conta em uma data | F55: F1 | G55: Alta | H55: Planejada | I55: T-033, T-057, T-059, T-063, T-064, T-108, T-123, T-170 | J55: Não | K55: Não | O55: contabil.balance.calculate | P55: accounting | Q55: reports / ledger | R55: https://github.com/bootstrapprx/kodoo/tree/main/modules/accounting | S55: Likely mapping; confirm exact function
A56: FN-052 | B56: Razão e Balancetes | C56: contabil.saldo.detalhar | D56: Consulta | E56: Do saldo aos lançamentos de origem | F56: F1 | G56: Alta | H56: Planejada | I56: T-033, T-060 | J56: Não | K56: Não | O56: contabil.balance.detalhar | P56: accounting | Q56: reports / ledger | R56: https://github.com/bootstrapprx/kodoo/tree/main/modules/accounting | S56: Likely mapping; confirm exact function
A57: FN-053 | B57: Razão e Balancetes | C57: contabil.balancete.gerar | D57: Relatório | E57: Balancete de verificação | F57: F1 | G57: Alta | H57: Planejada | I57: T-059 | J57: Não | K57: Não | O57: contabil.trial_balance.generate | P57: accounting | Q57: reports / ledger | R57: https://github.com/bootstrapprx/kodoo/tree/main/modules/accounting | S57: Likely mapping; confirm exact function
A58: FN-054 | B58: Razão e Balancetes | C58: contabil.diario_geral.gerar | D58: Relatório | E58: Diário geral | F58: F1 | G58: Média | H58: Planejada | I58: T-058 | J58: Não | K58: Não | O58: contabil.journal_geral.generate | P58: accounting | Q58: reports / ledger | R58: https://github.com/bootstrapprx/kodoo/tree/main/modules/accounting | S58: Likely mapping; confirm exact function
A59: FN-055 | B59: Razão e Balancetes | C59: contabil.extrato.gerar | D59: Relatório | E59: Extrato de conta | F59: F2 | G59: Média | H59: Planejada | I59: T-061 | J59: Não | K59: Não | O59: contabil.statement.generate | P59: accounting | Q59: reports / ledger | R59: https://github.com/bootstrapprx/kodoo/tree/main/modules/accounting | S59: Likely mapping; confirm exact function
A60: FN-056 | B60: Razão e Balancetes | C60: contabil.balancete.comparar | D60: Relatório | E60: Balancete comparativo entre períodos | F60: F4 | G60: Média | H60: Planejada | I60: T-062 | J60: Não | K60: Não | O60: contabil.trial_balance.comparar | P60: accounting | Q60: reports / ledger | R60: https://github.com/bootstrapprx/kodoo/tree/main/modules/accounting | S60: Likely mapping; confirm exact function
A61: FN-057 | B61: Períodos e Fechamento | C61: contabil.periodo.abrir | D61: Comando | E61: Abrir período | F61: F2 | G61: Alta | H61: Planejada | I61: T-065, T-066 | J61: Não | K61: Não | O61: contabil.period.open | P61: accounting | Q61: core / period close | R61: https://github.com/bootstrapprx/kodoo/tree/main/modules/accounting | S61: Likely mapping; confirm exact function
A62: FN-058 | B62: Períodos e Fechamento | C62: contabil.periodo.verificar_fechamento | D62: Consulta | E62: Verificações de fechamento | F62: F2 | G62: Alta | H62: Planejada | I62: T-067, T-071, T-172 | J62: Não | K62: Não | O62: contabil.period.verificar_fechamento | P62: accounting | Q62: core / period close | R62: https://github.com/bootstrapprx/kodoo/tree/main/modules/accounting | S62: Likely mapping; confirm exact function
A63: FN-059 | B63: Períodos e Fechamento | C63: contabil.periodo.fechar | D63: Comando | E63: Fechar período | F63: F2 | G63: Alta | H63: Planejada | I63: T-067 | J63: Não | K63: Não | O63: contabil.period.close | P63: accounting | Q63: core / period close | R63: https://github.com/bootstrapprx/kodoo/tree/main/modules/accounting | S63: Likely mapping; confirm exact function
A64: FN-060 | B64: Períodos e Fechamento | C64: contabil.periodo.reabrir | D64: Comando | E64: Reabrir período | F64: F2 | G64: Média | H64: Planejada | I64: T-068 | J64: Não | K64: Não | O64: contabil.period.reopen | P64: accounting | Q64: core / period close | R64: https://github.com/bootstrapprx/kodoo/tree/main/modules/accounting | S64: Likely mapping; confirm exact function
A65: FN-061 | B65: Períodos e Fechamento | C65: contabil.exercicio.encerrar | D65: Comando | E65: Encerrar exercício | F65: F4 | G65: Média | H65: Planejada | I65: T-070 | J65: Não | K65: Não | O65: contabil.exercicio.encerrar | P65: accounting | Q65: core / period close | R65: https://github.com/bootstrapprx/kodoo/tree/main/modules/accounting | S65: Likely mapping; confirm exact function
... A129: FN-125 | B129: Painéis | C129: painel.pendencias.consultar | D129: Consulta | E129: Pendências do usuário e da organização | F129: F4 | G129: Média | H129: Planejada | I129: T-173 | J129: Não | K129: Não | O129: dashboard.pendencias.query | P129: app composition / reports | Q129: dashboard | R129: https://github.com/bootstrapprx/kodoo/tree/main/apps/kalkulisto | S129: Likely composition/read-model; confirm
P130: unmapped / to verify | Q130: unspecified | R130: https://github.com/bootstrapprx/kodoo/tree/main/modules | S130: Proposed classification; validate against code
P131: unmapped / to verify | Q131: unspecified | R131: https://github.com/bootstrapprx/kodoo/tree/main/modules | S131: Proposed classification; validate against code
P132: unmapped / to verify | Q132: unspecified | R132: https://github.com/bootstrapprx/kodoo/tree/main/modules | S132: Proposed classification; validate against code
P133: unmapped / to verify | Q133: unspecified | R133: https://github.com/bootstrapprx/kodoo/tree/main/modules | S133: Proposed classification; validate against code
P134: unmapped / to verify | Q134: unspecified | R134: https://github.com/bootstrapprx/kodoo/tree/main/modules | S134: Proposed classification; validate against code
P135: unmapped / to verify | Q135: unspecified | R135: https://github.com/bootstrapprx/kodoo/tree/main/modules | S135: Proposed classification; validate against code
P136: unmapped / to verify | Q136: unspecified | R136: https://github.com/bootstrapprx/kodoo/tree/main/modules | S136: Proposed classification; validate against code
P137: unmapped / to verify | Q137: unspecified | R137: https://github.com/bootstrapprx/kodoo/tree/main/modules | S137: Proposed classification; validate against code
P138: unmapped / to verify | Q138: unspecified | R138: https://github.com/bootstrapprx/kodoo/tree/main/modules | S138: Proposed classification; validate against code
P139: unmapped / to verify | Q139: unspecified | R139: https://github.com/bootstrapprx/kodoo/tree/main/modules | S139: Proposed classification; validate against code
P140: unmapped / to verify | Q140: unspecified | R140: https://github.com/bootstrapprx/kodoo/tree/main/modules | S140: Proposed classification; validate against code
P141: unmapped / to verify | Q141: unspecified | R141: https://github.com/bootstrapprx/kodoo/tree/main/modules | S141: Proposed classification; validate against code
... P300: unmapped / to verify | Q300: unspecified | R300: https://github.com/bootstrapprx/kodoo/tree/main/modules | S300: Proposed classification; validate against code

Sheet Arquétipos
A1: Arquétipos de tela e seus componentes
A2: Cada arquétipo precisa de uma spec no crate kodoo-view e de um componente genérico no Dioxus. Atualize os status conforme avançar.
A4: Arquétipo | B4: Família | C4: Descrição | D4: Spec (kodoo-view) | E4: Componente Dioxus | F4: Telas planejadas ou existentes | G4: Notas
A5: Dashboard | B5: Orientação | C5: Widgets que apontam para telas de projeção | D5: Em andamento | E5: Planejada | F5: =IF(A5="","",COUNTIF(Telas!$D$5:$D$400,A5))
A6: Launcher | B6: Orientação | C6: Lançador de módulos e entradas | D6: Em andamento | E6: Planejada | F6: =IF(A6="","",COUNTIF(Telas!$D$5:$D$400,A6))
A7: List | B7: Consulta | C7: Grade com filtros, ordenação e paginação | D7: Em andamento | E7: Planejada | F7: =IF(A7="","",COUNTIF(Telas!$D$5:$D$400,A7))
A8: Detail | B8: Consulta | C8: Registro somente leitura com abas relacionadas | D8: Em andamento | E8: Planejada | F8: =IF(A8="","",COUNTIF(Telas!$D$5:$D$400,A8))
A9: Calendar | B9: Consulta | C9: Itens posicionados por data | D9: Em andamento | E9: Planejada | F9: =IF(A9="","",COUNTIF(Telas!$D$5:$D$400,A9))
A10: Kanban | B10: Consulta | C10: Cartões agrupados por campo | D10: Em andamento | E10: Planejada | F10: =IF(A10="","",COUNTIF(Telas!$D$5:$D$400,A10))
A11: Form | B11: Edição | C11: Criar e editar um registro | D11: Em andamento | E11: Planejada | F11: =IF(A11="","",COUNTIF(Telas!$D$5:$D$400,A11))
A12: MasterDetail | B12: Edição | C12: Cabeçalho com linhas (ex.: lançamento e partidas) | D12: Em andamento | E12: Planejada | F12: =IF(A12="","",COUNTIF(Telas!$D$5:$D$400,A12))
A13: BulkEdit | B13: Edição | C13: Alterar campos de vários registros | D13: Em andamento | E13: Planejada | F13: =IF(A13="","",COUNTIF(Telas!$D$5:$D$400,A13))
A14: Tree | B14: Classificação | C14: Hierarquia (ex.: plano de contas) | D14: Em andamento | E14: Planejada | F14: =IF(A14="","",COUNTIF(Telas!$D$5:$D$400,A14))
A15: Mapping | B15: Classificação | C15: Vínculos de-para entre entidades | D15: Em andamento | E15: Planejada | F15: =IF(A15="","",COUNTIF(Telas!$D$5:$D$400,A15))
A16: Report | B16: Projeção / Análise | C16: Relatório parametrizado com totais e drill-down | D16: Em andamento | E16: Planejada | F16: =IF(A16="","",COUNTIF(Telas!$D$5:$D$400,A16))
... A28: Shell | B28: Sistema | C28: Itens da casca da aplicação (login, 404, navegação, TUI) | D28: N/A | E28: Planejada | F28: =IF(A28="","",COUNTIF(Telas!$D$5:$D$400,A28))
F29: =IF(A29="","",COUNTIF(Telas!$D$5:$D$400,A29))
F30: =IF(A30="","",COUNTIF(Telas!$D$5:$D$400,A30))
F31: =IF(A31="","",COUNTIF(Telas!$D$5:$D$400,A31))
F32: =IF(A32="","",COUNTIF(Telas!$D$5:$D$400,A32))
F33: =IF(A33="","",COUNTIF(Telas!$D$5:$D$400,A33))
F34: =IF(A34="","",COUNTIF(Telas!$D$5:$D$400,A34))
F35: =IF(A35="","",COUNTIF(Telas!$D$5:$D$400,A35))
F36: =IF(A36="","",COUNTIF(Telas!$D$5:$D$400,A36))
F37: =IF(A37="","",COUNTIF(Telas!$D$5:$D$400,A37))
F38: =IF(A38="","",COUNTIF(Telas!$D$5:$D$400,A38))
F39: =IF(A39="","",COUNTIF(Telas!$D$5:$D$400,A39))
F40: =IF(A40="","",COUNTIF(Telas!$D$5:$D$400,A40))

Sheet Fases
A1: Roadmap do repositório — fases e critérios de saída
A2: Fonte principal: context/roadmap.md (21/09/2026) e context/domain-app-migration.md (19/10/2026). Não confundir com a classificação antiga do catálogo.
A4: Code | B4: Repository Phase / Workstream | C4: Objective | D4: Verifiable Exit Criteria | E4: Dependencies | F4: Initial Audit Status | G4: Source
A5: F0 | B5: Decisões de execução e provisionamento | C5: Fechar decisões operacionais que condicionam a implantação e a sequência do trabalho. | D5: Decisões registradas; responsáveis e ambiente-alvo definidos; decisões refletidas em scripts/docs e verificadas em ambiente limpo. | E5: — | F5: Documentado; confirmar decisões ainda abertas | G5: context/roadmap.md
A6: F1 | B6: Fundação PostgreSQL | C6: Papéis, ownership, execução de migrations e checks SQL. | D6: Bootstrap reproduzível; migrations/checks passam em banco limpo; ownership e permissões validados; CI prova o fluxo. | E6: F0 | F6: Parcial/documentado; validar contra HEAD atual | G6: context/roadmap.md; .github/workflows/ci.yml
A7: F2 | B7: Identidade, entidades e isolamento | C7: Identidade, organização/escopo, persistência e autorização transversal. | D7: Testes negativos provam isolamento entre organizações, rejeição de contexto ausente/malformado e ausência de vazamento após rollback/erro/reuso de conexão. | E7: F1 | F7: Implementação presente; aceite PostgreSQL 18 CI pendente | G7: context/roadmap.md; context/identity-isolation.md; context/f2-authorization-matrix.md
A8: F3 | B8: Primeira fatia operacional nativa | C8: Fluxo vertical durável e autorizado, da API à persistência, com evidência de auditoria. | D8: Mutação autorizada persiste no PostgreSQL; transições inválidas e requisições não autorizadas são rejeitadas; evidência/auditoria verificável. | E8: F2 | F8: Parcial; demonstrar fluxo ponta a ponta | G8: context/roadmap.md
A9: F4 | B9: Efeitos externos controlados | C9: Outbox/worker, retries, idempotência e tratamento de entregas ambíguas. | D9: Testes de falha, duplicação, timeout e retomada; provider dispatchers identificados como pendentes até prova. | E9: F3 | F9: Infra de worker/falhas documentada; dispatchers específicos pendentes | G9: context/roadmap.md
A10: F5 | B10: Inventário e migração de origem | C10: Inventário da origem, ensaio de importação e adaptador de compatibilidade Odoo restrito. | D10: Importação determinística com proveniência, reconciliação, relatório de divergências e contrato do adaptador; ensaio repetível. | E10: F3; decisões de F4 conforme integração | F10: Pendente no roadmap consultado | G10: context/roadmap.md
A11: F6 | B11: Cutover controlado e aposentadoria do adaptador | C11: Migrar tráfego/dados com fencing de escrita e plano seguro de recuperação. | D11: Critérios de corte aprovados; fencing comprovado; reconciliação pós-corte; nenhuma reversão obsoleta após escrita aceita no destino. | E11: F5 | F11: Pendente no roadmap consultado | G11: context/roadmap.md
A12: A1 | B12: Contabilidade e TigerBeetle (trilha paralela) | C12: Consolidar invariantes contábeis e o limite de autoridade do ledger. | D12: Postagem, reversão, saldos e reconciliação aceitos ponta a ponta no TigerBeetle; histórico de correções preservado; PostgreSQL não substitui a autoridade do ledger. | E12: F1; F2 para contexto organizacional | F12: Parcial: engines/CLI/TUI/reporting documentados; aceite autoritativo ponta a ponta ainda precisa de evidência | G12: context/roadmap.md; context/domain-app-migration.md

Sheet Modules
A1: Repository module map — ownership, completeness and entry links
A2: Status is based on repository documentation and directory presence, not a full audit of every source file. A directory is not proof of a complete module.
A4: Parent Module | B4: Submodule / Area | C4: Repository Path | D4: Status from docs | E4: Known gap / next action | F4: Relevant app / surface | G4: Repository Link | H4: Evidence / source | I4: Confidence
A5: accounting | B5: core, chart, calcs, fx, reports, bank, ledger, contract, cli, views/direct, views/tui | C5: modules/accounting | D5: Implemented in slices; incomplete as a product | E5: Finish open TODOs for periods/entries/batches/reversals/closing; expand bank/subledger reconciliation, primary reports/audit trail, remaining Kalkulisto read models and real-stack QA. | F5: apps/kalkulisto; backend; CLI/MCP; Ratatui | G5: https://github.com/bootstrapprx/kodoo/tree/main/modules/accounting | H5: context/domain-app-migration.md (2026-10-19) | I5: Documented
A6: people | B6: Direct view and domain module | C6: modules/people | D6: Direct view integrated; overall completeness not audited | E6: Validate API/CLI/MCP/TUI/Direct tests and identify remaining domain use cases; keep app shell separate from domain rules. | F6: apps/kalkulisto | G6: https://github.com/bootstrapprx/kodoo/tree/main/modules/people | H6: context/application-architecture.md (2026-10-19) | I6: Documented partially
A7: contests | B7: Module scaffolding / candidate native slice | C7: modules/contests | D7: Exists as candidate; not a committed first operational slice | E7: Do not treat scaffolding as product-complete. Define one bounded use case, auth/scope, persistence and surfaces; add Direct view/app only when coherent product flow exists. | F7: Future apps/trivia; backend; CLI/MCP; Ratatui as applicable | G7: https://github.com/bootstrapprx/kodoo/tree/main/modules/contests | H7: context/roadmap.md; context/application-architecture.md | I7: Documented as candidate
A8: knowledge | B8: Domain module scaffolding | C8: modules/knowledge | D8: Scaffolding exists; product Direct/app not yet established | E8: Define product boundary and coherent Direct experience before creating app; verify CLI/MCP/API/TUI coverage and tests. | F8: Future apps/knowledge or apps/trivia depending product decision | G8: https://github.com/bootstrapprx/kodoo/tree/main/modules/knowledge | H8: context/application-architecture.md (2026-10-19) | I8: Documented as planned/scaffolded
A9: admin-bi | B9: Admin / BI module | C9: modules/admin-bi | D9: Directory exists; completeness not established by reviewed docs | E9: Inspect module manifest and surfaces; classify direct metadata, CLI/MCP reachability, TUI wiring, tests and runtime integration. | F9: No app ownership confirmed | G9: https://github.com/bootstrapprx/kodoo/tree/main/modules/admin-bi | H9: Repository modules directory | I9: Needs code audit
A10: project-manager | B10: Project management module | C10: modules/project-manager | D10: Directory exists; completeness not established by reviewed docs | E10: Inspect actual use cases and surface coverage; decide product app/context before expanding UI. | F10: No app ownership confirmed | G10: https://github.com/bootstrapprx/kodoo/tree/main/modules/project-manager | H10: Repository modules directory | I10: Needs code audit
A11: proposals | B11: Proposals module | C11: modules/proposals | D11: Directory exists; completeness not established by reviewed docs | E11: Inspect manifest, API, CLI/MCP, TUI, Direct metadata and tests; define ownership and app placement. | F11: No app ownership confirmed | G11: https://github.com/bootstrapprx/kodoo/tree/main/modules/proposals | H11: Repository modules directory | I11: Needs code audit
A12: _template | B12: Module scaffold/template | C12: modules/_template | D12: Template exists; not a business domain | E12: Use as the starting point for new modules; verify generated surfaces via scripts/standard.py check. | F12: Template only | G12: https://github.com/bootstrapprx/kodoo/tree/main/modules/_template | H12: AGENTS.md; repository modules directory | I12: Template
A13: apps/kalkulisto | B13: Accounting/finance domain app | C13: apps/kalkulisto | D13: Existing Dioxus app; mounts accounting and people views | E13: Keep as product shell; don't move domain rules or ledger ownership into app. Validate desktop + WASM and real-stack QA per slice. | F13: Dioxus Direct | G13: https://github.com/bootstrapprx/kodoo/tree/main/apps/kalkulisto | H13: context/domain-app-migration.md; context/application-architecture.md | I13: Documented
A14: apps/kalkulisto-tui | B14: Operational verification console | C14: apps/kalkulisto-tui | D14: Exists; Ratatui verification/operations console | E14: Keep rules in modules; ensure applicable module views are wired and manually exercised against real backend/database. | F14: Ratatui | G14: https://github.com/bootstrapprx/kodoo/tree/main/apps/kalkulisto-tui | H14: context/application-architecture.md; AGENTS.md | I14: Documented
A15: apps/trivia | B15: Future contests/study product app | C15: apps/trivia | D15: Planned; do not create as empty directory | E15: Create only after contests/knowledge have coherent Direct views, navigation, session and product flows. | F15: Future Dioxus app | G15: https://github.com/bootstrapprx/kodoo/tree/main/context/application-architecture.md | H15: context/application-architecture.md (2026-10-19) | I15: Planned / not assumed present
A16: apps/knowledge | B16: Future knowledge product app | C16: apps/knowledge | D16: Possible future app; product boundary decision required | E16: Decide whether knowledge has a standalone product or is composed into trivia; don't create empty app. | F16: Future Dioxus app | G16: https://github.com/bootstrapprx/kodoo/tree/main/context/application-architecture.md | H16: context/application-architecture.md (2026-10-19) | I16: Planned / decision pending

Sheet Constants & Enums
A1: Constants & Enums — constantes de domínio, estados, códigos e políticas
A2: Um registro por definição. Constante = valor estável de domínio; Enum = estados/códigos permitidos; Policy = valor configurável por organização/exercício/usuário (não é constante). Linhas iniciais são PROPOSTAS, não afirmam que já existem no código. Colunas cinza são calculadas.
F3: Regra ou fórmula formal, testável. | G3: Ledger, PostgreSQL, subledger… | J3: Link ao código real. Vazio se não existir. | K3: Testes de cálculo, reconciliação, atualização. | P3: Sim = proprietário ainda indefinido (ver Decisões pendentes). | R3: Calculado a partir da aba Dependencies. | T3: Calculado: sinaliza lacunas.
A4: ID | B4: Name (EN) | C4: Type | D4: Parent Module | E4: Submodule | F4: Definition / Formula | G4: Data Source | H4: Dimensions & Filters | I4: Implementation Status | J4: Code Link | K4: Tests / Evidence | L4: Authority Level | M4: Repository Phase | N4: Priority | O4: Roadmap Item | P4: Ownership Decision Pending | Q4: Notes / Source | R4: Depends on (#) | S4: Used by (#) | T4: Health
A5: CONST-001 | B5: Currency precision and rounding rules | C5: DomainConstant | D5: accounting | E5: fx | F5: Minor-unit scale and rounding mode per currency, defined once. calcs, fx and reports call the same rounding rule instead of re-implementing it. | G5: Currency catalog (PostgreSQL); ledger amount scale | H5: Currency | I5: Planned | K5: Expected: property tests — rounding is deterministic and rounded parts reconcile to the rounded whole under the documented rule. | L5: Domain rule (authoritative) | M5: A1 | N5: P0 | O5: RM-023 | P5: Não | Q5: Proposed by review — existence in code not asserted. | R5: =IF(A5="","",COUNTIF(Dependencies!$B$5:$B$300,A5)) | S5: =IF(A5="","",COUNTIF(Dependencies!$F$5:$F$300,A5)) | T5: =IF(A5="","",IF(AND(OR(I5="Implemented",I5="Verified"),J5=""),"⚠ Sem link de código",IF(AND(I5="Verified",K5=""),"⚠ Sem evidência",IF(OR(P5="Sim",D5="TBD (owner pending)"),"◐ Proprietário pendente",IF(R5+S5=0,"○ Sem relações","✔ OK")))))
A6: CONST-002 | B6: Ledger amount representation | C6: DomainConstant | D6: accounting | E6: ledger | F6: Amounts cross the TigerBeetle boundary as integer minor units; decimal conversion happens only inside the accounting module. | G6: TigerBeetle (authoritative ledger) | H6: Ledger, currency | I6: Planned | K6: Expected: round-trip test decimal ↔ minor units; structural check that no other crate converts or touches ledger amounts. | L6: Domain rule (authoritative) | M6: A1 | N6: P0 | O6: RM-013 | P6: Não | Q6: Proposed by review — existence in code not asserted. | R6: =IF(A6="","",COUNTIF(Dependencies!$B$5:$B$300,A6)) | S6: =IF(A6="","",COUNTIF(Dependencies!$F$5:$F$300,A6)) | T6: =IF(A6="","",IF(AND(OR(I6="Implemented",I6="Verified"),J6=""),"⚠ Sem link de código",IF(AND(I6="Verified",K6=""),"⚠ Sem evidência",IF(OR(P6="Sim",D6="TBD (owner pending)"),"◐ Proprietário pendente",IF(R6+S6=0,"○ Sem relações","✔ OK")))))
A7: ENUM-001 | B7: Journal entry lifecycle states | C7: Enum | D7: accounting | E7: ledger | F7: Allowed states and legal transitions of a journal entry (for example draft → posted → reversed). Final value set to be confirmed against the domain model; corrections never delete history. | G7: PostgreSQL (operational state) + ledger events | H7: Organization, period | I7: Planned | K7: Expected: transition-table tests; invalid transitions rejected on every surface (API, CLI, MCP, UI). | L7: Domain rule (authoritative) | M7: A1 | N7: P0 | O7: RM-014 | P7: Não | Q7: Proposed by review — existence in code not asserted. | R7: =IF(A7="","",COUNTIF(Dependencies!$B$5:$B$300,A7)) | S7: =IF(A7="","",COUNTIF(Dependencies!$F$5:$F$300,A7)) | T7: =IF(A7="","",IF(AND(OR(I7="Implemented",I7="Verified"),J7=""),"⚠ Sem link de código",IF(AND(I7="Verified",K7=""),"⚠ Sem evidência",IF(OR(P7="Sim",D7="TBD (owner pending)"),"◐ Proprietário pendente",IF(R7+S7=0,"○ Sem relações","✔ OK")))))
A8: ENUM-002 | B8: Accounting period states | C8: Enum | D8: accounting | E8: core | F8: Period states that control whether posting is allowed (for example open → closed). Reopening rules to be decided. | G8: PostgreSQL | H8: Organization, fiscal period | I8: Planned | K8: Expected: posting into a closed period is rejected; reopen path audited. | L8: Domain rule (authoritative) | M8: A1 | N8: P0 | O8: RM-014 | P8: Não | Q8: Proposed by review — existence in code not asserted. | R8: =IF(A8="","",COUNTIF(Dependencies!$B$5:$B$300,A8)) | S8: =IF(A8="","",COUNTIF(Dependencies!$F$5:$F$300,A8)) | T8: =IF(A8="","",IF(AND(OR(I8="Implemented",I8="Verified"),J8=""),"⚠ Sem link de código",IF(AND(I8="Verified",K8=""),"⚠ Sem evidência",IF(OR(P8="Sim",D8="TBD (owner pending)"),"◐ Proprietário pendente",IF(R8+S8=0,"○ Sem relações","✔ OK")))))
A9: ENUM-003 | B9: Accounting profile catalog | C9: Enum | D9: accounting | E9: profiles | F9: Native profile codes: BR-GAAP, IFRS, US-GAAP, PCASP. Each profile owns its operational layer on top of the shared accounting core. | G9: Profile registry (accounting module) | H9: Organization | I9: Planned | K9: Expected: unknown profile code rejected; catalog test per profile. | L9: Domain rule (authoritative) | M9: A1 | N9: P1 | O9: RM-023 | P9: Não | Q9: Proposed by review — existence in code not asserted. | R9: =IF(A9="","",COUNTIF(Dependencies!$B$5:$B$300,A9)) | S9: =IF(A9="","",COUNTIF(Dependencies!$F$5:$F$300,A9)) | T9: =IF(A9="","",IF(AND(OR(I9="Implemented",I9="Verified"),J9=""),"⚠ Sem link de código",IF(AND(I9="Verified",K9=""),"⚠ Sem evidência",IF(OR(P9="Sim",D9="TBD (owner pending)"),"◐ Proprietário pendente",IF(R9+S9=0,"○ Sem relações","✔ OK")))))
A10: ENUM-004 | B10: Reconciliation item status | C10: Enum | D10: accounting | E10: bank | F10: Statuses for matching statements, subledger, journal and ledger (for example matched, unmatched, adjusted, disputed). Adjustments are explicit, never silent. | G10: PostgreSQL (reconciliation history) | H10: Organization, account, period | I10: Planned | K10: Expected: acceptance cases with divergence and correction. | L10: Domain rule (authoritative) | M10: A1 | N10: P1 | O10: RM-015 | P10: Não | Q10: Proposed by review — existence in code not asserted. | R10: =IF(A10="","",COUNTIF(Dependencies!$B$5:$B$300,A10)) | S10: =IF(A10="","",COUNTIF(Dependencies!$F$5:$F$300,A10)) | T10: =IF(A10="","",IF(AND(OR(I10="Implemented",I10="Verified"),J10=""),"⚠ Sem link de código",IF(AND(I10="Verified",K10=""),"⚠ Sem evidência",IF(OR(P10="Sim",D10="TBD (owner pending)"),"◐ Proprietário pendente",IF(R10+S10=0,"○ Sem relações","✔ OK")))))
A11: ENUM-005 | B11: Accounting event codes | C11: Enum | D11: accounting | E11: ledger | F11: Stable codes for accounting events (posting, reversal, closing, adjustment) used by the audit trail and by read models. | G11: Ledger events; audit trail | H11: Organization | I11: Planned | K11: Expected: every relevant mutation emits exactly one registered event code. | L11: Domain rule (authoritative) | M11: A1 | N11: P1 | O11: RM-016 | P11: Não | Q11: Proposed by review — existence in code not asserted. | R11: =IF(A11="","",COUNTIF(Dependencies!$B$5:$B$300,A11)) | S11: =IF(A11="","",COUNTIF(Dependencies!$F$5:$F$300,A11)) | T11: =IF(A11="","",IF(AND(OR(I11="Implemented",I11="Verified"),J11=""),"⚠ Sem link de código",IF(AND(I11="Verified",K11=""),"⚠ Sem evidência",IF(OR(P11="Sim",D11="TBD (owner pending)"),"◐ Proprietário pendente",IF(R11+S11=0,"○ Sem relações","✔ OK")))))
A12: POL-001 | B12: One operational layer per organization | C12: Policy | D12: accounting | E12: profiles | F12: An organization activates exactly one profile operational layer, chosen at onboarding. Cross-profile cases (for example US-GAAP × BR-GAAP imports and exports) go through explicit conversion contracts. | G12: Organization configuration (PostgreSQL) | H12: Organization | I12: Planned | K12: Expected: activating a second operational layer is rejected; conversion contracts tested. | L12: Configuration / policy | M12: A1 | N12: P0 | O12: RM-023 | P12: Não | Q12: Proposed by review — existence in code not asserted. | R12: =IF(A12="","",COUNTIF(Dependencies!$B$5:$B$300,A12)) | S12: =IF(A12="","",COUNTIF(Dependencies!$F$5:$F$300,A12)) | T12: =IF(A12="","",IF(AND(OR(I12="Implemented",I12="Verified"),J12=""),"⚠ Sem link de código",IF(AND(I12="Verified",K12=""),"⚠ Sem evidência",IF(OR(P12="Sim",D12="TBD (owner pending)"),"◐ Proprietário pendente",IF(R12+S12=0,"○ Sem relações","✔ OK")))))
A13: POL-002 | B13: Presentation currency | C13: Policy | D13: accounting | E13: fx | F13: Per-organization currency used to present reports and dashboards; never changes the currency in which the ledger records transactions. | G13: Organization configuration | H13: Organization, user | I13: Planned | K13: Expected: changing it alters presentation only; ledger balances unchanged. | L13: Configuration / policy | M13: A1 | N13: P1 | O13: RM-023 | P13: Não | Q13: Proposed by review — existence in code not asserted. | R13: =IF(A13="","",COUNTIF(Dependencies!$B$5:$B$300,A13)) | S13: =IF(A13="","",COUNTIF(Dependencies!$F$5:$F$300,A13)) | T13: =IF(A13="","",IF(AND(OR(I13="Implemented",I13="Verified"),J13=""),"⚠ Sem link de código",IF(AND(I13="Verified",K13=""),"⚠ Sem evidência",IF(OR(P13="Sim",D13="TBD (owner pending)"),"◐ Proprietário pendente",IF(R13+S13=0,"○ Sem relações","✔ OK")))))
A14: POL-003 | B14: Alert thresholds and targets | C14: Policy | D14: TBD (owner pending) | F14: Configurable limits and targets (for example overdue ratio, minimum cash) per organization or user. Configuration, not hardcoded constants. | G14: Organization / user configuration | H14: Organization, user | I14: Planned | K14: Expected: thresholds read from configuration only; defaults documented. | L14: Configuration / policy | M14: A1 | N14: P2 | O14: RM-023 | P14: Sim | Q14: Proposed by review — existence in code not asserted. Owner undecided — see DEC-002. | R14: =IF(A14="","",COUNTIF(Dependencies!$B$5:$B$300,A14)) | S14: =IF(A14="","",COUNTIF(Dependencies!$F$5:$F$300,A14)) | T14: =IF(A14="","",IF(AND(OR(I14="Implemented",I14="Verified"),J14=""),"⚠ Sem link de código",IF(AND(I14="Verified",K14=""),"⚠ Sem evidência",IF(OR(P14="Sim",D14="TBD (owner pending)"),"◐ Proprietário pendente",IF(R14+S14=0,"○ Sem relações","✔ OK")))))
A15: POL-004 | B15: Forecast horizon and refresh cadence | C15: Policy | D15: accounting | E15: reports | F15: Per-organization forecast horizons (30/60/90 days) and how often projections are regenerated. | G15: Organization configuration | H15: Organization | I15: Planned | K15: Expected: horizon and cadence changes produce a new assumption version. | L15: Configuration / policy | M15: A1 | N15: P1 | O15: RM-025 | P15: Não | Q15: Proposed by review — existence in code not asserted. | R15: =IF(A15="","",COUNTIF(Dependencies!$B$5:$B$300,A15)) | S15: =IF(A15="","",COUNTIF(Dependencies!$F$5:$F$300,A15)) | T15: =IF(A15="","",IF(AND(OR(I15="Implemented",I15="Verified"),J15=""),"⚠ Sem link de código",IF(AND(I15="Verified",K15=""),"⚠ Sem evidência",IF(OR(P15="Sim",D15="TBD (owner pending)"),"◐ Proprietário pendente",IF(R15+S15=0,"○ Sem relações","✔ OK")))))
R16: =IF(A16="","",COUNTIF(Dependencies!$B$5:$B$300,A16)) | S16: =IF(A16="","",COUNTIF(Dependencies!$F$5:$F$300,A16)) | T16: =IF(A16="","",IF(AND(OR(I16="Implemented",I16="Verified"),J16=""),"⚠ Sem link de código",IF(AND(I16="Verified",K16=""),"⚠ Sem evidência",IF(OR(P16="Sim",D16="TBD (owner pending)"),"◐ Proprietário pendente",IF(R16+S16=0,"○ Sem relações","✔ OK")))))
R17: =IF(A17="","",COUNTIF(Dependencies!$B$5:$B$300,A17)) | S17: =IF(A17="","",COUNTIF(Dependencies!$F$5:$F$300,A17)) | T17: =IF(A17="","",IF(AND(OR(I17="Implemented",I17="Verified"),J17=""),"⚠ Sem link de código",IF(AND(I17="Verified",K17=""),"⚠ Sem evidência",IF(OR(P17="Sim",D17="TBD (owner pending)"),"◐ Proprietário pendente",IF(R17+S17=0,"○ Sem relações","✔ OK")))))
R18: =IF(A18="","",COUNTIF(Dependencies!$B$5:$B$300,A18)) | S18: =IF(A18="","",COUNTIF(Dependencies!$F$5:$F$300,A18)) | T18: =IF(A18="","",IF(AND(OR(I18="Implemented",I18="Verified"),J18=""),"⚠ Sem link de código",IF(AND(I18="Verified",K18=""),"⚠ Sem evidência",IF(OR(P18="Sim",D18="TBD (owner pending)"),"◐ Proprietário pendente",IF(R18+S18=0,"○ Sem relações","✔ OK")))))
R19: =IF(A19="","",COUNTIF(Dependencies!$B$5:$B$300,A19)) | S19: =IF(A19="","",COUNTIF(Dependencies!$F$5:$F$300,A19)) | T19: =IF(A19="","",IF(AND(OR(I19="Implemented",I19="Verified"),J19=""),"⚠ Sem link de código",IF(AND(I19="Verified",K19=""),"⚠ Sem evidência",IF(OR(P19="Sim",D19="TBD (owner pending)"),"◐ Proprietário pendente",IF(R19+S19=0,"○ Sem relações","✔ OK")))))
R20: =IF(A20="","",COUNTIF(Dependencies!$B$5:$B$300,A20)) | S20: =IF(A20="","",COUNTIF(Dependencies!$F$5:$F$300,A20)) | T20: =IF(A20="","",IF(AND(OR(I20="Implemented",I20="Verified"),J20=""),"⚠ Sem link de código",IF(AND(I20="Verified",K20=""),"⚠ Sem evidência",IF(OR(P20="Sim",D20="TBD (owner pending)"),"◐ Proprietário pendente",IF(R20+S20=0,"○ Sem relações","✔ OK")))))
R21: =IF(A21="","",COUNTIF(Dependencies!$B$5:$B$300,A21)) | S21: =IF(A21="","",COUNTIF(Dependencies!$F$5:$F$300,A21)) | T21: =IF(A21="","",IF(AND(OR(I21="Implemented",I21="Verified"),J21=""),"⚠ Sem link de código",IF(AND(I21="Verified",K21=""),"⚠ Sem evidência",IF(OR(P21="Sim",D21="TBD (owner pending)"),"◐ Proprietário pendente",IF(R21+S21=0,"○ Sem relações","✔ OK")))))
R22: =IF(A22="","",COUNTIF(Dependencies!$B$5:$B$300,A22)) | S22: =IF(A22="","",COUNTIF(Dependencies!$F$5:$F$300,A22)) | T22: =IF(A22="","",IF(AND(OR(I22="Implemented",I22="Verified"),J22=""),"⚠ Sem link de código",IF(AND(I22="Verified",K22=""),"⚠ Sem evidência",IF(OR(P22="Sim",D22="TBD (owner pending)"),"◐ Proprietário pendente",IF(R22+S22=0,"○ Sem relações","✔ OK")))))
R23: =IF(A23="","",COUNTIF(Dependencies!$B$5:$B$300,A23)) | S23: =IF(A23="","",COUNTIF(Dependencies!$F$5:$F$300,A23)) | T23: =IF(A23="","",IF(AND(OR(I23="Implemented",I23="Verified"),J23=""),"⚠ Sem link de código",IF(AND(I23="Verified",K23=""),"⚠ Sem evidência",IF(OR(P23="Sim",D23="TBD (owner pending)"),"◐ Proprietário pendente",IF(R23+S23=0,"○ Sem relações","✔ OK")))))
R24: =IF(A24="","",COUNTIF(Dependencies!$B$5:$B$300,A24)) | S24: =IF(A24="","",COUNTIF(Dependencies!$F$5:$F$300,A24)) | T24: =IF(A24="","",IF(AND(OR(I24="Implemented",I24="Verified"),J24=""),"⚠ Sem link de código",IF(AND(I24="Verified",K24=""),"⚠ Sem evidência",IF(OR(P24="Sim",D24="TBD (owner pending)"),"◐ Proprietário pendente",IF(R24+S24=0,"○ Sem relações","✔ OK")))))
R25: =IF(A25="","",COUNTIF(Dependencies!$B$5:$B$300,A25)) | S25: =IF(A25="","",COUNTIF(Dependencies!$F$5:$F$300,A25)) | T25: =IF(A25="","",IF(AND(OR(I25="Implemented",I25="Verified"),J25=""),"⚠ Sem link de código",IF(AND(I25="Verified",K25=""),"⚠ Sem evidência",IF(OR(P25="Sim",D25="TBD (owner pending)"),"◐ Proprietário pendente",IF(R25+S25=0,"○ Sem relações","✔ OK")))))
R26: =IF(A26="","",COUNTIF(Dependencies!$B$5:$B$300,A26)) | S26: =IF(A26="","",COUNTIF(Dependencies!$F$5:$F$300,A26)) | T26: =IF(A26="","",IF(AND(OR(I26="Implemented",I26="Verified"),J26=""),"⚠ Sem link de código",IF(AND(I26="Verified",K26=""),"⚠ Sem evidência",IF(OR(P26="Sim",D26="TBD (owner pending)"),"◐ Proprietário pendente",IF(R26+S26=0,"○ Sem relações","✔ OK")))))
R27: =IF(A27="","",COUNTIF(Dependencies!$B$5:$B$300,A27)) | S27: =IF(A27="","",COUNTIF(Dependencies!$F$5:$F$300,A27)) | T27: =IF(A27="","",IF(AND(OR(I27="Implemented",I27="Verified"),J27=""),"⚠ Sem link de código",IF(AND(I27="Verified",K27=""),"⚠ Sem evidência",IF(OR(P27="Sim",D27="TBD (owner pending)"),"◐ Proprietário pendente",IF(R27+S27=0,"○ Sem relações","✔ OK")))))
... R200: =IF(A200="","",COUNTIF(Dependencies!$B$5:$B$300,A200)) | S200: =IF(A200="","",COUNTIF(Dependencies!$F$5:$F$300,A200)) | T200: =IF(A200="","",IF(AND(OR(I200="Implemented",I200="Verified"),J200=""),"⚠ Sem link de código",IF(AND(I200="Verified",K200=""),"⚠ Sem evidência",IF(OR(P200="Sim",D200="TBD (owner pending)"),"◐ Proprietário pendente",IF(R200+S200=0,"○ Sem relações","✔ OK")))))

Sheet Metrics & Formulas
A1: Metrics & Formulas — definições canônicas de indicadores
A2: Cada métrica tem UMA definição canônica; dashboards compõem métricas, não recalculam. Linhas iniciais são PROPOSTAS, não afirmam que já existem no código. Colunas cinza são calculadas.
F3: Regra ou fórmula formal, testável. | G3: Ledger, PostgreSQL, subledger… | J3: Link ao código real. Vazio se não existir. | K3: Testes de cálculo, reconciliação, atualização. | P3: Sim = proprietário ainda indefinido (ver Decisões pendentes). | R3: Calculado a partir da aba Dependencies. | T3: Calculado: sinaliza lacunas.
A4: ID | B4: Name (EN) | C4: Type | D4: Parent Module | E4: Submodule | F4: Definition / Formula | G4: Data Source | H4: Dimensions & Filters | I4: Implementation Status | J4: Code Link | K4: Tests / Evidence | L4: Authority Level | M4: Repository Phase | N4: Priority | O4: Roadmap Item | P4: Ownership Decision Pending | Q4: Notes / Source | R4: Depends on (#) | S4: Used by (#) | T4: Health
A5: METRIC-001 | B5: Posted revenue by period | C5: Metric | D5: accounting | E5: reports | F5: Net credit movement on revenue-class accounts for posted entries dated within [period_start, period_end]; excludes drafts and fully reversed entries; shown in presentation currency using the fx rule in force. | G5: Authoritative ledger balances → reports read model | H5: Organization, period, currency, account group | I5: Planned | K5: Expected: reconciles to ledger balances for the same period; excluded states covered by tests. | L5: Derived read model | M5: A1 | N5: P1 | O5: RM-024 | P5: Não | Q5: Proposed by review — existence in code not asserted. | R5: =IF(A5="","",COUNTIF(Dependencies!$B$5:$B$300,A5)) | S5: =IF(A5="","",COUNTIF(Dependencies!$F$5:$F$300,A5)) | T5: =IF(A5="","",IF(AND(OR(I5="Implemented",I5="Verified"),J5=""),"⚠ Sem link de código",IF(AND(I5="Verified",K5=""),"⚠ Sem evidência",IF(OR(P5="Sim",D5="TBD (owner pending)"),"◐ Proprietário pendente",IF(R5+S5=0,"○ Sem relações","✔ OK")))))
A6: METRIC-002 | B6: Accounts receivable aging | C6: Metric | D6: accounting | E6: reports | F6: Open receivable balance grouped in buckets as of a reference date (current, 1–30, 31–60, 61–90, 90+ days past due). Bucket edges are policy, not constants. | G6: Receivables subledger, reconciled to the ledger control account | H6: Organization, customer, currency, as-of date | I6: Planned | K6: Expected: bucket totals equal the open receivable balance; reconciles to the control account. | L6: Derived read model | M6: A1 | N6: P1 | O6: RM-024 | P6: Não | Q6: Proposed by review — existence in code not asserted. | R6: =IF(A6="","",COUNTIF(Dependencies!$B$5:$B$300,A6)) | S6: =IF(A6="","",COUNTIF(Dependencies!$F$5:$F$300,A6)) | T6: =IF(A6="","",IF(AND(OR(I6="Implemented",I6="Verified"),J6=""),"⚠ Sem link de código",IF(AND(I6="Verified",K6=""),"⚠ Sem evidência",IF(OR(P6="Sim",D6="TBD (owner pending)"),"◐ Proprietário pendente",IF(R6+S6=0,"○ Sem relações","✔ OK")))))
A7: METRIC-003 | B7: Overdue receivables | C7: Metric | D7: accounting | E7: reports | F7: Sum of open receivable balance with due date before the as-of date. Must equal the past-due buckets of METRIC-002. | G7: Receivables subledger | H7: Organization, customer, currency, as-of date | I7: Planned | K7: Expected: equality test against METRIC-002 past-due buckets. | L7: Derived read model | M7: A1 | N7: P1 | O7: RM-024 | P7: Não | Q7: Proposed by review — existence in code not asserted. | R7: =IF(A7="","",COUNTIF(Dependencies!$B$5:$B$300,A7)) | S7: =IF(A7="","",COUNTIF(Dependencies!$F$5:$F$300,A7)) | T7: =IF(A7="","",IF(AND(OR(I7="Implemented",I7="Verified"),J7=""),"⚠ Sem link de código",IF(AND(I7="Verified",K7=""),"⚠ Sem evidência",IF(OR(P7="Sim",D7="TBD (owner pending)"),"◐ Proprietário pendente",IF(R7+S7=0,"○ Sem relações","✔ OK")))))
A8: METRIC-004 | B8: Available balance | C8: Metric | D8: accounting | E8: bank | F8: Ledger balance of cash and bank accounts minus uncleared or held outflows. Treatment of holds to be formalized. | G8: Ledger balances; bank reconciliation state | H8: Organization, account, currency, as-of instant | I8: Planned | K8: Expected: reconciles to bank statements after reconciliation; holds rule tested. | L8: Derived read model | M8: A1 | N8: P1 | O8: RM-024 | P8: Não | Q8: Proposed by review — existence in code not asserted. | R8: =IF(A8="","",COUNTIF(Dependencies!$B$5:$B$300,A8)) | S8: =IF(A8="","",COUNTIF(Dependencies!$F$5:$F$300,A8)) | T8: =IF(A8="","",IF(AND(OR(I8="Implemented",I8="Verified"),J8=""),"⚠ Sem link de código",IF(AND(I8="Verified",K8=""),"⚠ Sem evidência",IF(OR(P8="Sim",D8="TBD (owner pending)"),"◐ Proprietário pendente",IF(R8+S8=0,"○ Sem relações","✔ OK")))))
A9: METRIC-005 | B9: Gross margin | C9: Metric | D9: accounting | E9: reports | F9: (Revenue − cost of sales) ÷ Revenue, stored as a fraction. Returns empty (not zero) when revenue is zero. | G9: Ledger balances → reports read model | H9: Organization, period, currency, segment | I9: Planned | K9: Expected: zero-revenue guard; matches the income statement for the same period. | L9: Derived read model | M9: A1 | N9: P2 | O9: RM-024 | P9: Não | Q9: Proposed by review — existence in code not asserted. | R9: =IF(A9="","",COUNTIF(Dependencies!$B$5:$B$300,A9)) | S9: =IF(A9="","",COUNTIF(Dependencies!$F$5:$F$300,A9)) | T9: =IF(A9="","",IF(AND(OR(I9="Implemented",I9="Verified"),J9=""),"⚠ Sem link de código",IF(AND(I9="Verified",K9=""),"⚠ Sem evidência",IF(OR(P9="Sim",D9="TBD (owner pending)"),"◐ Proprietário pendente",IF(R9+S9=0,"○ Sem relações","✔ OK")))))
A10: METRIC-006 | B10: Budget variance | C10: Metric | D10: accounting | E10: reports | F10: Actual − budget per account and period; percentage = variance ÷ budget, empty when budget is zero. Ownership may move to a future budget module. | G10: Ledger actuals + budget data (source to be defined) | H10: Organization, account, period, budget version | I10: Planned | K10: Expected: variance sums to total actual − total budget; zero-budget guard. | L10: Derived read model | M10: A1 | N10: P2 | O10: RM-024 | P10: Sim | Q10: Proposed by review — existence in code not asserted. Owner undecided — see DEC-001. | R10: =IF(A10="","",COUNTIF(Dependencies!$B$5:$B$300,A10)) | S10: =IF(A10="","",COUNTIF(Dependencies!$F$5:$F$300,A10)) | T10: =IF(A10="","",IF(AND(OR(I10="Implemented",I10="Verified"),J10=""),"⚠ Sem link de código",IF(AND(I10="Verified",K10=""),"⚠ Sem evidência",IF(OR(P10="Sim",D10="TBD (owner pending)"),"◐ Proprietário pendente",IF(R10+S10=0,"○ Sem relações","✔ OK")))))
R11: =IF(A11="","",COUNTIF(Dependencies!$B$5:$B$300,A11)) | S11: =IF(A11="","",COUNTIF(Dependencies!$F$5:$F$300,A11)) | T11: =IF(A11="","",IF(AND(OR(I11="Implemented",I11="Verified"),J11=""),"⚠ Sem link de código",IF(AND(I11="Verified",K11=""),"⚠ Sem evidência",IF(OR(P11="Sim",D11="TBD (owner pending)"),"◐ Proprietário pendente",IF(R11+S11=0,"○ Sem relações","✔ OK")))))
R12: =IF(A12="","",COUNTIF(Dependencies!$B$5:$B$300,A12)) | S12: =IF(A12="","",COUNTIF(Dependencies!$F$5:$F$300,A12)) | T12: =IF(A12="","",IF(AND(OR(I12="Implemented",I12="Verified"),J12=""),"⚠ Sem link de código",IF(AND(I12="Verified",K12=""),"⚠ Sem evidência",IF(OR(P12="Sim",D12="TBD (owner pending)"),"◐ Proprietário pendente",IF(R12+S12=0,"○ Sem relações","✔ OK")))))
R13: =IF(A13="","",COUNTIF(Dependencies!$B$5:$B$300,A13)) | S13: =IF(A13="","",COUNTIF(Dependencies!$F$5:$F$300,A13)) | T13: =IF(A13="","",IF(AND(OR(I13="Implemented",I13="Verified"),J13=""),"⚠ Sem link de código",IF(AND(I13="Verified",K13=""),"⚠ Sem evidência",IF(OR(P13="Sim",D13="TBD (owner pending)"),"◐ Proprietário pendente",IF(R13+S13=0,"○ Sem relações","✔ OK")))))
R14: =IF(A14="","",COUNTIF(Dependencies!$B$5:$B$300,A14)) | S14: =IF(A14="","",COUNTIF(Dependencies!$F$5:$F$300,A14)) | T14: =IF(A14="","",IF(AND(OR(I14="Implemented",I14="Verified"),J14=""),"⚠ Sem link de código",IF(AND(I14="Verified",K14=""),"⚠ Sem evidência",IF(OR(P14="Sim",D14="TBD (owner pending)"),"◐ Proprietário pendente",IF(R14+S14=0,"○ Sem relações","✔ OK")))))
R15: =IF(A15="","",COUNTIF(Dependencies!$B$5:$B$300,A15)) | S15: =IF(A15="","",COUNTIF(Dependencies!$F$5:$F$300,A15)) | T15: =IF(A15="","",IF(AND(OR(I15="Implemented",I15="Verified"),J15=""),"⚠ Sem link de código",IF(AND(I15="Verified",K15=""),"⚠ Sem evidência",IF(OR(P15="Sim",D15="TBD (owner pending)"),"◐ Proprietário pendente",IF(R15+S15=0,"○ Sem relações","✔ OK")))))
R16: =IF(A16="","",COUNTIF(Dependencies!$B$5:$B$300,A16)) | S16: =IF(A16="","",COUNTIF(Dependencies!$F$5:$F$300,A16)) | T16: =IF(A16="","",IF(AND(OR(I16="Implemented",I16="Verified"),J16=""),"⚠ Sem link de código",IF(AND(I16="Verified",K16=""),"⚠ Sem evidência",IF(OR(P16="Sim",D16="TBD (owner pending)"),"◐ Proprietário pendente",IF(R16+S16=0,"○ Sem relações","✔ OK")))))
R17: =IF(A17="","",COUNTIF(Dependencies!$B$5:$B$300,A17)) | S17: =IF(A17="","",COUNTIF(Dependencies!$F$5:$F$300,A17)) | T17: =IF(A17="","",IF(AND(OR(I17="Implemented",I17="Verified"),J17=""),"⚠ Sem link de código",IF(AND(I17="Verified",K17=""),"⚠ Sem evidência",IF(OR(P17="Sim",D17="TBD (owner pending)"),"◐ Proprietário pendente",IF(R17+S17=0,"○ Sem relações","✔ OK")))))
R18: =IF(A18="","",COUNTIF(Dependencies!$B$5:$B$300,A18)) | S18: =IF(A18="","",COUNTIF(Dependencies!$F$5:$F$300,A18)) | T18: =IF(A18="","",IF(AND(OR(I18="Implemented",I18="Verified"),J18=""),"⚠ Sem link de código",IF(AND(I18="Verified",K18=""),"⚠ Sem evidência",IF(OR(P18="Sim",D18="TBD (owner pending)"),"◐ Proprietário pendente",IF(R18+S18=0,"○ Sem relações","✔ OK")))))
R19: =IF(A19="","",COUNTIF(Dependencies!$B$5:$B$300,A19)) | S19: =IF(A19="","",COUNTIF(Dependencies!$F$5:$F$300,A19)) | T19: =IF(A19="","",IF(AND(OR(I19="Implemented",I19="Verified"),J19=""),"⚠ Sem link de código",IF(AND(I19="Verified",K19=""),"⚠ Sem evidência",IF(OR(P19="Sim",D19="TBD (owner pending)"),"◐ Proprietário pendente",IF(R19+S19=0,"○ Sem relações","✔ OK")))))
R20: =IF(A20="","",COUNTIF(Dependencies!$B$5:$B$300,A20)) | S20: =IF(A20="","",COUNTIF(Dependencies!$F$5:$F$300,A20)) | T20: =IF(A20="","",IF(AND(OR(I20="Implemented",I20="Verified"),J20=""),"⚠ Sem link de código",IF(AND(I20="Verified",K20=""),"⚠ Sem evidência",IF(OR(P20="Sim",D20="TBD (owner pending)"),"◐ Proprietário pendente",IF(R20+S20=0,"○ Sem relações","✔ OK")))))
R21: =IF(A21="","",COUNTIF(Dependencies!$B$5:$B$300,A21)) | S21: =IF(A21="","",COUNTIF(Dependencies!$F$5:$F$300,A21)) | T21: =IF(A21="","",IF(AND(OR(I21="Implemented",I21="Verified"),J21=""),"⚠ Sem link de código",IF(AND(I21="Verified",K21=""),"⚠ Sem evidência",IF(OR(P21="Sim",D21="TBD (owner pending)"),"◐ Proprietário pendente",IF(R21+S21=0,"○ Sem relações","✔ OK")))))
R22: =IF(A22="","",COUNTIF(Dependencies!$B$5:$B$300,A22)) | S22: =IF(A22="","",COUNTIF(Dependencies!$F$5:$F$300,A22)) | T22: =IF(A22="","",IF(AND(OR(I22="Implemented",I22="Verified"),J22=""),"⚠ Sem link de código",IF(AND(I22="Verified",K22=""),"⚠ Sem evidência",IF(OR(P22="Sim",D22="TBD (owner pending)"),"◐ Proprietário pendente",IF(R22+S22=0,"○ Sem relações","✔ OK")))))
... R200: =IF(A200="","",COUNTIF(Dependencies!$B$5:$B$300,A200)) | S200: =IF(A200="","",COUNTIF(Dependencies!$F$5:$F$300,A200)) | T200: =IF(A200="","",IF(AND(OR(I200="Implemented",I200="Verified"),J200=""),"⚠ Sem link de código",IF(AND(I200="Verified",K200=""),"⚠ Sem evidência",IF(OR(P200="Sim",D200="TBD (owner pending)"),"◐ Proprietário pendente",IF(R200+S200=0,"○ Sem relações","✔ OK")))))

Sheet Projections & Dashboards
A1: Projections & Dashboards — contratos de leitura e composições visuais
A2: Projeção NÃO é constante nem saldo contábil: é cálculo sobre dados, premissas e um instante de referência. Dashboard só compõe métricas (sem autoridade de cálculo). Linhas iniciais são PROPOSTAS, não afirmam que já existem no código.
F3: Regra ou fórmula formal, testável. | G3: Ledger, PostgreSQL, subledger… | J3: Link ao código real. Vazio se não existir. | K3: Testes de cálculo, reconciliação, atualização. | P3: Sim = proprietário ainda indefinido (ver Decisões pendentes). | R3: Calculado a partir da aba Dependencies. | T3: Calculado: sinaliza lacunas.
A4: ID | B4: Name (EN) | C4: Type | D4: Parent Module | E4: Submodule | F4: Definition / Formula | G4: Data Source | H4: Dimensions & Filters | I4: Implementation Status | J4: Code Link | K4: Tests / Evidence | L4: Authority Level | M4: Repository Phase | N4: Priority | O4: Roadmap Item | P4: Ownership Decision Pending | Q4: Notes / Source | R4: Depends on (#) | S4: Used by (#) | T4: Health | U4: Horizon / Period | V4: Assumptions & Reference Instant | W4: Non-authoritative Notice
A5: PROJ-001 | B5: Cash flow forecast, 30/60/90 days | C5: Projection | D5: accounting | E5: reports | F5: Opening balance at the reference date + expected receipts − expected payments for each horizon. Overdue, recurring and uncertain items follow a versioned assumption set; every output carries the assumption version and its generation instant. | G5: Ledger opening balance + receivable/payable subledgers | H5: Organization, horizon (30/60/90), currency, scenario | I5: Planned | K5: Expected: reproducible from the same inputs and assumption version; realized vs projected variance tracked. | L5: Projection (non-authoritative) | M5: A1 | N5: P1 | O5: RM-025 | P5: Não | Q5: Proposed by review — existence in code not asserted. | R5: =IF(A5="","",COUNTIF(Dependencies!$B$5:$B$300,A5)) | S5: =IF(A5="","",COUNTIF(Dependencies!$F$5:$F$300,A5)) | T5: =IF(A5="","",IF(AND(OR(I5="Implemented",I5="Verified"),J5=""),"⚠ Sem link de código",IF(AND(I5="Verified",K5=""),"⚠ Sem evidência",IF(OR(P5="Sim",D5="TBD (owner pending)"),"◐ Proprietário pendente",IF(R5+S5=0,"○ Sem relações","✔ OK"))))) | U5: 30 / 60 / 90 days | V5: Reference date and instant required; assumption set versioned. | W5: Must be labelled "Projection" and never shown as an official ledger balance.
A6: PROJ-002 | B6: Actual versus budget | C6: Projection | D6: accounting | E6: reports | F6: Compares realized values (ledger) with budgeted values per account and period, using METRIC-006. | G6: Ledger actuals + budget data (source to be defined) | H6: Organization, account, period, budget version | I6: Planned | K6: Expected: totals tie to METRIC-006; budget version and cut-off shown. | L6: Projection (non-authoritative) | M6: A1 | N6: P2 | O6: RM-025 | P6: Sim | Q6: Proposed by review — existence in code not asserted. Owner undecided — see DEC-001. | R6: =IF(A6="","",COUNTIF(Dependencies!$B$5:$B$300,A6)) | S6: =IF(A6="","",COUNTIF(Dependencies!$F$5:$F$300,A6)) | T6: =IF(A6="","",IF(AND(OR(I6="Implemented",I6="Verified"),J6=""),"⚠ Sem link de código",IF(AND(I6="Verified",K6=""),"⚠ Sem evidência",IF(OR(P6="Sim",D6="TBD (owner pending)"),"◐ Proprietário pendente",IF(R6+S6=0,"○ Sem relações","✔ OK"))))) | U6: Month / quarter / year | V6: Budget version and cut-off date required. | W6: Budget is a plan, not an accounting balance; label accordingly.
A7: DASH-001 | B7: Finance overview dashboard | C7: Dashboard | D7: apps/kalkulisto | E7: Dashboard archetype | F7: Composes METRIC-001, METRIC-002, METRIC-004 and PROJ-001 into one screen. Presentation only — no calculation authority. | G7: Accounting read models | H7: Organization, period, currency | I7: Planned | K7: Expected: every figure traces to a canonical metric ID; loading/empty/error states covered. | L7: Presentation only | M7: A1 | N7: P1 | O7: RM-017 | P7: Não | Q7: Proposed by review — existence in code not asserted. | R7: =IF(A7="","",COUNTIF(Dependencies!$B$5:$B$300,A7)) | S7: =IF(A7="","",COUNTIF(Dependencies!$F$5:$F$300,A7)) | T7: =IF(A7="","",IF(AND(OR(I7="Implemented",I7="Verified"),J7=""),"⚠ Sem link de código",IF(AND(I7="Verified",K7=""),"⚠ Sem evidência",IF(OR(P7="Sim",D7="TBD (owner pending)"),"◐ Proprietário pendente",IF(R7+S7=0,"○ Sem relações","✔ OK"))))) | U7: — | V7: — | W7: Projection widgets must carry the projection label and generation instant.
A8: DASH-002 | B8: Reconciliation exceptions dashboard | C8: Dashboard | D8: accounting | E8: bank | F8: Data and rules (exception selection, aging of exceptions) live in the accounting module; apps/kalkulisto only presents them. | G8: Reconciliation history (PostgreSQL) + ledger | H8: Organization, account, period | I8: Planned | K8: Expected: exception counts equal ENUM-004 states; no silent adjustments shown as matched. | L8: Derived read model | M8: A1 | N8: P1 | O8: RM-015 | P8: Não | Q8: Proposed by review — existence in code not asserted. Data/rules: accounting; presentation: apps/kalkulisto. | R8: =IF(A8="","",COUNTIF(Dependencies!$B$5:$B$300,A8)) | S8: =IF(A8="","",COUNTIF(Dependencies!$F$5:$F$300,A8)) | T8: =IF(A8="","",IF(AND(OR(I8="Implemented",I8="Verified"),J8=""),"⚠ Sem link de código",IF(AND(I8="Verified",K8=""),"⚠ Sem evidência",IF(OR(P8="Sim",D8="TBD (owner pending)"),"◐ Proprietário pendente",IF(R8+S8=0,"○ Sem relações","✔ OK"))))) | U8: — | V8: — | W8: —
R9: =IF(A9="","",COUNTIF(Dependencies!$B$5:$B$300,A9)) | S9: =IF(A9="","",COUNTIF(Dependencies!$F$5:$F$300,A9)) | T9: =IF(A9="","",IF(AND(OR(I9="Implemented",I9="Verified"),J9=""),"⚠ Sem link de código",IF(AND(I9="Verified",K9=""),"⚠ Sem evidência",IF(OR(P9="Sim",D9="TBD (owner pending)"),"◐ Proprietário pendente",IF(R9+S9=0,"○ Sem relações","✔ OK")))))
R10: =IF(A10="","",COUNTIF(Dependencies!$B$5:$B$300,A10)) | S10: =IF(A10="","",COUNTIF(Dependencies!$F$5:$F$300,A10)) | T10: =IF(A10="","",IF(AND(OR(I10="Implemented",I10="Verified"),J10=""),"⚠ Sem link de código",IF(AND(I10="Verified",K10=""),"⚠ Sem evidência",IF(OR(P10="Sim",D10="TBD (owner pending)"),"◐ Proprietário pendente",IF(R10+S10=0,"○ Sem relações","✔ OK")))))
R11: =IF(A11="","",COUNTIF(Dependencies!$B$5:$B$300,A11)) | S11: =IF(A11="","",COUNTIF(Dependencies!$F$5:$F$300,A11)) | T11: =IF(A11="","",IF(AND(OR(I11="Implemented",I11="Verified"),J11=""),"⚠ Sem link de código",IF(AND(I11="Verified",K11=""),"⚠ Sem evidência",IF(OR(P11="Sim",D11="TBD (owner pending)"),"◐ Proprietário pendente",IF(R11+S11=0,"○ Sem relações","✔ OK")))))
R12: =IF(A12="","",COUNTIF(Dependencies!$B$5:$B$300,A12)) | S12: =IF(A12="","",COUNTIF(Dependencies!$F$5:$F$300,A12)) | T12: =IF(A12="","",IF(AND(OR(I12="Implemented",I12="Verified"),J12=""),"⚠ Sem link de código",IF(AND(I12="Verified",K12=""),"⚠ Sem evidência",IF(OR(P12="Sim",D12="TBD (owner pending)"),"◐ Proprietário pendente",IF(R12+S12=0,"○ Sem relações","✔ OK")))))
R13: =IF(A13="","",COUNTIF(Dependencies!$B$5:$B$300,A13)) | S13: =IF(A13="","",COUNTIF(Dependencies!$F$5:$F$300,A13)) | T13: =IF(A13="","",IF(AND(OR(I13="Implemented",I13="Verified"),J13=""),"⚠ Sem link de código",IF(AND(I13="Verified",K13=""),"⚠ Sem evidência",IF(OR(P13="Sim",D13="TBD (owner pending)"),"◐ Proprietário pendente",IF(R13+S13=0,"○ Sem relações","✔ OK")))))
R14: =IF(A14="","",COUNTIF(Dependencies!$B$5:$B$300,A14)) | S14: =IF(A14="","",COUNTIF(Dependencies!$F$5:$F$300,A14)) | T14: =IF(A14="","",IF(AND(OR(I14="Implemented",I14="Verified"),J14=""),"⚠ Sem link de código",IF(AND(I14="Verified",K14=""),"⚠ Sem evidência",IF(OR(P14="Sim",D14="TBD (owner pending)"),"◐ Proprietário pendente",IF(R14+S14=0,"○ Sem relações","✔ OK")))))
R15: =IF(A15="","",COUNTIF(Dependencies!$B$5:$B$300,A15)) | S15: =IF(A15="","",COUNTIF(Dependencies!$F$5:$F$300,A15)) | T15: =IF(A15="","",IF(AND(OR(I15="Implemented",I15="Verified"),J15=""),"⚠ Sem link de código",IF(AND(I15="Verified",K15=""),"⚠ Sem evidência",IF(OR(P15="Sim",D15="TBD (owner pending)"),"◐ Proprietário pendente",IF(R15+S15=0,"○ Sem relações","✔ OK")))))
R16: =IF(A16="","",COUNTIF(Dependencies!$B$5:$B$300,A16)) | S16: =IF(A16="","",COUNTIF(Dependencies!$F$5:$F$300,A16)) | T16: =IF(A16="","",IF(AND(OR(I16="Implemented",I16="Verified"),J16=""),"⚠ Sem link de código",IF(AND(I16="Verified",K16=""),"⚠ Sem evidência",IF(OR(P16="Sim",D16="TBD (owner pending)"),"◐ Proprietário pendente",IF(R16+S16=0,"○ Sem relações","✔ OK")))))
R17: =IF(A17="","",COUNTIF(Dependencies!$B$5:$B$300,A17)) | S17: =IF(A17="","",COUNTIF(Dependencies!$F$5:$F$300,A17)) | T17: =IF(A17="","",IF(AND(OR(I17="Implemented",I17="Verified"),J17=""),"⚠ Sem link de código",IF(AND(I17="Verified",K17=""),"⚠ Sem evidência",IF(OR(P17="Sim",D17="TBD (owner pending)"),"◐ Proprietário pendente",IF(R17+S17=0,"○ Sem relações","✔ OK")))))
R18: =IF(A18="","",COUNTIF(Dependencies!$B$5:$B$300,A18)) | S18: =IF(A18="","",COUNTIF(Dependencies!$F$5:$F$300,A18)) | T18: =IF(A18="","",IF(AND(OR(I18="Implemented",I18="Verified"),J18=""),"⚠ Sem link de código",IF(AND(I18="Verified",K18=""),"⚠ Sem evidência",IF(OR(P18="Sim",D18="TBD (owner pending)"),"◐ Proprietário pendente",IF(R18+S18=0,"○ Sem relações","✔ OK")))))
R19: =IF(A19="","",COUNTIF(Dependencies!$B$5:$B$300,A19)) | S19: =IF(A19="","",COUNTIF(Dependencies!$F$5:$F$300,A19)) | T19: =IF(A19="","",IF(AND(OR(I19="Implemented",I19="Verified"),J19=""),"⚠ Sem link de código",IF(AND(I19="Verified",K19=""),"⚠ Sem evidência",IF(OR(P19="Sim",D19="TBD (owner pending)"),"◐ Proprietário pendente",IF(R19+S19=0,"○ Sem relações","✔ OK")))))
R20: =IF(A20="","",COUNTIF(Dependencies!$B$5:$B$300,A20)) | S20: =IF(A20="","",COUNTIF(Dependencies!$F$5:$F$300,A20)) | T20: =IF(A20="","",IF(AND(OR(I20="Implemented",I20="Verified"),J20=""),"⚠ Sem link de código",IF(AND(I20="Verified",K20=""),"⚠ Sem evidência",IF(OR(P20="Sim",D20="TBD (owner pending)"),"◐ Proprietário pendente",IF(R20+S20=0,"○ Sem relações","✔ OK")))))
... R200: =IF(A200="","",COUNTIF(Dependencies!$B$5:$B$300,A200)) | S200: =IF(A200="","",COUNTIF(Dependencies!$F$5:$F$300,A200)) | T200: =IF(A200="","",IF(AND(OR(I200="Implemented",I200="Verified"),J200=""),"⚠ Sem link de código",IF(AND(I200="Verified",K200=""),"⚠ Sem evidência",IF(OR(P200="Sim",D200="TBD (owner pending)"),"◐ Proprietário pendente",IF(R200+S200=0,"○ Sem relações","✔ OK")))))

Sheet Dependencies
A1: Dependencies — relações entre definições, funções, telas, módulos e itens do roadmap
A2: Digite apenas From ID, Relation e To ID (aceita CONST-/ENUM-/POL-/METRIC-/PROJ-/DASH-, FN-, T-, RM- ou o nome do módulo pai da aba Modules). Nome, tipo e validade são calculados. Lê-se: "From <Relation> To".
A4: ID | B4: From ID | C4: From Name | D4: From Type | E4: Relation | F4: To ID | G4: To Name | H4: To Type | I4: Valid? | J4: Notes
A5: DEP-001 | B5: METRIC-001 | C5: =IF(B5="","",IFERROR(INDEX('Constants & Enums'!$B$5:$B$200,MATCH(B5,'Constants & Enums'!$A$5:$A$200,0)),IFERROR(INDEX('Metrics & Formulas'!$B$5:$B$200,MATCH(B5,'Metrics & Formulas'!$A$5:$A$200,0)),IFERROR(INDEX('Projections & Dashboards'!$B$5:$B$200,MATCH(B5,'Projections & Dashboards'!$A$5:$A$200,0)),IFERROR(INDEX(Funções!$O$5:$O$300,MATCH(B5,Funções!$A$5:$A$300,0)),IFERROR(INDEX(Telas!$C$5:$C$400,MATCH(B5,Telas!$A$5:$A$400,0)),IFERROR(INDEX(Roadmap!$D$6:$D$200,MATCH(B5,Roadmap!$A$6:$A$200,0)),IFERROR(INDEX(Modules!$C$5:$C$100,MATCH(B5,Modules!$A$5:$A$100,0)),"NOT FOUND")))))))) | D5: =IF(B5="","",IF(C5="NOT FOUND","—",IFERROR(INDEX(Listas!$J$5:$J$13,MATCH(LEFT(B5,FIND("-",B5)-1),Listas!$I$5:$I$13,0)),"Module / area"))) | E5: governed by | F5: CONST-001 | G5: =IF(F5="","",IFERROR(INDEX('Constants & Enums'!$B$5:$B$200,MATCH(F5,'Constants & Enums'!$A$5:$A$200,0)),IFERROR(INDEX('Metrics & Formulas'!$B$5:$B$200,MATCH(F5,'Metrics & Formulas'!$A$5:$A$200,0)),IFERROR(INDEX('Projections & Dashboards'!$B$5:$B$200,MATCH(F5,'Projections & Dashboards'!$A$5:$A$200,0)),IFERROR(INDEX(Funções!$O$5:$O$300,MATCH(F5,Funções!$A$5:$A$300,0)),IFERROR(INDEX(Telas!$C$5:$C$400,MATCH(F5,Telas!$A$5:$A$400,0)),IFERROR(INDEX(Roadmap!$D$6:$D$200,MATCH(F5,Roadmap!$A$6:$A$200,0)),IFERROR(INDEX(Modules!$C$5:$C$100,MATCH(F5,Modules!$A$5:$A$100,0)),"NOT FOUND")))))))) | H5: =IF(F5="","",IF(G5="NOT FOUND","—",IFERROR(INDEX(Listas!$J$5:$J$13,MATCH(LEFT(F5,FIND("-",F5)-1),Listas!$I$5:$I$13,0)),"Module / area"))) | I5: =IF(AND(B5="",F5=""),"",IF(OR(C5="NOT FOUND",G5="NOT FOUND"),"✖ ID inexistente",IF(B5=F5,"✖ Autorreferência",IF(E5="","✖ Sem relação","✔ OK")))) | J5: Rounding and scale come from the single canonical rule.
A6: DEP-002 | B6: METRIC-001 | C6: =IF(B6="","",IFERROR(INDEX('Constants & Enums'!$B$5:$B$200,MATCH(B6,'Constants & Enums'!$A$5:$A$200,0)),IFERROR(INDEX('Metrics & Formulas'!$B$5:$B$200,MATCH(B6,'Metrics & Formulas'!$A$5:$A$200,0)),IFERROR(INDEX('Projections & Dashboards'!$B$5:$B$200,MATCH(B6,'Projections & Dashboards'!$A$5:$A$200,0)),IFERROR(INDEX(Funções!$O$5:$O$300,MATCH(B6,Funções!$A$5:$A$300,0)),IFERROR(INDEX(Telas!$C$5:$C$400,MATCH(B6,Telas!$A$5:$A$400,0)),IFERROR(INDEX(Roadmap!$D$6:$D$200,MATCH(B6,Roadmap!$A$6:$A$200,0)),IFERROR(INDEX(Modules!$C$5:$C$100,MATCH(B6,Modules!$A$5:$A$100,0)),"NOT FOUND")))))))) | D6: =IF(B6="","",IF(C6="NOT FOUND","—",IFERROR(INDEX(Listas!$J$5:$J$13,MATCH(LEFT(B6,FIND("-",B6)-1),Listas!$I$5:$I$13,0)),"Module / area"))) | E6: governed by | F6: ENUM-001 | G6: =IF(F6="","",IFERROR(INDEX('Constants & Enums'!$B$5:$B$200,MATCH(F6,'Constants & Enums'!$A$5:$A$200,0)),IFERROR(INDEX('Metrics & Formulas'!$B$5:$B$200,MATCH(F6,'Metrics & Formulas'!$A$5:$A$200,0)),IFERROR(INDEX('Projections & Dashboards'!$B$5:$B$200,MATCH(F6,'Projections & Dashboards'!$A$5:$A$200,0)),IFERROR(INDEX(Funções!$O$5:$O$300,MATCH(F6,Funções!$A$5:$A$300,0)),IFERROR(INDEX(Telas!$C$5:$C$400,MATCH(F6,Telas!$A$5:$A$400,0)),IFERROR(INDEX(Roadmap!$D$6:$D$200,MATCH(F6,Roadmap!$A$6:$A$200,0)),IFERROR(INDEX(Modules!$C$5:$C$100,MATCH(F6,Modules!$A$5:$A$100,0)),"NOT FOUND")))))))) | H6: =IF(F6="","",IF(G6="NOT FOUND","—",IFERROR(INDEX(Listas!$J$5:$J$13,MATCH(LEFT(F6,FIND("-",F6)-1),Listas!$I$5:$I$13,0)),"Module / area"))) | I6: =IF(AND(B6="",F6=""),"",IF(OR(C6="NOT FOUND",G6="NOT FOUND"),"✖ ID inexistente",IF(B6=F6,"✖ Autorreferência",IF(E6="","✖ Sem relação","✔ OK")))) | J6: Only posted entries count.
A7: DEP-003 | B7: METRIC-001 | C7: =IF(B7="","",IFERROR(INDEX('Constants & Enums'!$B$5:$B$200,MATCH(B7,'Constants & Enums'!$A$5:$A$200,0)),IFERROR(INDEX('Metrics & Formulas'!$B$5:$B$200,MATCH(B7,'Metrics & Formulas'!$A$5:$A$200,0)),IFERROR(INDEX('Projections & Dashboards'!$B$5:$B$200,MATCH(B7,'Projections & Dashboards'!$A$5:$A$200,0)),IFERROR(INDEX(Funções!$O$5:$O$300,MATCH(B7,Funções!$A$5:$A$300,0)),IFERROR(INDEX(Telas!$C$5:$C$400,MATCH(B7,Telas!$A$5:$A$400,0)),IFERROR(INDEX(Roadmap!$D$6:$D$200,MATCH(B7,Roadmap!$A$6:$A$200,0)),IFERROR(INDEX(Modules!$C$5:$C$100,MATCH(B7,Modules!$A$5:$A$100,0)),"NOT FOUND")))))))) | D7: =IF(B7="","",IF(C7="NOT FOUND","—",IFERROR(INDEX(Listas!$J$5:$J$13,MATCH(LEFT(B7,FIND("-",B7)-1),Listas!$I$5:$I$13,0)),"Module / area"))) | E7: validated by | F7: RM-016 | G7: =IF(F7="","",IFERROR(INDEX('Constants & Enums'!$B$5:$B$200,MATCH(F7,'Constants & Enums'!$A$5:$A$200,0)),IFERROR(INDEX('Metrics & Formulas'!$B$5:$B$200,MATCH(F7,'Metrics & Formulas'!$A$5:$A$200,0)),IFERROR(INDEX('Projections & Dashboards'!$B$5:$B$200,MATCH(F7,'Projections & Dashboards'!$A$5:$A$200,0)),IFERROR(INDEX(Funções!$O$5:$O$300,MATCH(F7,Funções!$A$5:$A$300,0)),IFERROR(INDEX(Telas!$C$5:$C$400,MATCH(F7,Telas!$A$5:$A$400,0)),IFERROR(INDEX(Roadmap!$D$6:$D$200,MATCH(F7,Roadmap!$A$6:$A$200,0)),IFERROR(INDEX(Modules!$C$5:$C$100,MATCH(F7,Modules!$A$5:$A$100,0)),"NOT FOUND")))))))) | H7: =IF(F7="","",IF(G7="NOT FOUND","—",IFERROR(INDEX(Listas!$J$5:$J$13,MATCH(LEFT(F7,FIND("-",F7)-1),Listas!$I$5:$I$13,0)),"Module / area"))) | I7: =IF(AND(B7="",F7=""),"",IF(OR(C7="NOT FOUND",G7="NOT FOUND"),"✖ ID inexistente",IF(B7=F7,"✖ Autorreferência",IF(E7="","✖ Sem relação","✔ OK")))) | J7: Reports reconcile to the authoritative ledger.
A8: DEP-004 | B8: METRIC-002 | C8: =IF(B8="","",IFERROR(INDEX('Constants & Enums'!$B$5:$B$200,MATCH(B8,'Constants & Enums'!$A$5:$A$200,0)),IFERROR(INDEX('Metrics & Formulas'!$B$5:$B$200,MATCH(B8,'Metrics & Formulas'!$A$5:$A$200,0)),IFERROR(INDEX('Projections & Dashboards'!$B$5:$B$200,MATCH(B8,'Projections & Dashboards'!$A$5:$A$200,0)),IFERROR(INDEX(Funções!$O$5:$O$300,MATCH(B8,Funções!$A$5:$A$300,0)),IFERROR(INDEX(Telas!$C$5:$C$400,MATCH(B8,Telas!$A$5:$A$400,0)),IFERROR(INDEX(Roadmap!$D$6:$D$200,MATCH(B8,Roadmap!$A$6:$A$200,0)),IFERROR(INDEX(Modules!$C$5:$C$100,MATCH(B8,Modules!$A$5:$A$100,0)),"NOT FOUND")))))))) | D8: =IF(B8="","",IF(C8="NOT FOUND","—",IFERROR(INDEX(Listas!$J$5:$J$13,MATCH(LEFT(B8,FIND("-",B8)-1),Listas!$I$5:$I$13,0)),"Module / area"))) | E8: governed by | F8: CONST-001 | G8: =IF(F8="","",IFERROR(INDEX('Constants & Enums'!$B$5:$B$200,MATCH(F8,'Constants & Enums'!$A$5:$A$200,0)),IFERROR(INDEX('Metrics & Formulas'!$B$5:$B$200,MATCH(F8,'Metrics & Formulas'!$A$5:$A$200,0)),IFERROR(INDEX('Projections & Dashboards'!$B$5:$B$200,MATCH(F8,'Projections & Dashboards'!$A$5:$A$200,0)),IFERROR(INDEX(Funções!$O$5:$O$300,MATCH(F8,Funções!$A$5:$A$300,0)),IFERROR(INDEX(Telas!$C$5:$C$400,MATCH(F8,Telas!$A$5:$A$400,0)),IFERROR(INDEX(Roadmap!$D$6:$D$200,MATCH(F8,Roadmap!$A$6:$A$200,0)),IFERROR(INDEX(Modules!$C$5:$C$100,MATCH(F8,Modules!$A$5:$A$100,0)),"NOT FOUND")))))))) | H8: =IF(F8="","",IF(G8="NOT FOUND","—",IFERROR(INDEX(Listas!$J$5:$J$13,MATCH(LEFT(F8,FIND("-",F8)-1),Listas!$I$5:$I$13,0)),"Module / area"))) | I8: =IF(AND(B8="",F8=""),"",IF(OR(C8="NOT FOUND",G8="NOT FOUND"),"✖ ID inexistente",IF(B8=F8,"✖ Autorreferência",IF(E8="","✖ Sem relação","✔ OK"))))
A9: DEP-005 | B9: METRIC-003 | C9: =IF(B9="","",IFERROR(INDEX('Constants & Enums'!$B$5:$B$200,MATCH(B9,'Constants & Enums'!$A$5:$A$200,0)),IFERROR(INDEX('Metrics & Formulas'!$B$5:$B$200,MATCH(B9,'Metrics & Formulas'!$A$5:$A$200,0)),IFERROR(INDEX('Projections & Dashboards'!$B$5:$B$200,MATCH(B9,'Projections & Dashboards'!$A$5:$A$200,0)),IFERROR(INDEX(Funções!$O$5:$O$300,MATCH(B9,Funções!$A$5:$A$300,0)),IFERROR(INDEX(Telas!$C$5:$C$400,MATCH(B9,Telas!$A$5:$A$400,0)),IFERROR(INDEX(Roadmap!$D$6:$D$200,MATCH(B9,Roadmap!$A$6:$A$200,0)),IFERROR(INDEX(Modules!$C$5:$C$100,MATCH(B9,Modules!$A$5:$A$100,0)),"NOT FOUND")))))))) | D9: =IF(B9="","",IF(C9="NOT FOUND","—",IFERROR(INDEX(Listas!$J$5:$J$13,MATCH(LEFT(B9,FIND("-",B9)-1),Listas!$I$5:$I$13,0)),"Module / area"))) | E9: computed from | F9: METRIC-002 | G9: =IF(F9="","",IFERROR(INDEX('Constants & Enums'!$B$5:$B$200,MATCH(F9,'Constants & Enums'!$A$5:$A$200,0)),IFERROR(INDEX('Metrics & Formulas'!$B$5:$B$200,MATCH(F9,'Metrics & Formulas'!$A$5:$A$200,0)),IFERROR(INDEX('Projections & Dashboards'!$B$5:$B$200,MATCH(F9,'Projections & Dashboards'!$A$5:$A$200,0)),IFERROR(INDEX(Funções!$O$5:$O$300,MATCH(F9,Funções!$A$5:$A$300,0)),IFERROR(INDEX(Telas!$C$5:$C$400,MATCH(F9,Telas!$A$5:$A$400,0)),IFERROR(INDEX(Roadmap!$D$6:$D$200,MATCH(F9,Roadmap!$A$6:$A$200,0)),IFERROR(INDEX(Modules!$C$5:$C$100,MATCH(F9,Modules!$A$5:$A$100,0)),"NOT FOUND")))))))) | H9: =IF(F9="","",IF(G9="NOT FOUND","—",IFERROR(INDEX(Listas!$J$5:$J$13,MATCH(LEFT(F9,FIND("-",F9)-1),Listas!$I$5:$I$13,0)),"Module / area"))) | I9: =IF(AND(B9="",F9=""),"",IF(OR(C9="NOT FOUND",G9="NOT FOUND"),"✖ ID inexistente",IF(B9=F9,"✖ Autorreferência",IF(E9="","✖ Sem relação","✔ OK")))) | J9: Must equal the past-due buckets.
A10: DEP-006 | B10: METRIC-004 | C10: =IF(B10="","",IFERROR(INDEX('Constants & Enums'!$B$5:$B$200,MATCH(B10,'Constants & Enums'!$A$5:$A$200,0)),IFERROR(INDEX('Metrics & Formulas'!$B$5:$B$200,MATCH(B10,'Metrics & Formulas'!$A$5:$A$200,0)),IFERROR(INDEX('Projections & Dashboards'!$B$5:$B$200,MATCH(B10,'Projections & Dashboards'!$A$5:$A$200,0)),IFERROR(INDEX(Funções!$O$5:$O$300,MATCH(B10,Funções!$A$5:$A$300,0)),IFERROR(INDEX(Telas!$C$5:$C$400,MATCH(B10,Telas!$A$5:$A$400,0)),IFERROR(INDEX(Roadmap!$D$6:$D$200,MATCH(B10,Roadmap!$A$6:$A$200,0)),IFERROR(INDEX(Modules!$C$5:$C$100,MATCH(B10,Modules!$A$5:$A$100,0)),"NOT FOUND")))))))) | D10: =IF(B10="","",IF(C10="NOT FOUND","—",IFERROR(INDEX(Listas!$J$5:$J$13,MATCH(LEFT(B10,FIND("-",B10)-1),Listas!$I$5:$I$13,0)),"Module / area"))) | E10: governed by | F10: CONST-002 | G10: =IF(F10="","",IFERROR(INDEX('Constants & Enums'!$B$5:$B$200,MATCH(F10,'Constants & Enums'!$A$5:$A$200,0)),IFERROR(INDEX('Metrics & Formulas'!$B$5:$B$200,MATCH(F10,'Metrics & Formulas'!$A$5:$A$200,0)),IFERROR(INDEX('Projections & Dashboards'!$B$5:$B$200,MATCH(F10,'Projections & Dashboards'!$A$5:$A$200,0)),IFERROR(INDEX(Funções!$O$5:$O$300,MATCH(F10,Funções!$A$5:$A$300,0)),IFERROR(INDEX(Telas!$C$5:$C$400,MATCH(F10,Telas!$A$5:$A$400,0)),IFERROR(INDEX(Roadmap!$D$6:$D$200,MATCH(F10,Roadmap!$A$6:$A$200,0)),IFERROR(INDEX(Modules!$C$5:$C$100,MATCH(F10,Modules!$A$5:$A$100,0)),"NOT FOUND")))))))) | H10: =IF(F10="","",IF(G10="NOT FOUND","—",IFERROR(INDEX(Listas!$J$5:$J$13,MATCH(LEFT(F10,FIND("-",F10)-1),Listas!$I$5:$I$13,0)),"Module / area"))) | I10: =IF(AND(B10="",F10=""),"",IF(OR(C10="NOT FOUND",G10="NOT FOUND"),"✖ ID inexistente",IF(B10=F10,"✖ Autorreferência",IF(E10="","✖ Sem relação","✔ OK"))))
A11: DEP-007 | B11: METRIC-004 | C11: =IF(B11="","",IFERROR(INDEX('Constants & Enums'!$B$5:$B$200,MATCH(B11,'Constants & Enums'!$A$5:$A$200,0)),IFERROR(INDEX('Metrics & Formulas'!$B$5:$B$200,MATCH(B11,'Metrics & Formulas'!$A$5:$A$200,0)),IFERROR(INDEX('Projections & Dashboards'!$B$5:$B$200,MATCH(B11,'Projections & Dashboards'!$A$5:$A$200,0)),IFERROR(INDEX(Funções!$O$5:$O$300,MATCH(B11,Funções!$A$5:$A$300,0)),IFERROR(INDEX(Telas!$C$5:$C$400,MATCH(B11,Telas!$A$5:$A$400,0)),IFERROR(INDEX(Roadmap!$D$6:$D$200,MATCH(B11,Roadmap!$A$6:$A$200,0)),IFERROR(INDEX(Modules!$C$5:$C$100,MATCH(B11,Modules!$A$5:$A$100,0)),"NOT FOUND")))))))) | D11: =IF(B11="","",IF(C11="NOT FOUND","—",IFERROR(INDEX(Listas!$J$5:$J$13,MATCH(LEFT(B11,FIND("-",B11)-1),Listas!$I$5:$I$13,0)),"Module / area"))) | E11: governed by | F11: ENUM-001 | G11: =IF(F11="","",IFERROR(INDEX('Constants & Enums'!$B$5:$B$200,MATCH(F11,'Constants & Enums'!$A$5:$A$200,0)),IFERROR(INDEX('Metrics & Formulas'!$B$5:$B$200,MATCH(F11,'Metrics & Formulas'!$A$5:$A$200,0)),IFERROR(INDEX('Projections & Dashboards'!$B$5:$B$200,MATCH(F11,'Projections & Dashboards'!$A$5:$A$200,0)),IFERROR(INDEX(Funções!$O$5:$O$300,MATCH(F11,Funções!$A$5:$A$300,0)),IFERROR(INDEX(Telas!$C$5:$C$400,MATCH(F11,Telas!$A$5:$A$400,0)),IFERROR(INDEX(Roadmap!$D$6:$D$200,MATCH(F11,Roadmap!$A$6:$A$200,0)),IFERROR(INDEX(Modules!$C$5:$C$100,MATCH(F11,Modules!$A$5:$A$100,0)),"NOT FOUND")))))))) | H11: =IF(F11="","",IF(G11="NOT FOUND","—",IFERROR(INDEX(Listas!$J$5:$J$13,MATCH(LEFT(F11,FIND("-",F11)-1),Listas!$I$5:$I$13,0)),"Module / area"))) | I11: =IF(AND(B11="",F11=""),"",IF(OR(C11="NOT FOUND",G11="NOT FOUND"),"✖ ID inexistente",IF(B11=F11,"✖ Autorreferência",IF(E11="","✖ Sem relação","✔ OK"))))
A12: DEP-008 | B12: METRIC-005 | C12: =IF(B12="","",IFERROR(INDEX('Constants & Enums'!$B$5:$B$200,MATCH(B12,'Constants & Enums'!$A$5:$A$200,0)),IFERROR(INDEX('Metrics & Formulas'!$B$5:$B$200,MATCH(B12,'Metrics & Formulas'!$A$5:$A$200,0)),IFERROR(INDEX('Projections & Dashboards'!$B$5:$B$200,MATCH(B12,'Projections & Dashboards'!$A$5:$A$200,0)),IFERROR(INDEX(Funções!$O$5:$O$300,MATCH(B12,Funções!$A$5:$A$300,0)),IFERROR(INDEX(Telas!$C$5:$C$400,MATCH(B12,Telas!$A$5:$A$400,0)),IFERROR(INDEX(Roadmap!$D$6:$D$200,MATCH(B12,Roadmap!$A$6:$A$200,0)),IFERROR(INDEX(Modules!$C$5:$C$100,MATCH(B12,Modules!$A$5:$A$100,0)),"NOT FOUND")))))))) | D12: =IF(B12="","",IF(C12="NOT FOUND","—",IFERROR(INDEX(Listas!$J$5:$J$13,MATCH(LEFT(B12,FIND("-",B12)-1),Listas!$I$5:$I$13,0)),"Module / area"))) | E12: computed from | F12: METRIC-001 | G12: =IF(F12="","",IFERROR(INDEX('Constants & Enums'!$B$5:$B$200,MATCH(F12,'Constants & Enums'!$A$5:$A$200,0)),IFERROR(INDEX('Metrics & Formulas'!$B$5:$B$200,MATCH(F12,'Metrics & Formulas'!$A$5:$A$200,0)),IFERROR(INDEX('Projections & Dashboards'!$B$5:$B$200,MATCH(F12,'Projections & Dashboards'!$A$5:$A$200,0)),IFERROR(INDEX(Funções!$O$5:$O$300,MATCH(F12,Funções!$A$5:$A$300,0)),IFERROR(INDEX(Telas!$C$5:$C$400,MATCH(F12,Telas!$A$5:$A$400,0)),IFERROR(INDEX(Roadmap!$D$6:$D$200,MATCH(F12,Roadmap!$A$6:$A$200,0)),IFERROR(INDEX(Modules!$C$5:$C$100,MATCH(F12,Modules!$A$5:$A$100,0)),"NOT FOUND")))))))) | H12: =IF(F12="","",IF(G12="NOT FOUND","—",IFERROR(INDEX(Listas!$J$5:$J$13,MATCH(LEFT(F12,FIND("-",F12)-1),Listas!$I$5:$I$13,0)),"Module / area"))) | I12: =IF(AND(B12="",F12=""),"",IF(OR(C12="NOT FOUND",G12="NOT FOUND"),"✖ ID inexistente",IF(B12=F12,"✖ Autorreferência",IF(E12="","✖ Sem relação","✔ OK")))) | J12: Revenue is the denominator.
A13: DEP-009 | B13: METRIC-006 | C13: =IF(B13="","",IFERROR(INDEX('Constants & Enums'!$B$5:$B$200,MATCH(B13,'Constants & Enums'!$A$5:$A$200,0)),IFERROR(INDEX('Metrics & Formulas'!$B$5:$B$200,MATCH(B13,'Metrics & Formulas'!$A$5:$A$200,0)),IFERROR(INDEX('Projections & Dashboards'!$B$5:$B$200,MATCH(B13,'Projections & Dashboards'!$A$5:$A$200,0)),IFERROR(INDEX(Funções!$O$5:$O$300,MATCH(B13,Funções!$A$5:$A$300,0)),IFERROR(INDEX(Telas!$C$5:$C$400,MATCH(B13,Telas!$A$5:$A$400,0)),IFERROR(INDEX(Roadmap!$D$6:$D$200,MATCH(B13,Roadmap!$A$6:$A$200,0)),IFERROR(INDEX(Modules!$C$5:$C$100,MATCH(B13,Modules!$A$5:$A$100,0)),"NOT FOUND")))))))) | D13: =IF(B13="","",IF(C13="NOT FOUND","—",IFERROR(INDEX(Listas!$J$5:$J$13,MATCH(LEFT(B13,FIND("-",B13)-1),Listas!$I$5:$I$13,0)),"Module / area"))) | E13: reads from | F13: accounting | G13: =IF(F13="","",IFERROR(INDEX('Constants & Enums'!$B$5:$B$200,MATCH(F13,'Constants & Enums'!$A$5:$A$200,0)),IFERROR(INDEX('Metrics & Formulas'!$B$5:$B$200,MATCH(F13,'Metrics & Formulas'!$A$5:$A$200,0)),IFERROR(INDEX('Projections & Dashboards'!$B$5:$B$200,MATCH(F13,'Projections & Dashboards'!$A$5:$A$200,0)),IFERROR(INDEX(Funções!$O$5:$O$300,MATCH(F13,Funções!$A$5:$A$300,0)),IFERROR(INDEX(Telas!$C$5:$C$400,MATCH(F13,Telas!$A$5:$A$400,0)),IFERROR(INDEX(Roadmap!$D$6:$D$200,MATCH(F13,Roadmap!$A$6:$A$200,0)),IFERROR(INDEX(Modules!$C$5:$C$100,MATCH(F13,Modules!$A$5:$A$100,0)),"NOT FOUND")))))))) | H13: =IF(F13="","",IF(G13="NOT FOUND","—",IFERROR(INDEX(Listas!$J$5:$J$13,MATCH(LEFT(F13,FIND("-",F13)-1),Listas!$I$5:$I$13,0)),"Module / area"))) | I13: =IF(AND(B13="",F13=""),"",IF(OR(C13="NOT FOUND",G13="NOT FOUND"),"✖ ID inexistente",IF(B13=F13,"✖ Autorreferência",IF(E13="","✖ Sem relação","✔ OK")))) | J13: Actuals from the ledger; budget source still to be defined (DEC-001).
A14: DEP-010 | B14: PROJ-001 | C14: =IF(B14="","",IFERROR(INDEX('Constants & Enums'!$B$5:$B$200,MATCH(B14,'Constants & Enums'!$A$5:$A$200,0)),IFERROR(INDEX('Metrics & Formulas'!$B$5:$B$200,MATCH(B14,'Metrics & Formulas'!$A$5:$A$200,0)),IFERROR(INDEX('Projections & Dashboards'!$B$5:$B$200,MATCH(B14,'Projections & Dashboards'!$A$5:$A$200,0)),IFERROR(INDEX(Funções!$O$5:$O$300,MATCH(B14,Funções!$A$5:$A$300,0)),IFERROR(INDEX(Telas!$C$5:$C$400,MATCH(B14,Telas!$A$5:$A$400,0)),IFERROR(INDEX(Roadmap!$D$6:$D$200,MATCH(B14,Roadmap!$A$6:$A$200,0)),IFERROR(INDEX(Modules!$C$5:$C$100,MATCH(B14,Modules!$A$5:$A$100,0)),"NOT FOUND")))))))) | D14: =IF(B14="","",IF(C14="NOT FOUND","—",IFERROR(INDEX(Listas!$J$5:$J$13,MATCH(LEFT(B14,FIND("-",B14)-1),Listas!$I$5:$I$13,0)),"Module / area"))) | E14: computed from | F14: METRIC-004 | G14: =IF(F14="","",IFERROR(INDEX('Constants & Enums'!$B$5:$B$200,MATCH(F14,'Constants & Enums'!$A$5:$A$200,0)),IFERROR(INDEX('Metrics & Formulas'!$B$5:$B$200,MATCH(F14,'Metrics & Formulas'!$A$5:$A$200,0)),IFERROR(INDEX('Projections & Dashboards'!$B$5:$B$200,MATCH(F14,'Projections & Dashboards'!$A$5:$A$200,0)),IFERROR(INDEX(Funções!$O$5:$O$300,MATCH(F14,Funções!$A$5:$A$300,0)),IFERROR(INDEX(Telas!$C$5:$C$400,MATCH(F14,Telas!$A$5:$A$400,0)),IFERROR(INDEX(Roadmap!$D$6:$D$200,MATCH(F14,Roadmap!$A$6:$A$200,0)),IFERROR(INDEX(Modules!$C$5:$C$100,MATCH(F14,Modules!$A$5:$A$100,0)),"NOT FOUND")))))))) | H14: =IF(F14="","",IF(G14="NOT FOUND","—",IFERROR(INDEX(Listas!$J$5:$J$13,MATCH(LEFT(F14,FIND("-",F14)-1),Listas!$I$5:$I$13,0)),"Module / area"))) | I14: =IF(AND(B14="",F14=""),"",IF(OR(C14="NOT FOUND",G14="NOT FOUND"),"✖ ID inexistente",IF(B14=F14,"✖ Autorreferência",IF(E14="","✖ Sem relação","✔ OK")))) | J14: Opening balance.
A15: DEP-011 | B15: PROJ-001 | C15: =IF(B15="","",IFERROR(INDEX('Constants & Enums'!$B$5:$B$200,MATCH(B15,'Constants & Enums'!$A$5:$A$200,0)),IFERROR(INDEX('Metrics & Formulas'!$B$5:$B$200,MATCH(B15,'Metrics & Formulas'!$A$5:$A$200,0)),IFERROR(INDEX('Projections & Dashboards'!$B$5:$B$200,MATCH(B15,'Projections & Dashboards'!$A$5:$A$200,0)),IFERROR(INDEX(Funções!$O$5:$O$300,MATCH(B15,Funções!$A$5:$A$300,0)),IFERROR(INDEX(Telas!$C$5:$C$400,MATCH(B15,Telas!$A$5:$A$400,0)),IFERROR(INDEX(Roadmap!$D$6:$D$200,MATCH(B15,Roadmap!$A$6:$A$200,0)),IFERROR(INDEX(Modules!$C$5:$C$100,MATCH(B15,Modules!$A$5:$A$100,0)),"NOT FOUND")))))))) | D15: =IF(B15="","",IF(C15="NOT FOUND","—",IFERROR(INDEX(Listas!$J$5:$J$13,MATCH(LEFT(B15,FIND("-",B15)-1),Listas!$I$5:$I$13,0)),"Module / area"))) | E15: computed from | F15: METRIC-002 | G15: =IF(F15="","",IFERROR(INDEX('Constants & Enums'!$B$5:$B$200,MATCH(F15,'Constants & Enums'!$A$5:$A$200,0)),IFERROR(INDEX('Metrics & Formulas'!$B$5:$B$200,MATCH(F15,'Metrics & Formulas'!$A$5:$A$200,0)),IFERROR(INDEX('Projections & Dashboards'!$B$5:$B$200,MATCH(F15,'Projections & Dashboards'!$A$5:$A$200,0)),IFERROR(INDEX(Funções!$O$5:$O$300,MATCH(F15,Funções!$A$5:$A$300,0)),IFERROR(INDEX(Telas!$C$5:$C$400,MATCH(F15,Telas!$A$5:$A$400,0)),IFERROR(INDEX(Roadmap!$D$6:$D$200,MATCH(F15,Roadmap!$A$6:$A$200,0)),IFERROR(INDEX(Modules!$C$5:$C$100,MATCH(F15,Modules!$A$5:$A$100,0)),"NOT FOUND")))))))) | H15: =IF(F15="","",IF(G15="NOT FOUND","—",IFERROR(INDEX(Listas!$J$5:$J$13,MATCH(LEFT(F15,FIND("-",F15)-1),Listas!$I$5:$I$13,0)),"Module / area"))) | I15: =IF(AND(B15="",F15=""),"",IF(OR(C15="NOT FOUND",G15="NOT FOUND"),"✖ ID inexistente",IF(B15=F15,"✖ Autorreferência",IF(E15="","✖ Sem relação","✔ OK")))) | J15: Expected receipts.
A16: DEP-012 | B16: PROJ-001 | C16: =IF(B16="","",IFERROR(INDEX('Constants & Enums'!$B$5:$B$200,MATCH(B16,'Constants & Enums'!$A$5:$A$200,0)),IFERROR(INDEX('Metrics & Formulas'!$B$5:$B$200,MATCH(B16,'Metrics & Formulas'!$A$5:$A$200,0)),IFERROR(INDEX('Projections & Dashboards'!$B$5:$B$200,MATCH(B16,'Projections & Dashboards'!$A$5:$A$200,0)),IFERROR(INDEX(Funções!$O$5:$O$300,MATCH(B16,Funções!$A$5:$A$300,0)),IFERROR(INDEX(Telas!$C$5:$C$400,MATCH(B16,Telas!$A$5:$A$400,0)),IFERROR(INDEX(Roadmap!$D$6:$D$200,MATCH(B16,Roadmap!$A$6:$A$200,0)),IFERROR(INDEX(Modules!$C$5:$C$100,MATCH(B16,Modules!$A$5:$A$100,0)),"NOT FOUND")))))))) | D16: =IF(B16="","",IF(C16="NOT FOUND","—",IFERROR(INDEX(Listas!$J$5:$J$13,MATCH(LEFT(B16,FIND("-",B16)-1),Listas!$I$5:$I$13,0)),"Module / area"))) | E16: governed by | F16: POL-004 | G16: =IF(F16="","",IFERROR(INDEX('Constants & Enums'!$B$5:$B$200,MATCH(F16,'Constants & Enums'!$A$5:$A$200,0)),IFERROR(INDEX('Metrics & Formulas'!$B$5:$B$200,MATCH(F16,'Metrics & Formulas'!$A$5:$A$200,0)),IFERROR(INDEX('Projections & Dashboards'!$B$5:$B$200,MATCH(F16,'Projections & Dashboards'!$A$5:$A$200,0)),IFERROR(INDEX(Funções!$O$5:$O$300,MATCH(F16,Funções!$A$5:$A$300,0)),IFERROR(INDEX(Telas!$C$5:$C$400,MATCH(F16,Telas!$A$5:$A$400,0)),IFERROR(INDEX(Roadmap!$D$6:$D$200,MATCH(F16,Roadmap!$A$6:$A$200,0)),IFERROR(INDEX(Modules!$C$5:$C$100,MATCH(F16,Modules!$A$5:$A$100,0)),"NOT FOUND")))))))) | H16: =IF(F16="","",IF(G16="NOT FOUND","—",IFERROR(INDEX(Listas!$J$5:$J$13,MATCH(LEFT(F16,FIND("-",F16)-1),Listas!$I$5:$I$13,0)),"Module / area"))) | I16: =IF(AND(B16="",F16=""),"",IF(OR(C16="NOT FOUND",G16="NOT FOUND"),"✖ ID inexistente",IF(B16=F16,"✖ Autorreferência",IF(E16="","✖ Sem relação","✔ OK")))) | J16: Horizon and cadence.
A17: DEP-013 | B17: PROJ-001 | C17: =IF(B17="","",IFERROR(INDEX('Constants & Enums'!$B$5:$B$200,MATCH(B17,'Constants & Enums'!$A$5:$A$200,0)),IFERROR(INDEX('Metrics & Formulas'!$B$5:$B$200,MATCH(B17,'Metrics & Formulas'!$A$5:$A$200,0)),IFERROR(INDEX('Projections & Dashboards'!$B$5:$B$200,MATCH(B17,'Projections & Dashboards'!$A$5:$A$200,0)),IFERROR(INDEX(Funções!$O$5:$O$300,MATCH(B17,Funções!$A$5:$A$300,0)),IFERROR(INDEX(Telas!$C$5:$C$400,MATCH(B17,Telas!$A$5:$A$400,0)),IFERROR(INDEX(Roadmap!$D$6:$D$200,MATCH(B17,Roadmap!$A$6:$A$200,0)),IFERROR(INDEX(Modules!$C$5:$C$100,MATCH(B17,Modules!$A$5:$A$100,0)),"NOT FOUND")))))))) | D17: =IF(B17="","",IF(C17="NOT FOUND","—",IFERROR(INDEX(Listas!$J$5:$J$13,MATCH(LEFT(B17,FIND("-",B17)-1),Listas!$I$5:$I$13,0)),"Module / area"))) | E17: governed by | F17: POL-002 | G17: =IF(F17="","",IFERROR(INDEX('Constants & Enums'!$B$5:$B$200,MATCH(F17,'Constants & Enums'!$A$5:$A$200,0)),IFERROR(INDEX('Metrics & Formulas'!$B$5:$B$200,MATCH(F17,'Metrics & Formulas'!$A$5:$A$200,0)),IFERROR(INDEX('Projections & Dashboards'!$B$5:$B$200,MATCH(F17,'Projections & Dashboards'!$A$5:$A$200,0)),IFERROR(INDEX(Funções!$O$5:$O$300,MATCH(F17,Funções!$A$5:$A$300,0)),IFERROR(INDEX(Telas!$C$5:$C$400,MATCH(F17,Telas!$A$5:$A$400,0)),IFERROR(INDEX(Roadmap!$D$6:$D$200,MATCH(F17,Roadmap!$A$6:$A$200,0)),IFERROR(INDEX(Modules!$C$5:$C$100,MATCH(F17,Modules!$A$5:$A$100,0)),"NOT FOUND")))))))) | H17: =IF(F17="","",IF(G17="NOT FOUND","—",IFERROR(INDEX(Listas!$J$5:$J$13,MATCH(LEFT(F17,FIND("-",F17)-1),Listas!$I$5:$I$13,0)),"Module / area"))) | I17: =IF(AND(B17="",F17=""),"",IF(OR(C17="NOT FOUND",G17="NOT FOUND"),"✖ ID inexistente",IF(B17=F17,"✖ Autorreferência",IF(E17="","✖ Sem relação","✔ OK")))) | J17: Presentation currency.
A18: DEP-014 | B18: PROJ-002 | C18: =IF(B18="","",IFERROR(INDEX('Constants & Enums'!$B$5:$B$200,MATCH(B18,'Constants & Enums'!$A$5:$A$200,0)),IFERROR(INDEX('Metrics & Formulas'!$B$5:$B$200,MATCH(B18,'Metrics & Formulas'!$A$5:$A$200,0)),IFERROR(INDEX('Projections & Dashboards'!$B$5:$B$200,MATCH(B18,'Projections & Dashboards'!$A$5:$A$200,0)),IFERROR(INDEX(Funções!$O$5:$O$300,MATCH(B18,Funções!$A$5:$A$300,0)),IFERROR(INDEX(Telas!$C$5:$C$400,MATCH(B18,Telas!$A$5:$A$400,0)),IFERROR(INDEX(Roadmap!$D$6:$D$200,MATCH(B18,Roadmap!$A$6:$A$200,0)),IFERROR(INDEX(Modules!$C$5:$C$100,MATCH(B18,Modules!$A$5:$A$100,0)),"NOT FOUND")))))))) | D18: =IF(B18="","",IF(C18="NOT FOUND","—",IFERROR(INDEX(Listas!$J$5:$J$13,MATCH(LEFT(B18,FIND("-",B18)-1),Listas!$I$5:$I$13,0)),"Module / area"))) | E18: computed from | F18: METRIC-006 | G18: =IF(F18="","",IFERROR(INDEX('Constants & Enums'!$B$5:$B$200,MATCH(F18,'Constants & Enums'!$A$5:$A$200,0)),IFERROR(INDEX('Metrics & Formulas'!$B$5:$B$200,MATCH(F18,'Metrics & Formulas'!$A$5:$A$200,0)),IFERROR(INDEX('Projections & Dashboards'!$B$5:$B$200,MATCH(F18,'Projections & Dashboards'!$A$5:$A$200,0)),IFERROR(INDEX(Funções!$O$5:$O$300,MATCH(F18,Funções!$A$5:$A$300,0)),IFERROR(INDEX(Telas!$C$5:$C$400,MATCH(F18,Telas!$A$5:$A$400,0)),IFERROR(INDEX(Roadmap!$D$6:$D$200,MATCH(F18,Roadmap!$A$6:$A$200,0)),IFERROR(INDEX(Modules!$C$5:$C$100,MATCH(F18,Modules!$A$5:$A$100,0)),"NOT FOUND")))))))) | H18: =IF(F18="","",IF(G18="NOT FOUND","—",IFERROR(INDEX(Listas!$J$5:$J$13,MATCH(LEFT(F18,FIND("-",F18)-1),Listas!$I$5:$I$13,0)),"Module / area"))) | I18: =IF(AND(B18="",F18=""),"",IF(OR(C18="NOT FOUND",G18="NOT FOUND"),"✖ ID inexistente",IF(B18=F18,"✖ Autorreferência",IF(E18="","✖ Sem relação","✔ OK"))))
A19: DEP-015 | B19: PROJ-002 | C19: =IF(B19="","",IFERROR(INDEX('Constants & Enums'!$B$5:$B$200,MATCH(B19,'Constants & Enums'!$A$5:$A$200,0)),IFERROR(INDEX('Metrics & Formulas'!$B$5:$B$200,MATCH(B19,'Metrics & Formulas'!$A$5:$A$200,0)),IFERROR(INDEX('Projections & Dashboards'!$B$5:$B$200,MATCH(B19,'Projections & Dashboards'!$A$5:$A$200,0)),IFERROR(INDEX(Funções!$O$5:$O$300,MATCH(B19,Funções!$A$5:$A$300,0)),IFERROR(INDEX(Telas!$C$5:$C$400,MATCH(B19,Telas!$A$5:$A$400,0)),IFERROR(INDEX(Roadmap!$D$6:$D$200,MATCH(B19,Roadmap!$A$6:$A$200,0)),IFERROR(INDEX(Modules!$C$5:$C$100,MATCH(B19,Modules!$A$5:$A$100,0)),"NOT FOUND")))))))) | D19: =IF(B19="","",IF(C19="NOT FOUND","—",IFERROR(INDEX(Listas!$J$5:$J$13,MATCH(LEFT(B19,FIND("-",B19)-1),Listas!$I$5:$I$13,0)),"Module / area"))) | E19: governed by | F19: POL-003 | G19: =IF(F19="","",IFERROR(INDEX('Constants & Enums'!$B$5:$B$200,MATCH(F19,'Constants & Enums'!$A$5:$A$200,0)),IFERROR(INDEX('Metrics & Formulas'!$B$5:$B$200,MATCH(F19,'Metrics & Formulas'!$A$5:$A$200,0)),IFERROR(INDEX('Projections & Dashboards'!$B$5:$B$200,MATCH(F19,'Projections & Dashboards'!$A$5:$A$200,0)),IFERROR(INDEX(Funções!$O$5:$O$300,MATCH(F19,Funções!$A$5:$A$300,0)),IFERROR(INDEX(Telas!$C$5:$C$400,MATCH(F19,Telas!$A$5:$A$400,0)),IFERROR(INDEX(Roadmap!$D$6:$D$200,MATCH(F19,Roadmap!$A$6:$A$200,0)),IFERROR(INDEX(Modules!$C$5:$C$100,MATCH(F19,Modules!$A$5:$A$100,0)),"NOT FOUND")))))))) | H19: =IF(F19="","",IF(G19="NOT FOUND","—",IFERROR(INDEX(Listas!$J$5:$J$13,MATCH(LEFT(F19,FIND("-",F19)-1),Listas!$I$5:$I$13,0)),"Module / area"))) | I19: =IF(AND(B19="",F19=""),"",IF(OR(C19="NOT FOUND",G19="NOT FOUND"),"✖ ID inexistente",IF(B19=F19,"✖ Autorreferência",IF(E19="","✖ Sem relação","✔ OK")))) | J19: Targets and alert limits.
A20: DEP-016 | B20: DASH-001 | C20: =IF(B20="","",IFERROR(INDEX('Constants & Enums'!$B$5:$B$200,MATCH(B20,'Constants & Enums'!$A$5:$A$200,0)),IFERROR(INDEX('Metrics & Formulas'!$B$5:$B$200,MATCH(B20,'Metrics & Formulas'!$A$5:$A$200,0)),IFERROR(INDEX('Projections & Dashboards'!$B$5:$B$200,MATCH(B20,'Projections & Dashboards'!$A$5:$A$200,0)),IFERROR(INDEX(Funções!$O$5:$O$300,MATCH(B20,Funções!$A$5:$A$300,0)),IFERROR(INDEX(Telas!$C$5:$C$400,MATCH(B20,Telas!$A$5:$A$400,0)),IFERROR(INDEX(Roadmap!$D$6:$D$200,MATCH(B20,Roadmap!$A$6:$A$200,0)),IFERROR(INDEX(Modules!$C$5:$C$100,MATCH(B20,Modules!$A$5:$A$100,0)),"NOT FOUND")))))))) | D20: =IF(B20="","",IF(C20="NOT FOUND","—",IFERROR(INDEX(Listas!$J$5:$J$13,MATCH(LEFT(B20,FIND("-",B20)-1),Listas!$I$5:$I$13,0)),"Module / area"))) | E20: reads from | F20: METRIC-001 | G20: =IF(F20="","",IFERROR(INDEX('Constants & Enums'!$B$5:$B$200,MATCH(F20,'Constants & Enums'!$A$5:$A$200,0)),IFERROR(INDEX('Metrics & Formulas'!$B$5:$B$200,MATCH(F20,'Metrics & Formulas'!$A$5:$A$200,0)),IFERROR(INDEX('Projections & Dashboards'!$B$5:$B$200,MATCH(F20,'Projections & Dashboards'!$A$5:$A$200,0)),IFERROR(INDEX(Funções!$O$5:$O$300,MATCH(F20,Funções!$A$5:$A$300,0)),IFERROR(INDEX(Telas!$C$5:$C$400,MATCH(F20,Telas!$A$5:$A$400,0)),IFERROR(INDEX(Roadmap!$D$6:$D$200,MATCH(F20,Roadmap!$A$6:$A$200,0)),IFERROR(INDEX(Modules!$C$5:$C$100,MATCH(F20,Modules!$A$5:$A$100,0)),"NOT FOUND")))))))) | H20: =IF(F20="","",IF(G20="NOT FOUND","—",IFERROR(INDEX(Listas!$J$5:$J$13,MATCH(LEFT(F20,FIND("-",F20)-1),Listas!$I$5:$I$13,0)),"Module / area"))) | I20: =IF(AND(B20="",F20=""),"",IF(OR(C20="NOT FOUND",G20="NOT FOUND"),"✖ ID inexistente",IF(B20=F20,"✖ Autorreferência",IF(E20="","✖ Sem relação","✔ OK"))))
A21: DEP-017 | B21: DASH-001 | C21: =IF(B21="","",IFERROR(INDEX('Constants & Enums'!$B$5:$B$200,MATCH(B21,'Constants & Enums'!$A$5:$A$200,0)),IFERROR(INDEX('Metrics & Formulas'!$B$5:$B$200,MATCH(B21,'Metrics & Formulas'!$A$5:$A$200,0)),IFERROR(INDEX('Projections & Dashboards'!$B$5:$B$200,MATCH(B21,'Projections & Dashboards'!$A$5:$A$200,0)),IFERROR(INDEX(Funções!$O$5:$O$300,MATCH(B21,Funções!$A$5:$A$300,0)),IFERROR(INDEX(Telas!$C$5:$C$400,MATCH(B21,Telas!$A$5:$A$400,0)),IFERROR(INDEX(Roadmap!$D$6:$D$200,MATCH(B21,Roadmap!$A$6:$A$200,0)),IFERROR(INDEX(Modules!$C$5:$C$100,MATCH(B21,Modules!$A$5:$A$100,0)),"NOT FOUND")))))))) | D21: =IF(B21="","",IF(C21="NOT FOUND","—",IFERROR(INDEX(Listas!$J$5:$J$13,MATCH(LEFT(B21,FIND("-",B21)-1),Listas!$I$5:$I$13,0)),"Module / area"))) | E21: reads from | F21: METRIC-002 | G21: =IF(F21="","",IFERROR(INDEX('Constants & Enums'!$B$5:$B$200,MATCH(F21,'Constants & Enums'!$A$5:$A$200,0)),IFERROR(INDEX('Metrics & Formulas'!$B$5:$B$200,MATCH(F21,'Metrics & Formulas'!$A$5:$A$200,0)),IFERROR(INDEX('Projections & Dashboards'!$B$5:$B$200,MATCH(F21,'Projections & Dashboards'!$A$5:$A$200,0)),IFERROR(INDEX(Funções!$O$5:$O$300,MATCH(F21,Funções!$A$5:$A$300,0)),IFERROR(INDEX(Telas!$C$5:$C$400,MATCH(F21,Telas!$A$5:$A$400,0)),IFERROR(INDEX(Roadmap!$D$6:$D$200,MATCH(F21,Roadmap!$A$6:$A$200,0)),IFERROR(INDEX(Modules!$C$5:$C$100,MATCH(F21,Modules!$A$5:$A$100,0)),"NOT FOUND")))))))) | H21: =IF(F21="","",IF(G21="NOT FOUND","—",IFERROR(INDEX(Listas!$J$5:$J$13,MATCH(LEFT(F21,FIND("-",F21)-1),Listas!$I$5:$I$13,0)),"Module / area"))) | I21: =IF(AND(B21="",F21=""),"",IF(OR(C21="NOT FOUND",G21="NOT FOUND"),"✖ ID inexistente",IF(B21=F21,"✖ Autorreferência",IF(E21="","✖ Sem relação","✔ OK"))))
A22: DEP-018 | B22: DASH-001 | C22: =IF(B22="","",IFERROR(INDEX('Constants & Enums'!$B$5:$B$200,MATCH(B22,'Constants & Enums'!$A$5:$A$200,0)),IFERROR(INDEX('Metrics & Formulas'!$B$5:$B$200,MATCH(B22,'Metrics & Formulas'!$A$5:$A$200,0)),IFERROR(INDEX('Projections & Dashboards'!$B$5:$B$200,MATCH(B22,'Projections & Dashboards'!$A$5:$A$200,0)),IFERROR(INDEX(Funções!$O$5:$O$300,MATCH(B22,Funções!$A$5:$A$300,0)),IFERROR(INDEX(Telas!$C$5:$C$400,MATCH(B22,Telas!$A$5:$A$400,0)),IFERROR(INDEX(Roadmap!$D$6:$D$200,MATCH(B22,Roadmap!$A$6:$A$200,0)),IFERROR(INDEX(Modules!$C$5:$C$100,MATCH(B22,Modules!$A$5:$A$100,0)),"NOT FOUND")))))))) | D22: =IF(B22="","",IF(C22="NOT FOUND","—",IFERROR(INDEX(Listas!$J$5:$J$13,MATCH(LEFT(B22,FIND("-",B22)-1),Listas!$I$5:$I$13,0)),"Module / area"))) | E22: reads from | F22: PROJ-001 | G22: =IF(F22="","",IFERROR(INDEX('Constants & Enums'!$B$5:$B$200,MATCH(F22,'Constants & Enums'!$A$5:$A$200,0)),IFERROR(INDEX('Metrics & Formulas'!$B$5:$B$200,MATCH(F22,'Metrics & Formulas'!$A$5:$A$200,0)),IFERROR(INDEX('Projections & Dashboards'!$B$5:$B$200,MATCH(F22,'Projections & Dashboards'!$A$5:$A$200,0)),IFERROR(INDEX(Funções!$O$5:$O$300,MATCH(F22,Funções!$A$5:$A$300,0)),IFERROR(INDEX(Telas!$C$5:$C$400,MATCH(F22,Telas!$A$5:$A$400,0)),IFERROR(INDEX(Roadmap!$D$6:$D$200,MATCH(F22,Roadmap!$A$6:$A$200,0)),IFERROR(INDEX(Modules!$C$5:$C$100,MATCH(F22,Modules!$A$5:$A$100,0)),"NOT FOUND")))))))) | H22: =IF(F22="","",IF(G22="NOT FOUND","—",IFERROR(INDEX(Listas!$J$5:$J$13,MATCH(LEFT(F22,FIND("-",F22)-1),Listas!$I$5:$I$13,0)),"Module / area"))) | I22: =IF(AND(B22="",F22=""),"",IF(OR(C22="NOT FOUND",G22="NOT FOUND"),"✖ ID inexistente",IF(B22=F22,"✖ Autorreferência",IF(E22="","✖ Sem relação","✔ OK")))) | J22: Projection widgets must be labelled.
A23: DEP-019 | B23: DASH-001 | C23: =IF(B23="","",IFERROR(INDEX('Constants & Enums'!$B$5:$B$200,MATCH(B23,'Constants & Enums'!$A$5:$A$200,0)),IFERROR(INDEX('Metrics & Formulas'!$B$5:$B$200,MATCH(B23,'Metrics & Formulas'!$A$5:$A$200,0)),IFERROR(INDEX('Projections & Dashboards'!$B$5:$B$200,MATCH(B23,'Projections & Dashboards'!$A$5:$A$200,0)),IFERROR(INDEX(Funções!$O$5:$O$300,MATCH(B23,Funções!$A$5:$A$300,0)),IFERROR(INDEX(Telas!$C$5:$C$400,MATCH(B23,Telas!$A$5:$A$400,0)),IFERROR(INDEX(Roadmap!$D$6:$D$200,MATCH(B23,Roadmap!$A$6:$A$200,0)),IFERROR(INDEX(Modules!$C$5:$C$100,MATCH(B23,Modules!$A$5:$A$100,0)),"NOT FOUND")))))))) | D23: =IF(B23="","",IF(C23="NOT FOUND","—",IFERROR(INDEX(Listas!$J$5:$J$13,MATCH(LEFT(B23,FIND("-",B23)-1),Listas!$I$5:$I$13,0)),"Module / area"))) | E23: depends on | F23: RM-017 | G23: =IF(F23="","",IFERROR(INDEX('Constants & Enums'!$B$5:$B$200,MATCH(F23,'Constants & Enums'!$A$5:$A$200,0)),IFERROR(INDEX('Metrics & Formulas'!$B$5:$B$200,MATCH(F23,'Metrics & Formulas'!$A$5:$A$200,0)),IFERROR(INDEX('Projections & Dashboards'!$B$5:$B$200,MATCH(F23,'Projections & Dashboards'!$A$5:$A$200,0)),IFERROR(INDEX(Funções!$O$5:$O$300,MATCH(F23,Funções!$A$5:$A$300,0)),IFERROR(INDEX(Telas!$C$5:$C$400,MATCH(F23,Telas!$A$5:$A$400,0)),IFERROR(INDEX(Roadmap!$D$6:$D$200,MATCH(F23,Roadmap!$A$6:$A$200,0)),IFERROR(INDEX(Modules!$C$5:$C$100,MATCH(F23,Modules!$A$5:$A$100,0)),"NOT FOUND")))))))) | H23: =IF(F23="","",IF(G23="NOT FOUND","—",IFERROR(INDEX(Listas!$J$5:$J$13,MATCH(LEFT(F23,FIND("-",F23)-1),Listas!$I$5:$I$13,0)),"Module / area"))) | I23: =IF(AND(B23="",F23=""),"",IF(OR(C23="NOT FOUND",G23="NOT FOUND"),"✖ ID inexistente",IF(B23=F23,"✖ Autorreferência",IF(E23="","✖ Sem relação","✔ OK")))) | J23: Kalkulisto read models.
A24: DEP-020 | B24: DASH-002 | C24: =IF(B24="","",IFERROR(INDEX('Constants & Enums'!$B$5:$B$200,MATCH(B24,'Constants & Enums'!$A$5:$A$200,0)),IFERROR(INDEX('Metrics & Formulas'!$B$5:$B$200,MATCH(B24,'Metrics & Formulas'!$A$5:$A$200,0)),IFERROR(INDEX('Projections & Dashboards'!$B$5:$B$200,MATCH(B24,'Projections & Dashboards'!$A$5:$A$200,0)),IFERROR(INDEX(Funções!$O$5:$O$300,MATCH(B24,Funções!$A$5:$A$300,0)),IFERROR(INDEX(Telas!$C$5:$C$400,MATCH(B24,Telas!$A$5:$A$400,0)),IFERROR(INDEX(Roadmap!$D$6:$D$200,MATCH(B24,Roadmap!$A$6:$A$200,0)),IFERROR(INDEX(Modules!$C$5:$C$100,MATCH(B24,Modules!$A$5:$A$100,0)),"NOT FOUND")))))))) | D24: =IF(B24="","",IF(C24="NOT FOUND","—",IFERROR(INDEX(Listas!$J$5:$J$13,MATCH(LEFT(B24,FIND("-",B24)-1),Listas!$I$5:$I$13,0)),"Module / area"))) | E24: reads from | F24: ENUM-004 | G24: =IF(F24="","",IFERROR(INDEX('Constants & Enums'!$B$5:$B$200,MATCH(F24,'Constants & Enums'!$A$5:$A$200,0)),IFERROR(INDEX('Metrics & Formulas'!$B$5:$B$200,MATCH(F24,'Metrics & Formulas'!$A$5:$A$200,0)),IFERROR(INDEX('Projections & Dashboards'!$B$5:$B$200,MATCH(F24,'Projections & Dashboards'!$A$5:$A$200,0)),IFERROR(INDEX(Funções!$O$5:$O$300,MATCH(F24,Funções!$A$5:$A$300,0)),IFERROR(INDEX(Telas!$C$5:$C$400,MATCH(F24,Telas!$A$5:$A$400,0)),IFERROR(INDEX(Roadmap!$D$6:$D$200,MATCH(F24,Roadmap!$A$6:$A$200,0)),IFERROR(INDEX(Modules!$C$5:$C$100,MATCH(F24,Modules!$A$5:$A$100,0)),"NOT FOUND")))))))) | H24: =IF(F24="","",IF(G24="NOT FOUND","—",IFERROR(INDEX(Listas!$J$5:$J$13,MATCH(LEFT(F24,FIND("-",F24)-1),Listas!$I$5:$I$13,0)),"Module / area"))) | I24: =IF(AND(B24="",F24=""),"",IF(OR(C24="NOT FOUND",G24="NOT FOUND"),"✖ ID inexistente",IF(B24=F24,"✖ Autorreferência",IF(E24="","✖ Sem relação","✔ OK"))))
A25: DEP-021 | B25: DASH-002 | C25: =IF(B25="","",IFERROR(INDEX('Constants & Enums'!$B$5:$B$200,MATCH(B25,'Constants & Enums'!$A$5:$A$200,0)),IFERROR(INDEX('Metrics & Formulas'!$B$5:$B$200,MATCH(B25,'Metrics & Formulas'!$A$5:$A$200,0)),IFERROR(INDEX('Projections & Dashboards'!$B$5:$B$200,MATCH(B25,'Projections & Dashboards'!$A$5:$A$200,0)),IFERROR(INDEX(Funções!$O$5:$O$300,MATCH(B25,Funções!$A$5:$A$300,0)),IFERROR(INDEX(Telas!$C$5:$C$400,MATCH(B25,Telas!$A$5:$A$400,0)),IFERROR(INDEX(Roadmap!$D$6:$D$200,MATCH(B25,Roadmap!$A$6:$A$200,0)),IFERROR(INDEX(Modules!$C$5:$C$100,MATCH(B25,Modules!$A$5:$A$100,0)),"NOT FOUND")))))))) | D25: =IF(B25="","",IF(C25="NOT FOUND","—",IFERROR(INDEX(Listas!$J$5:$J$13,MATCH(LEFT(B25,FIND("-",B25)-1),Listas!$I$5:$I$13,0)),"Module / area"))) | E25: depends on | F25: RM-015 | G25: =IF(F25="","",IFERROR(INDEX('Constants & Enums'!$B$5:$B$200,MATCH(F25,'Constants & Enums'!$A$5:$A$200,0)),IFERROR(INDEX('Metrics & Formulas'!$B$5:$B$200,MATCH(F25,'Metrics & Formulas'!$A$5:$A$200,0)),IFERROR(INDEX('Projections & Dashboards'!$B$5:$B$200,MATCH(F25,'Projections & Dashboards'!$A$5:$A$200,0)),IFERROR(INDEX(Funções!$O$5:$O$300,MATCH(F25,Funções!$A$5:$A$300,0)),IFERROR(INDEX(Telas!$C$5:$C$400,MATCH(F25,Telas!$A$5:$A$400,0)),IFERROR(INDEX(Roadmap!$D$6:$D$200,MATCH(F25,Roadmap!$A$6:$A$200,0)),IFERROR(INDEX(Modules!$C$5:$C$100,MATCH(F25,Modules!$A$5:$A$100,0)),"NOT FOUND")))))))) | H25: =IF(F25="","",IF(G25="NOT FOUND","—",IFERROR(INDEX(Listas!$J$5:$J$13,MATCH(LEFT(F25,FIND("-",F25)-1),Listas!$I$5:$I$13,0)),"Module / area"))) | I25: =IF(AND(B25="",F25=""),"",IF(OR(C25="NOT FOUND",G25="NOT FOUND"),"✖ ID inexistente",IF(B25=F25,"✖ Autorreferência",IF(E25="","✖ Sem relação","✔ OK")))) | J25: Reconciliation model.
A26: DEP-022 | B26: POL-001 | C26: =IF(B26="","",IFERROR(INDEX('Constants & Enums'!$B$5:$B$200,MATCH(B26,'Constants & Enums'!$A$5:$A$200,0)),IFERROR(INDEX('Metrics & Formulas'!$B$5:$B$200,MATCH(B26,'Metrics & Formulas'!$A$5:$A$200,0)),IFERROR(INDEX('Projections & Dashboards'!$B$5:$B$200,MATCH(B26,'Projections & Dashboards'!$A$5:$A$200,0)),IFERROR(INDEX(Funções!$O$5:$O$300,MATCH(B26,Funções!$A$5:$A$300,0)),IFERROR(INDEX(Telas!$C$5:$C$400,MATCH(B26,Telas!$A$5:$A$400,0)),IFERROR(INDEX(Roadmap!$D$6:$D$200,MATCH(B26,Roadmap!$A$6:$A$200,0)),IFERROR(INDEX(Modules!$C$5:$C$100,MATCH(B26,Modules!$A$5:$A$100,0)),"NOT FOUND")))))))) | D26: =IF(B26="","",IF(C26="NOT FOUND","—",IFERROR(INDEX(Listas!$J$5:$J$13,MATCH(LEFT(B26,FIND("-",B26)-1),Listas!$I$5:$I$13,0)),"Module / area"))) | E26: governed by | F26: ENUM-003 | G26: =IF(F26="","",IFERROR(INDEX('Constants & Enums'!$B$5:$B$200,MATCH(F26,'Constants & Enums'!$A$5:$A$200,0)),IFERROR(INDEX('Metrics & Formulas'!$B$5:$B$200,MATCH(F26,'Metrics & Formulas'!$A$5:$A$200,0)),IFERROR(INDEX('Projections & Dashboards'!$B$5:$B$200,MATCH(F26,'Projections & Dashboards'!$A$5:$A$200,0)),IFERROR(INDEX(Funções!$O$5:$O$300,MATCH(F26,Funções!$A$5:$A$300,0)),IFERROR(INDEX(Telas!$C$5:$C$400,MATCH(F26,Telas!$A$5:$A$400,0)),IFERROR(INDEX(Roadmap!$D$6:$D$200,MATCH(F26,Roadmap!$A$6:$A$200,0)),IFERROR(INDEX(Modules!$C$5:$C$100,MATCH(F26,Modules!$A$5:$A$100,0)),"NOT FOUND")))))))) | H26: =IF(F26="","",IF(G26="NOT FOUND","—",IFERROR(INDEX(Listas!$J$5:$J$13,MATCH(LEFT(F26,FIND("-",F26)-1),Listas!$I$5:$I$13,0)),"Module / area"))) | I26: =IF(AND(B26="",F26=""),"",IF(OR(C26="NOT FOUND",G26="NOT FOUND"),"✖ ID inexistente",IF(B26=F26,"✖ Autorreferência",IF(E26="","✖ Sem relação","✔ OK"))))
A27: DEP-023 | B27: POL-002 | C27: =IF(B27="","",IFERROR(INDEX('Constants & Enums'!$B$5:$B$200,MATCH(B27,'Constants & Enums'!$A$5:$A$200,0)),IFERROR(INDEX('Metrics & Formulas'!$B$5:$B$200,MATCH(B27,'Metrics & Formulas'!$A$5:$A$200,0)),IFERROR(INDEX('Projections & Dashboards'!$B$5:$B$200,MATCH(B27,'Projections & Dashboards'!$A$5:$A$200,0)),IFERROR(INDEX(Funções!$O$5:$O$300,MATCH(B27,Funções!$A$5:$A$300,0)),IFERROR(INDEX(Telas!$C$5:$C$400,MATCH(B27,Telas!$A$5:$A$400,0)),IFERROR(INDEX(Roadmap!$D$6:$D$200,MATCH(B27,Roadmap!$A$6:$A$200,0)),IFERROR(INDEX(Modules!$C$5:$C$100,MATCH(B27,Modules!$A$5:$A$100,0)),"NOT FOUND")))))))) | D27: =IF(B27="","",IF(C27="NOT FOUND","—",IFERROR(INDEX(Listas!$J$5:$J$13,MATCH(LEFT(B27,FIND("-",B27)-1),Listas!$I$5:$I$13,0)),"Module / area"))) | E27: governed by | F27: CONST-001 | G27: =IF(F27="","",IFERROR(INDEX('Constants & Enums'!$B$5:$B$200,MATCH(F27,'Constants & Enums'!$A$5:$A$200,0)),IFERROR(INDEX('Metrics & Formulas'!$B$5:$B$200,MATCH(F27,'Metrics & Formulas'!$A$5:$A$200,0)),IFERROR(INDEX('Projections & Dashboards'!$B$5:$B$200,MATCH(F27,'Projections & Dashboards'!$A$5:$A$200,0)),IFERROR(INDEX(Funções!$O$5:$O$300,MATCH(F27,Funções!$A$5:$A$300,0)),IFERROR(INDEX(Telas!$C$5:$C$400,MATCH(F27,Telas!$A$5:$A$400,0)),IFERROR(INDEX(Roadmap!$D$6:$D$200,MATCH(F27,Roadmap!$A$6:$A$200,0)),IFERROR(INDEX(Modules!$C$5:$C$100,MATCH(F27,Modules!$A$5:$A$100,0)),"NOT FOUND")))))))) | H27: =IF(F27="","",IF(G27="NOT FOUND","—",IFERROR(INDEX(Listas!$J$5:$J$13,MATCH(LEFT(F27,FIND("-",F27)-1),Listas!$I$5:$I$13,0)),"Module / area"))) | I27: =IF(AND(B27="",F27=""),"",IF(OR(C27="NOT FOUND",G27="NOT FOUND"),"✖ ID inexistente",IF(B27=F27,"✖ Autorreferência",IF(E27="","✖ Sem relação","✔ OK"))))
A28: DEP-024 | B28: ENUM-001 | C28: =IF(B28="","",IFERROR(INDEX('Constants & Enums'!$B$5:$B$200,MATCH(B28,'Constants & Enums'!$A$5:$A$200,0)),IFERROR(INDEX('Metrics & Formulas'!$B$5:$B$200,MATCH(B28,'Metrics & Formulas'!$A$5:$A$200,0)),IFERROR(INDEX('Projections & Dashboards'!$B$5:$B$200,MATCH(B28,'Projections & Dashboards'!$A$5:$A$200,0)),IFERROR(INDEX(Funções!$O$5:$O$300,MATCH(B28,Funções!$A$5:$A$300,0)),IFERROR(INDEX(Telas!$C$5:$C$400,MATCH(B28,Telas!$A$5:$A$400,0)),IFERROR(INDEX(Roadmap!$D$6:$D$200,MATCH(B28,Roadmap!$A$6:$A$200,0)),IFERROR(INDEX(Modules!$C$5:$C$100,MATCH(B28,Modules!$A$5:$A$100,0)),"NOT FOUND")))))))) | D28: =IF(B28="","",IF(C28="NOT FOUND","—",IFERROR(INDEX(Listas!$J$5:$J$13,MATCH(LEFT(B28,FIND("-",B28)-1),Listas!$I$5:$I$13,0)),"Module / area"))) | E28: depends on | F28: ENUM-005 | G28: =IF(F28="","",IFERROR(INDEX('Constants & Enums'!$B$5:$B$200,MATCH(F28,'Constants & Enums'!$A$5:$A$200,0)),IFERROR(INDEX('Metrics & Formulas'!$B$5:$B$200,MATCH(F28,'Metrics & Formulas'!$A$5:$A$200,0)),IFERROR(INDEX('Projections & Dashboards'!$B$5:$B$200,MATCH(F28,'Projections & Dashboards'!$A$5:$A$200,0)),IFERROR(INDEX(Funções!$O$5:$O$300,MATCH(F28,Funções!$A$5:$A$300,0)),IFERROR(INDEX(Telas!$C$5:$C$400,MATCH(F28,Telas!$A$5:$A$400,0)),IFERROR(INDEX(Roadmap!$D$6:$D$200,MATCH(F28,Roadmap!$A$6:$A$200,0)),IFERROR(INDEX(Modules!$C$5:$C$100,MATCH(F28,Modules!$A$5:$A$100,0)),"NOT FOUND")))))))) | H28: =IF(F28="","",IF(G28="NOT FOUND","—",IFERROR(INDEX(Listas!$J$5:$J$13,MATCH(LEFT(F28,FIND("-",F28)-1),Listas!$I$5:$I$13,0)),"Module / area"))) | I28: =IF(AND(B28="",F28=""),"",IF(OR(C28="NOT FOUND",G28="NOT FOUND"),"✖ ID inexistente",IF(B28=F28,"✖ Autorreferência",IF(E28="","✖ Sem relação","✔ OK")))) | J28: Emits registered event codes.
A29: DEP-025 | B29: ENUM-002 | C29: =IF(B29="","",IFERROR(INDEX('Constants & Enums'!$B$5:$B$200,MATCH(B29,'Constants & Enums'!$A$5:$A$200,0)),IFERROR(INDEX('Metrics & Formulas'!$B$5:$B$200,MATCH(B29,'Metrics & Formulas'!$A$5:$A$200,0)),IFERROR(INDEX('Projections & Dashboards'!$B$5:$B$200,MATCH(B29,'Projections & Dashboards'!$A$5:$A$200,0)),IFERROR(INDEX(Funções!$O$5:$O$300,MATCH(B29,Funções!$A$5:$A$300,0)),IFERROR(INDEX(Telas!$C$5:$C$400,MATCH(B29,Telas!$A$5:$A$400,0)),IFERROR(INDEX(Roadmap!$D$6:$D$200,MATCH(B29,Roadmap!$A$6:$A$200,0)),IFERROR(INDEX(Modules!$C$5:$C$100,MATCH(B29,Modules!$A$5:$A$100,0)),"NOT FOUND")))))))) | D29: =IF(B29="","",IF(C29="NOT FOUND","—",IFERROR(INDEX(Listas!$J$5:$J$13,MATCH(LEFT(B29,FIND("-",B29)-1),Listas!$I$5:$I$13,0)),"Module / area"))) | E29: depends on | F29: RM-014 | G29: =IF(F29="","",IFERROR(INDEX('Constants & Enums'!$B$5:$B$200,MATCH(F29,'Constants & Enums'!$A$5:$A$200,0)),IFERROR(INDEX('Metrics & Formulas'!$B$5:$B$200,MATCH(F29,'Metrics & Formulas'!$A$5:$A$200,0)),IFERROR(INDEX('Projections & Dashboards'!$B$5:$B$200,MATCH(F29,'Projections & Dashboards'!$A$5:$A$200,0)),IFERROR(INDEX(Funções!$O$5:$O$300,MATCH(F29,Funções!$A$5:$A$300,0)),IFERROR(INDEX(Telas!$C$5:$C$400,MATCH(F29,Telas!$A$5:$A$400,0)),IFERROR(INDEX(Roadmap!$D$6:$D$200,MATCH(F29,Roadmap!$A$6:$A$200,0)),IFERROR(INDEX(Modules!$C$5:$C$100,MATCH(F29,Modules!$A$5:$A$100,0)),"NOT FOUND")))))))) | H29: =IF(F29="","",IF(G29="NOT FOUND","—",IFERROR(INDEX(Listas!$J$5:$J$13,MATCH(LEFT(F29,FIND("-",F29)-1),Listas!$I$5:$I$13,0)),"Module / area"))) | I29: =IF(AND(B29="",F29=""),"",IF(OR(C29="NOT FOUND",G29="NOT FOUND"),"✖ ID inexistente",IF(B29=F29,"✖ Autorreferência",IF(E29="","✖ Sem relação","✔ OK"))))
A30: DEP-026 | B30: ENUM-004 | C30: =IF(B30="","",IFERROR(INDEX('Constants & Enums'!$B$5:$B$200,MATCH(B30,'Constants & Enums'!$A$5:$A$200,0)),IFERROR(INDEX('Metrics & Formulas'!$B$5:$B$200,MATCH(B30,'Metrics & Formulas'!$A$5:$A$200,0)),IFERROR(INDEX('Projections & Dashboards'!$B$5:$B$200,MATCH(B30,'Projections & Dashboards'!$A$5:$A$200,0)),IFERROR(INDEX(Funções!$O$5:$O$300,MATCH(B30,Funções!$A$5:$A$300,0)),IFERROR(INDEX(Telas!$C$5:$C$400,MATCH(B30,Telas!$A$5:$A$400,0)),IFERROR(INDEX(Roadmap!$D$6:$D$200,MATCH(B30,Roadmap!$A$6:$A$200,0)),IFERROR(INDEX(Modules!$C$5:$C$100,MATCH(B30,Modules!$A$5:$A$100,0)),"NOT FOUND")))))))) | D30: =IF(B30="","",IF(C30="NOT FOUND","—",IFERROR(INDEX(Listas!$J$5:$J$13,MATCH(LEFT(B30,FIND("-",B30)-1),Listas!$I$5:$I$13,0)),"Module / area"))) | E30: depends on | F30: RM-015 | G30: =IF(F30="","",IFERROR(INDEX('Constants & Enums'!$B$5:$B$200,MATCH(F30,'Constants & Enums'!$A$5:$A$200,0)),IFERROR(INDEX('Metrics & Formulas'!$B$5:$B$200,MATCH(F30,'Metrics & Formulas'!$A$5:$A$200,0)),IFERROR(INDEX('Projections & Dashboards'!$B$5:$B$200,MATCH(F30,'Projections & Dashboards'!$A$5:$A$200,0)),IFERROR(INDEX(Funções!$O$5:$O$300,MATCH(F30,Funções!$A$5:$A$300,0)),IFERROR(INDEX(Telas!$C$5:$C$400,MATCH(F30,Telas!$A$5:$A$400,0)),IFERROR(INDEX(Roadmap!$D$6:$D$200,MATCH(F30,Roadmap!$A$6:$A$200,0)),IFERROR(INDEX(Modules!$C$5:$C$100,MATCH(F30,Modules!$A$5:$A$100,0)),"NOT FOUND")))))))) | H30: =IF(F30="","",IF(G30="NOT FOUND","—",IFERROR(INDEX(Listas!$J$5:$J$13,MATCH(LEFT(F30,FIND("-",F30)-1),Listas!$I$5:$I$13,0)),"Module / area"))) | I30: =IF(AND(B30="",F30=""),"",IF(OR(C30="NOT FOUND",G30="NOT FOUND"),"✖ ID inexistente",IF(B30=F30,"✖ Autorreferência",IF(E30="","✖ Sem relação","✔ OK"))))
A31: DEP-027 | B31: CONST-002 | C31: =IF(B31="","",IFERROR(INDEX('Constants & Enums'!$B$5:$B$200,MATCH(B31,'Constants & Enums'!$A$5:$A$200,0)),IFERROR(INDEX('Metrics & Formulas'!$B$5:$B$200,MATCH(B31,'Metrics & Formulas'!$A$5:$A$200,0)),IFERROR(INDEX('Projections & Dashboards'!$B$5:$B$200,MATCH(B31,'Projections & Dashboards'!$A$5:$A$200,0)),IFERROR(INDEX(Funções!$O$5:$O$300,MATCH(B31,Funções!$A$5:$A$300,0)),IFERROR(INDEX(Telas!$C$5:$C$400,MATCH(B31,Telas!$A$5:$A$400,0)),IFERROR(INDEX(Roadmap!$D$6:$D$200,MATCH(B31,Roadmap!$A$6:$A$200,0)),IFERROR(INDEX(Modules!$C$5:$C$100,MATCH(B31,Modules!$A$5:$A$100,0)),"NOT FOUND")))))))) | D31: =IF(B31="","",IF(C31="NOT FOUND","—",IFERROR(INDEX(Listas!$J$5:$J$13,MATCH(LEFT(B31,FIND("-",B31)-1),Listas!$I$5:$I$13,0)),"Module / area"))) | E31: depends on | F31: RM-013 | G31: =IF(F31="","",IFERROR(INDEX('Constants & Enums'!$B$5:$B$200,MATCH(F31,'Constants & Enums'!$A$5:$A$200,0)),IFERROR(INDEX('Metrics & Formulas'!$B$5:$B$200,MATCH(F31,'Metrics & Formulas'!$A$5:$A$200,0)),IFERROR(INDEX('Projections & Dashboards'!$B$5:$B$200,MATCH(F31,'Projections & Dashboards'!$A$5:$A$200,0)),IFERROR(INDEX(Funções!$O$5:$O$300,MATCH(F31,Funções!$A$5:$A$300,0)),IFERROR(INDEX(Telas!$C$5:$C$400,MATCH(F31,Telas!$A$5:$A$400,0)),IFERROR(INDEX(Roadmap!$D$6:$D$200,MATCH(F31,Roadmap!$A$6:$A$200,0)),IFERROR(INDEX(Modules!$C$5:$C$100,MATCH(F31,Modules!$A$5:$A$100,0)),"NOT FOUND")))))))) | H31: =IF(F31="","",IF(G31="NOT FOUND","—",IFERROR(INDEX(Listas!$J$5:$J$13,MATCH(LEFT(F31,FIND("-",F31)-1),Listas!$I$5:$I$13,0)),"Module / area"))) | I31: =IF(AND(B31="",F31=""),"",IF(OR(C31="NOT FOUND",G31="NOT FOUND"),"✖ ID inexistente",IF(B31=F31,"✖ Autorreferência",IF(E31="","✖ Sem relação","✔ OK")))) | J31: TigerBeetle stays the ledger authority.
A32: DEP-028 | B32: DASH-001 | C32: =IF(B32="","",IFERROR(INDEX('Constants & Enums'!$B$5:$B$200,MATCH(B32,'Constants & Enums'!$A$5:$A$200,0)),IFERROR(INDEX('Metrics & Formulas'!$B$5:$B$200,MATCH(B32,'Metrics & Formulas'!$A$5:$A$200,0)),IFERROR(INDEX('Projections & Dashboards'!$B$5:$B$200,MATCH(B32,'Projections & Dashboards'!$A$5:$A$200,0)),IFERROR(INDEX(Funções!$O$5:$O$300,MATCH(B32,Funções!$A$5:$A$300,0)),IFERROR(INDEX(Telas!$C$5:$C$400,MATCH(B32,Telas!$A$5:$A$400,0)),IFERROR(INDEX(Roadmap!$D$6:$D$200,MATCH(B32,Roadmap!$A$6:$A$200,0)),IFERROR(INDEX(Modules!$C$5:$C$100,MATCH(B32,Modules!$A$5:$A$100,0)),"NOT FOUND")))))))) | D32: =IF(B32="","",IF(C32="NOT FOUND","—",IFERROR(INDEX(Listas!$J$5:$J$13,MATCH(LEFT(B32,FIND("-",B32)-1),Listas!$I$5:$I$13,0)),"Module / area"))) | E32: displayed in | F32: T-170 | G32: =IF(F32="","",IFERROR(INDEX('Constants & Enums'!$B$5:$B$200,MATCH(F32,'Constants & Enums'!$A$5:$A$200,0)),IFERROR(INDEX('Metrics & Formulas'!$B$5:$B$200,MATCH(F32,'Metrics & Formulas'!$A$5:$A$200,0)),IFERROR(INDEX('Projections & Dashboards'!$B$5:$B$200,MATCH(F32,'Projections & Dashboards'!$A$5:$A$200,0)),IFERROR(INDEX(Funções!$O$5:$O$300,MATCH(F32,Funções!$A$5:$A$300,0)),IFERROR(INDEX(Telas!$C$5:$C$400,MATCH(F32,Telas!$A$5:$A$400,0)),IFERROR(INDEX(Roadmap!$D$6:$D$200,MATCH(F32,Roadmap!$A$6:$A$200,0)),IFERROR(INDEX(Modules!$C$5:$C$100,MATCH(F32,Modules!$A$5:$A$100,0)),"NOT FOUND")))))))) | H32: =IF(F32="","",IF(G32="NOT FOUND","—",IFERROR(INDEX(Listas!$J$5:$J$13,MATCH(LEFT(F32,FIND("-",F32)-1),Listas!$I$5:$I$13,0)),"Module / area"))) | I32: =IF(AND(B32="",F32=""),"",IF(OR(C32="NOT FOUND",G32="NOT FOUND"),"✖ ID inexistente",IF(B32=F32,"✖ Autorreferência",IF(E32="","✖ Sem relação","✔ OK")))) | J32: Screen from legacy inventory (Painel contábil) — confirm it is the same screen.
C33: =IF(B33="","",IFERROR(INDEX('Constants & Enums'!$B$5:$B$200,MATCH(B33,'Constants & Enums'!$A$5:$A$200,0)),IFERROR(INDEX('Metrics & Formulas'!$B$5:$B$200,MATCH(B33,'Metrics & Formulas'!$A$5:$A$200,0)),IFERROR(INDEX('Projections & Dashboards'!$B$5:$B$200,MATCH(B33,'Projections & Dashboards'!$A$5:$A$200,0)),IFERROR(INDEX(Funções!$O$5:$O$300,MATCH(B33,Funções!$A$5:$A$300,0)),IFERROR(INDEX(Telas!$C$5:$C$400,MATCH(B33,Telas!$A$5:$A$400,0)),IFERROR(INDEX(Roadmap!$D$6:$D$200,MATCH(B33,Roadmap!$A$6:$A$200,0)),IFERROR(INDEX(Modules!$C$5:$C$100,MATCH(B33,Modules!$A$5:$A$100,0)),"NOT FOUND")))))))) | D33: =IF(B33="","",IF(C33="NOT FOUND","—",IFERROR(INDEX(Listas!$J$5:$J$13,MATCH(LEFT(B33,FIND("-",B33)-1),Listas!$I$5:$I$13,0)),"Module / area"))) | G33: =IF(F33="","",IFERROR(INDEX('Constants & Enums'!$B$5:$B$200,MATCH(F33,'Constants & Enums'!$A$5:$A$200,0)),IFERROR(INDEX('Metrics & Formulas'!$B$5:$B$200,MATCH(F33,'Metrics & Formulas'!$A$5:$A$200,0)),IFERROR(INDEX('Projections & Dashboards'!$B$5:$B$200,MATCH(F33,'Projections & Dashboards'!$A$5:$A$200,0)),IFERROR(INDEX(Funções!$O$5:$O$300,MATCH(F33,Funções!$A$5:$A$300,0)),IFERROR(INDEX(Telas!$C$5:$C$400,MATCH(F33,Telas!$A$5:$A$400,0)),IFERROR(INDEX(Roadmap!$D$6:$D$200,MATCH(F33,Roadmap!$A$6:$A$200,0)),IFERROR(INDEX(Modules!$C$5:$C$100,MATCH(F33,Modules!$A$5:$A$100,0)),"NOT FOUND")))))))) | H33: =IF(F33="","",IF(G33="NOT FOUND","—",IFERROR(INDEX(Listas!$J$5:$J$13,MATCH(LEFT(F33,FIND("-",F33)-1),Listas!$I$5:$I$13,0)),"Module / area"))) | I33: =IF(AND(B33="",F33=""),"",IF(OR(C33="NOT FOUND",G33="NOT FOUND"),"✖ ID inexistente",IF(B33=F33,"✖ Autorreferência",IF(E33="","✖ Sem relação","✔ OK"))))
C34: =IF(B34="","",IFERROR(INDEX('Constants & Enums'!$B$5:$B$200,MATCH(B34,'Constants & Enums'!$A$5:$A$200,0)),IFERROR(INDEX('Metrics & Formulas'!$B$5:$B$200,MATCH(B34,'Metrics & Formulas'!$A$5:$A$200,0)),IFERROR(INDEX('Projections & Dashboards'!$B$5:$B$200,MATCH(B34,'Projections & Dashboards'!$A$5:$A$200,0)),IFERROR(INDEX(Funções!$O$5:$O$300,MATCH(B34,Funções!$A$5:$A$300,0)),IFERROR(INDEX(Telas!$C$5:$C$400,MATCH(B34,Telas!$A$5:$A$400,0)),IFERROR(INDEX(Roadmap!$D$6:$D$200,MATCH(B34,Roadmap!$A$6:$A$200,0)),IFERROR(INDEX(Modules!$C$5:$C$100,MATCH(B34,Modules!$A$5:$A$100,0)),"NOT FOUND")))))))) | D34: =IF(B34="","",IF(C34="NOT FOUND","—",IFERROR(INDEX(Listas!$J$5:$J$13,MATCH(LEFT(B34,FIND("-",B34)-1),Listas!$I$5:$I$13,0)),"Module / area"))) | G34: =IF(F34="","",IFERROR(INDEX('Constants & Enums'!$B$5:$B$200,MATCH(F34,'Constants & Enums'!$A$5:$A$200,0)),IFERROR(INDEX('Metrics & Formulas'!$B$5:$B$200,MATCH(F34,'Metrics & Formulas'!$A$5:$A$200,0)),IFERROR(INDEX('Projections & Dashboards'!$B$5:$B$200,MATCH(F34,'Projections & Dashboards'!$A$5:$A$200,0)),IFERROR(INDEX(Funções!$O$5:$O$300,MATCH(F34,Funções!$A$5:$A$300,0)),IFERROR(INDEX(Telas!$C$5:$C$400,MATCH(F34,Telas!$A$5:$A$400,0)),IFERROR(INDEX(Roadmap!$D$6:$D$200,MATCH(F34,Roadmap!$A$6:$A$200,0)),IFERROR(INDEX(Modules!$C$5:$C$100,MATCH(F34,Modules!$A$5:$A$100,0)),"NOT FOUND")))))))) | H34: =IF(F34="","",IF(G34="NOT FOUND","—",IFERROR(INDEX(Listas!$J$5:$J$13,MATCH(LEFT(F34,FIND("-",F34)-1),Listas!$I$5:$I$13,0)),"Module / area"))) | I34: =IF(AND(B34="",F34=""),"",IF(OR(C34="NOT FOUND",G34="NOT FOUND"),"✖ ID inexistente",IF(B34=F34,"✖ Autorreferência",IF(E34="","✖ Sem relação","✔ OK"))))
C35: =IF(B35="","",IFERROR(INDEX('Constants & Enums'!$B$5:$B$200,MATCH(B35,'Constants & Enums'!$A$5:$A$200,0)),IFERROR(INDEX('Metrics & Formulas'!$B$5:$B$200,MATCH(B35,'Metrics & Formulas'!$A$5:$A$200,0)),IFERROR(INDEX('Projections & Dashboards'!$B$5:$B$200,MATCH(B35,'Projections & Dashboards'!$A$5:$A$200,0)),IFERROR(INDEX(Funções!$O$5:$O$300,MATCH(B35,Funções!$A$5:$A$300,0)),IFERROR(INDEX(Telas!$C$5:$C$400,MATCH(B35,Telas!$A$5:$A$400,0)),IFERROR(INDEX(Roadmap!$D$6:$D$200,MATCH(B35,Roadmap!$A$6:$A$200,0)),IFERROR(INDEX(Modules!$C$5:$C$100,MATCH(B35,Modules!$A$5:$A$100,0)),"NOT FOUND")))))))) | D35: =IF(B35="","",IF(C35="NOT FOUND","—",IFERROR(INDEX(Listas!$J$5:$J$13,MATCH(LEFT(B35,FIND("-",B35)-1),Listas!$I$5:$I$13,0)),"Module / area"))) | G35: =IF(F35="","",IFERROR(INDEX('Constants & Enums'!$B$5:$B$200,MATCH(F35,'Constants & Enums'!$A$5:$A$200,0)),IFERROR(INDEX('Metrics & Formulas'!$B$5:$B$200,MATCH(F35,'Metrics & Formulas'!$A$5:$A$200,0)),IFERROR(INDEX('Projections & Dashboards'!$B$5:$B$200,MATCH(F35,'Projections & Dashboards'!$A$5:$A$200,0)),IFERROR(INDEX(Funções!$O$5:$O$300,MATCH(F35,Funções!$A$5:$A$300,0)),IFERROR(INDEX(Telas!$C$5:$C$400,MATCH(F35,Telas!$A$5:$A$400,0)),IFERROR(INDEX(Roadmap!$D$6:$D$200,MATCH(F35,Roadmap!$A$6:$A$200,0)),IFERROR(INDEX(Modules!$C$5:$C$100,MATCH(F35,Modules!$A$5:$A$100,0)),"NOT FOUND")))))))) | H35: =IF(F35="","",IF(G35="NOT FOUND","—",IFERROR(INDEX(Listas!$J$5:$J$13,MATCH(LEFT(F35,FIND("-",F35)-1),Listas!$I$5:$I$13,0)),"Module / area"))) | I35: =IF(AND(B35="",F35=""),"",IF(OR(C35="NOT FOUND",G35="NOT FOUND"),"✖ ID inexistente",IF(B35=F35,"✖ Autorreferência",IF(E35="","✖ Sem relação","✔ OK"))))
C36: =IF(B36="","",IFERROR(INDEX('Constants & Enums'!$B$5:$B$200,MATCH(B36,'Constants & Enums'!$A$5:$A$200,0)),IFERROR(INDEX('Metrics & Formulas'!$B$5:$B$200,MATCH(B36,'Metrics & Formulas'!$A$5:$A$200,0)),IFERROR(INDEX('Projections & Dashboards'!$B$5:$B$200,MATCH(B36,'Projections & Dashboards'!$A$5:$A$200,0)),IFERROR(INDEX(Funções!$O$5:$O$300,MATCH(B36,Funções!$A$5:$A$300,0)),IFERROR(INDEX(Telas!$C$5:$C$400,MATCH(B36,Telas!$A$5:$A$400,0)),IFERROR(INDEX(Roadmap!$D$6:$D$200,MATCH(B36,Roadmap!$A$6:$A$200,0)),IFERROR(INDEX(Modules!$C$5:$C$100,MATCH(B36,Modules!$A$5:$A$100,0)),"NOT FOUND")))))))) | D36: =IF(B36="","",IF(C36="NOT FOUND","—",IFERROR(INDEX(Listas!$J$5:$J$13,MATCH(LEFT(B36,FIND("-",B36)-1),Listas!$I$5:$I$13,0)),"Module / area"))) | G36: =IF(F36="","",IFERROR(INDEX('Constants & Enums'!$B$5:$B$200,MATCH(F36,'Constants & Enums'!$A$5:$A$200,0)),IFERROR(INDEX('Metrics & Formulas'!$B$5:$B$200,MATCH(F36,'Metrics & Formulas'!$A$5:$A$200,0)),IFERROR(INDEX('Projections & Dashboards'!$B$5:$B$200,MATCH(F36,'Projections & Dashboards'!$A$5:$A$200,0)),IFERROR(INDEX(Funções!$O$5:$O$300,MATCH(F36,Funções!$A$5:$A$300,0)),IFERROR(INDEX(Telas!$C$5:$C$400,MATCH(F36,Telas!$A$5:$A$400,0)),IFERROR(INDEX(Roadmap!$D$6:$D$200,MATCH(F36,Roadmap!$A$6:$A$200,0)),IFERROR(INDEX(Modules!$C$5:$C$100,MATCH(F36,Modules!$A$5:$A$100,0)),"NOT FOUND")))))))) | H36: =IF(F36="","",IF(G36="NOT FOUND","—",IFERROR(INDEX(Listas!$J$5:$J$13,MATCH(LEFT(F36,FIND("-",F36)-1),Listas!$I$5:$I$13,0)),"Module / area"))) | I36: =IF(AND(B36="",F36=""),"",IF(OR(C36="NOT FOUND",G36="NOT FOUND"),"✖ ID inexistente",IF(B36=F36,"✖ Autorreferência",IF(E36="","✖ Sem relação","✔ OK"))))
